Workbook

Sheet Lisez-moi
A1: Opération Château v2 — Prévisionnels 10 ans
A2: Généré le 2026-10-14 par build_model.py à partir de hypotheses.py. Toutes les cellules de calcul sont des formules : modifiez les cellules jaunes (texte bleu) pour recalculer.
A3: Statuts des hypothèses (colonne D des blocs, colonne G des tableaux) : PL = page lue, EX = extrait de recherche, EST = estimation, INC = inconnu. Aucun financement, investisseur, vendeur ou subvention n'est acquis.
A4: Bien de référence : château + ~40-50 ha + écuries existantes à 2,5 M€ = médiane de 19 annonces de châteaux ≥ 30 ha (agent 1, pages lues). Exemple réel le plus proche : Ygrande (03), 2,65 M€, 40,7 ha, 24 boxes, manège, 16 chambres (vente SAFER, page lue).
A5: Scénario A — Château équestre « sport » : pension travail avec cavalier professionnel, valorisation et vente de jeunes chevaux, concours, pension premium. Financement bancaire classique (apport 1 M€).
A6: Scénario B — Château multiactivité : pension premium + pré + retraite, mariages plafonnés, gîte, séminaires, tournages. Financement bancaire classique (apport 1 M€).
A7: Variantes de financement de B : B_club_deal (apport 250 k€ + investisseurs majoritaires), B_credit_vendeur (apport 250 k€ + crédit-vendeur 1,5 M€), B_sans_dette (diagnostic de l'exploitation seule).
A8: Scénario C — Le capital d'abord : holding de reprise de PME 2026-2030, achat en année 5 (2031) presque sans dette, exploitation frugale. Les fonds propres viennent de la holding (NON acquis). C_holding_realiste : la holding n'apporte que ce qu'une reprise unique dégage. Feuilles H1-H3 : moteur de capital (ce que 1 à 3 reprises de PME produisent réellement).
A9: Scénario E — Bail emphytéotique : contrôle d'un domaine public pendant 50-99 ans sans propriété ; travaux à la charge du preneur ; redevance INCONNUE ; aucune valeur de sortie (améliorations au bailleur).
A10: Cas prudent / optimiste : dérivés du central (volumes, prix, charges, travaux, montée en charge) — voir Sources_hypotheses. Stress tests (feuilles S_*) : appliqués aux configurations non déficitaires.
A11: Simplifications : IS 25 % sans taux réduit ni plafonnement des déficits ; montants HT ; amortissements bâti 30 ans / travaux 15 ans ; pas de dividendes avant la sortie ; valeur de sortie = % du coût historique moins frais de cession ; loyer privé du fondateur hors CA d'exploitation.
A12: Verdict : VIABLE si trésorerie jamais négative, trésorerie an 10 ≥ réserve, DSCR (après gros entretien) ≥ 1,2 et cash-flow libre ≥ 0 dès la 2e année d'exploitation, TRI des investisseurs extérieurs ≥ 6 % et dirigeant payé par le domaine. NON AUTOFINANCÉ si tout passe sauf la rémunération du dirigeant. Sinon FRAGILE ou NON VIABLE.
A13: Corrections après audit (agent 8) : loyer privé retiré ; prix de pension ramenés au 3e quartile hors IdF (box 450 € TTC) ; 3 ETP pour ~54 équidés ; assurance 12 k€ ; gros entretien sur bâti + travaux ; IS 15 %/25 % ; crédit-vendeur aux conditions de marché ; prêts d'honneur comptés en dette ; C négocié limité à −20 % sur le prix ; valeur de sortie hors gros entretien ; indexation des charges = prix.

Sheet Comparaison
A1: Comparaison des scénarios et stress tests (valeurs liées aux feuilles)
A3: Feuille | B3: Emplois totaux | C3: Ressources prévues | D3: CA an 5 | E3: EBITDA an 5 | F3: EBITDA an 10 | G3: Part équestre CA an 5 | H3: Trésorerie min. | I3: Trésorerie an 10 | J3: DSCR min. (exploitation an 2+) | K3: Années FCF < 0 (exploitation an 2+) | L3: Dette soutenable | M3: Fonds propres nécessaires | N3: TRI investisseurs | O3: TRI fondateur | P3: Capital fondateur | Q3: Votes fondateur | R3: Verdict
A4: A_central | B4: ='A_central'!$B$184 | C4: ='A_central'!$B$185 | D4: ='A_central'!$B$186 | E4: ='A_central'!$B$187 | F4: ='A_central'!$B$188 | G4: ='A_central'!$B$189 | H4: ='A_central'!$B$190 | I4: ='A_central'!$B$191 | J4: ='A_central'!$B$192 | K4: ='A_central'!$B$193 | L4: ='A_central'!$B$196 | M4: ='A_central'!$B$197 | N4: ='A_central'!$B$194 | O4: ='A_central'!$B$195 | P4: ='A_central'!$B$198 | Q4: ='A_central'!$B$199 | R4: ='A_central'!$B$200
A5: A_prudent | B5: ='A_prudent'!$B$184 | C5: ='A_prudent'!$B$185 | D5: ='A_prudent'!$B$186 | E5: ='A_prudent'!$B$187 | F5: ='A_prudent'!$B$188 | G5: ='A_prudent'!$B$189 | H5: ='A_prudent'!$B$190 | I5: ='A_prudent'!$B$191 | J5: ='A_prudent'!$B$192 | K5: ='A_prudent'!$B$193 | L5: ='A_prudent'!$B$196 | M5: ='A_prudent'!$B$197 | N5: ='A_prudent'!$B$194 | O5: ='A_prudent'!$B$195 | P5: ='A_prudent'!$B$198 | Q5: ='A_prudent'!$B$199 | R5: ='A_prudent'!$B$200
A6: A_optimiste | B6: ='A_optimiste'!$B$184 | C6: ='A_optimiste'!$B$185 | D6: ='A_optimiste'!$B$186 | E6: ='A_optimiste'!$B$187 | F6: ='A_optimiste'!$B$188 | G6: ='A_optimiste'!$B$189 | H6: ='A_optimiste'!$B$190 | I6: ='A_optimiste'!$B$191 | J6: ='A_optimiste'!$B$192 | K6: ='A_optimiste'!$B$193 | L6: ='A_optimiste'!$B$196 | M6: ='A_optimiste'!$B$197 | N6: ='A_optimiste'!$B$194 | O6: ='A_optimiste'!$B$195 | P6: ='A_optimiste'!$B$198 | Q6: ='A_optimiste'!$B$199 | R6: ='A_optimiste'!$B$200
A7: B_central | B7: ='B_central'!$B$180 | C7: ='B_central'!$B$181 | D7: ='B_central'!$B$182 | E7: ='B_central'!$B$183 | F7: ='B_central'!$B$184 | G7: ='B_central'!$B$185 | H7: ='B_central'!$B$186 | I7: ='B_central'!$B$187 | J7: ='B_central'!$B$188 | K7: ='B_central'!$B$189 | L7: ='B_central'!$B$192 | M7: ='B_central'!$B$193 | N7: ='B_central'!$B$190 | O7: ='B_central'!$B$191 | P7: ='B_central'!$B$194 | Q7: ='B_central'!$B$195 | R7: ='B_central'!$B$196
A8: B_prudent | B8: ='B_prudent'!$B$180 | C8: ='B_prudent'!$B$181 | D8: ='B_prudent'!$B$182 | E8: ='B_prudent'!$B$183 | F8: ='B_prudent'!$B$184 | G8: ='B_prudent'!$B$185 | H8: ='B_prudent'!$B$186 | I8: ='B_prudent'!$B$187 | J8: ='B_prudent'!$B$188 | K8: ='B_prudent'!$B$189 | L8: ='B_prudent'!$B$192 | M8: ='B_prudent'!$B$193 | N8: ='B_prudent'!$B$190 | O8: ='B_prudent'!$B$191 | P8: ='B_prudent'!$B$194 | Q8: ='B_prudent'!$B$195 | R8: ='B_prudent'!$B$196
A9: B_optimiste | B9: ='B_optimiste'!$B$180 | C9: ='B_optimiste'!$B$181 | D9: ='B_optimiste'!$B$182 | E9: ='B_optimiste'!$B$183 | F9: ='B_optimiste'!$B$184 | G9: ='B_optimiste'!$B$185 | H9: ='B_optimiste'!$B$186 | I9: ='B_optimiste'!$B$187 | J9: ='B_optimiste'!$B$188 | K9: ='B_optimiste'!$B$189 | L9: ='B_optimiste'!$B$192 | M9: ='B_optimiste'!$B$193 | N9: ='B_optimiste'!$B$190 | O9: ='B_optimiste'!$B$191 | P9: ='B_optimiste'!$B$194 | Q9: ='B_optimiste'!$B$195 | R9: ='B_optimiste'!$B$196
A10: B_club_deal | B10: ='B_club_deal'!$B$180 | C10: ='B_club_deal'!$B$181 | D10: ='B_club_deal'!$B$182 | E10: ='B_club_deal'!$B$183 | F10: ='B_club_deal'!$B$184 | G10: ='B_club_deal'!$B$185 | H10: ='B_club_deal'!$B$186 | I10: ='B_club_deal'!$B$187 | J10: ='B_club_deal'!$B$188 | K10: ='B_club_deal'!$B$189 | L10: ='B_club_deal'!$B$192 | M10: ='B_club_deal'!$B$193 | N10: ='B_club_deal'!$B$190 | O10: ='B_club_deal'!$B$191 | P10: ='B_club_deal'!$B$194 | Q10: ='B_club_deal'!$B$195 | R10: ='B_club_deal'!$B$196
A11: B_credit_vendeur | B11: ='B_credit_vendeur'!$B$180 | C11: ='B_credit_vendeur'!$B$181 | D11: ='B_credit_vendeur'!$B$182 | E11: ='B_credit_vendeur'!$B$183 | F11: ='B_credit_vendeur'!$B$184 | G11: ='B_credit_vendeur'!$B$185 | H11: ='B_credit_vendeur'!$B$186 | I11: ='B_credit_vendeur'!$B$187 | J11: ='B_credit_vendeur'!$B$188 | K11: ='B_credit_vendeur'!$B$189 | L11: ='B_credit_vendeur'!$B$192 | M11: ='B_credit_vendeur'!$B$193 | N11: ='B_credit_vendeur'!$B$190 | O11: ='B_credit_vendeur'!$B$191 | P11: ='B_credit_vendeur'!$B$194 | Q11: ='B_credit_vendeur'!$B$195 | R11: ='B_credit_vendeur'!$B$196
A12: B_sans_dette | B12: ='B_sans_dette'!$B$180 | C12: ='B_sans_dette'!$B$181 | D12: ='B_sans_dette'!$B$182 | E12: ='B_sans_dette'!$B$183 | F12: ='B_sans_dette'!$B$184 | G12: ='B_sans_dette'!$B$185 | H12: ='B_sans_dette'!$B$186 | I12: ='B_sans_dette'!$B$187 | J12: ='B_sans_dette'!$B$188 | K12: ='B_sans_dette'!$B$189 | L12: ='B_sans_dette'!$B$192 | M12: ='B_sans_dette'!$B$193 | N12: ='B_sans_dette'!$B$190 | O12: ='B_sans_dette'!$B$191 | P12: ='B_sans_dette'!$B$194 | Q12: ='B_sans_dette'!$B$195 | R12: ='B_sans_dette'!$B$196
A13: B_frugal | B13: ='B_frugal'!$B$178 | C13: ='B_frugal'!$B$179 | D13: ='B_frugal'!$B$180 | E13: ='B_frugal'!$B$181 | F13: ='B_frugal'!$B$182 | G13: ='B_frugal'!$B$183 | H13: ='B_frugal'!$B$184 | I13: ='B_frugal'!$B$185 | J13: ='B_frugal'!$B$186 | K13: ='B_frugal'!$B$187 | L13: ='B_frugal'!$B$190 | M13: ='B_frugal'!$B$191 | N13: ='B_frugal'!$B$188 | O13: ='B_frugal'!$B$189 | P13: ='B_frugal'!$B$192 | Q13: ='B_frugal'!$B$193 | R13: ='B_frugal'!$B$194
A14: B_frugal_sans_dette | B14: ='B_frugal_sans_dette'!$B$178 | C14: ='B_frugal_sans_dette'!$B$179 | D14: ='B_frugal_sans_dette'!$B$180 | E14: ='B_frugal_sans_dette'!$B$181 | F14: ='B_frugal_sans_dette'!$B$182 | G14: ='B_frugal_sans_dette'!$B$183 | H14: ='B_frugal_sans_dette'!$B$184 | I14: ='B_frugal_sans_dette'!$B$185 | J14: ='B_frugal_sans_dette'!$B$186 | K14: ='B_frugal_sans_dette'!$B$187 | L14: ='B_frugal_sans_dette'!$B$190 | M14: ='B_frugal_sans_dette'!$B$191 | N14: ='B_frugal_sans_dette'!$B$188 | O14: ='B_frugal_sans_dette'!$B$189 | P14: ='B_frugal_sans_dette'!$B$192 | Q14: ='B_frugal_sans_dette'!$B$193 | R14: ='B_frugal_sans_dette'!$B$194
A15: A_frugal | B15: ='A_frugal'!$B$180 | C15: ='A_frugal'!$B$181 | D15: ='A_frugal'!$B$182 | E15: ='A_frugal'!$B$183 | F15: ='A_frugal'!$B$184 | G15: ='A_frugal'!$B$185 | H15: ='A_frugal'!$B$186 | I15: ='A_frugal'!$B$187 | J15: ='A_frugal'!$B$188 | K15: ='A_frugal'!$B$189 | L15: ='A_frugal'!$B$192 | M15: ='A_frugal'!$B$193 | N15: ='A_frugal'!$B$190 | O15: ='A_frugal'!$B$191 | P15: ='A_frugal'!$B$194 | Q15: ='A_frugal'!$B$195 | R15: ='A_frugal'!$B$196
A16: C_central | B16: ='C_central'!$B$178 | C16: ='C_central'!$B$179 | D16: ='C_central'!$B$180 | E16: ='C_central'!$B$181 | F16: ='C_central'!$B$182 | G16: ='C_central'!$B$183 | H16: ='C_central'!$B$184 | I16: ='C_central'!$B$185 | J16: ='C_central'!$B$186 | K16: ='C_central'!$B$187 | L16: ='C_central'!$B$190 | M16: ='C_central'!$B$191 | N16: ='C_central'!$B$188 | O16: ='C_central'!$B$189 | P16: ='C_central'!$B$192 | Q16: ='C_central'!$B$193 | R16: ='C_central'!$B$194
A17: C_prudent | B17: ='C_prudent'!$B$178 | C17: ='C_prudent'!$B$179 | D17: ='C_prudent'!$B$180 | E17: ='C_prudent'!$B$181 | F17: ='C_prudent'!$B$182 | G17: ='C_prudent'!$B$183 | H17: ='C_prudent'!$B$184 | I17: ='C_prudent'!$B$185 | J17: ='C_prudent'!$B$186 | K17: ='C_prudent'!$B$187 | L17: ='C_prudent'!$B$190 | M17: ='C_prudent'!$B$191 | N17: ='C_prudent'!$B$188 | O17: ='C_prudent'!$B$189 | P17: ='C_prudent'!$B$192 | Q17: ='C_prudent'!$B$193 | R17: ='C_prudent'!$B$194
A18: C_optimiste | B18: ='C_optimiste'!$B$178 | C18: ='C_optimiste'!$B$179 | D18: ='C_optimiste'!$B$180 | E18: ='C_optimiste'!$B$181 | F18: ='C_optimiste'!$B$182 | G18: ='C_optimiste'!$B$183 | H18: ='C_optimiste'!$B$184 | I18: ='C_optimiste'!$B$185 | J18: ='C_optimiste'!$B$186 | K18: ='C_optimiste'!$B$187 | L18: ='C_optimiste'!$B$190 | M18: ='C_optimiste'!$B$191 | N18: ='C_optimiste'!$B$188 | O18: ='C_optimiste'!$B$189 | P18: ='C_optimiste'!$B$192 | Q18: ='C_optimiste'!$B$193 | R18: ='C_optimiste'!$B$194
A19: C_negocie | B19: ='C_negocie'!$B$178 | C19: ='C_negocie'!$B$179 | D19: ='C_negocie'!$B$180 | E19: ='C_negocie'!$B$181 | F19: ='C_negocie'!$B$182 | G19: ='C_negocie'!$B$183 | H19: ='C_negocie'!$B$184 | I19: ='C_negocie'!$B$185 | J19: ='C_negocie'!$B$186 | K19: ='C_negocie'!$B$187 | L19: ='C_negocie'!$B$190 | M19: ='C_negocie'!$B$191 | N19: ='C_negocie'!$B$188 | O19: ='C_negocie'!$B$189 | P19: ='C_negocie'!$B$192 | Q19: ='C_negocie'!$B$193 | R19: ='C_negocie'!$B$194
A20: C_holding_realiste | B20: ='C_holding_realiste'!$B$178 | C20: ='C_holding_realiste'!$B$179 | D20: ='C_holding_realiste'!$B$180 | E20: ='C_holding_realiste'!$B$181 | F20: ='C_holding_realiste'!$B$182 | G20: ='C_holding_realiste'!$B$183 | H20: ='C_holding_realiste'!$B$184 | I20: ='C_holding_realiste'!$B$185 | J20: ='C_holding_realiste'!$B$186 | K20: ='C_holding_realiste'!$B$187 | L20: ='C_holding_realiste'!$B$190 | M20: ='C_holding_realiste'!$B$191 | N20: ='C_holding_realiste'!$B$188 | O20: ='C_holding_realiste'!$B$189 | P20: ='C_holding_realiste'!$B$192 | Q20: ='C_holding_realiste'!$B$193 | R20: ='C_holding_realiste'!$B$194
A21: D_chateau_modeste | B21: ='D_chateau_modeste'!$B$176 | C21: ='D_chateau_modeste'!$B$177 | D21: ='D_chateau_modeste'!$B$178 | E21: ='D_chateau_modeste'!$B$179 | F21: ='D_chateau_modeste'!$B$180 | G21: ='D_chateau_modeste'!$B$181 | H21: ='D_chateau_modeste'!$B$182 | I21: ='D_chateau_modeste'!$B$183 | J21: ='D_chateau_modeste'!$B$184 | K21: ='D_chateau_modeste'!$B$185 | L21: ='D_chateau_modeste'!$B$188 | M21: ='D_chateau_modeste'!$B$189 | N21: ='D_chateau_modeste'!$B$186 | O21: ='D_chateau_modeste'!$B$187 | P21: ='D_chateau_modeste'!$B$190 | Q21: ='D_chateau_modeste'!$B$191 | R21: ='D_chateau_modeste'!$B$192
A22: E_bail_emphyteotique | B22: ='E_bail_emphyteotique'!$B$180 | C22: ='E_bail_emphyteotique'!$B$181 | D22: ='E_bail_emphyteotique'!$B$182 | E22: ='E_bail_emphyteotique'!$B$183 | F22: ='E_bail_emphyteotique'!$B$184 | G22: ='E_bail_emphyteotique'!$B$185 | H22: ='E_bail_emphyteotique'!$B$186 | I22: ='E_bail_emphyteotique'!$B$187 | J22: ='E_bail_emphyteotique'!$B$188 | K22: ='E_bail_emphyteotique'!$B$189 | L22: ='E_bail_emphyteotique'!$B$192 | M22: ='E_bail_emphyteotique'!$B$193 | N22: ='E_bail_emphyteotique'!$B$190 | O22: ='E_bail_emphyteotique'!$B$191 | P22: ='E_bail_emphyteotique'!$B$194 | Q22: ='E_bail_emphyteotique'!$B$195 | R22: ='E_bail_emphyteotique'!$B$196
A23: E_allege | B23: ='E_allege'!$B$180 | C23: ='E_allege'!$B$181 | D23: ='E_allege'!$B$182 | E23: ='E_allege'!$B$183 | F23: ='E_allege'!$B$184 | G23: ='E_allege'!$B$185 | H23: ='E_allege'!$B$186 | I23: ='E_allege'!$B$187 | J23: ='E_allege'!$B$188 | K23: ='E_allege'!$B$189 | L23: ='E_allege'!$B$192 | M23: ='E_allege'!$B$193 | N23: ='E_allege'!$B$190 | O23: ='E_allege'!$B$191 | P23: ='E_allege'!$B$194 | Q23: ='E_allege'!$B$195 | R23: ='E_allege'!$B$196
A24: S_Cc_CA-30 | B24: ='S_Cc_CA-30'!$B$178 | C24: ='S_Cc_CA-30'!$B$179 | D24: ='S_Cc_CA-30'!$B$180 | E24: ='S_Cc_CA-30'!$B$181 | F24: ='S_Cc_CA-30'!$B$182 | G24: ='S_Cc_CA-30'!$B$183 | H24: ='S_Cc_CA-30'!$B$184 | I24: ='S_Cc_CA-30'!$B$185 | J24: ='S_Cc_CA-30'!$B$186 | K24: ='S_Cc_CA-30'!$B$187 | L24: ='S_Cc_CA-30'!$B$190 | M24: ='S_Cc_CA-30'!$B$191 | N24: ='S_Cc_CA-30'!$B$188 | O24: ='S_Cc_CA-30'!$B$189 | P24: ='S_Cc_CA-30'!$B$192 | Q24: ='S_Cc_CA-30'!$B$193 | R24: ='S_Cc_CA-30'!$B$194
A25: S_Cc_Travaux+30 | B25: ='S_Cc_Travaux+30'!$B$178 | C25: ='S_Cc_Travaux+30'!$B$179 | D25: ='S_Cc_Travaux+30'!$B$180 | E25: ='S_Cc_Travaux+30'!$B$181 | F25: ='S_Cc_Travaux+30'!$B$182 | G25: ='S_Cc_Travaux+30'!$B$183 | H25: ='S_Cc_Travaux+30'!$B$184 | I25: ='S_Cc_Travaux+30'!$B$185 | J25: ='S_Cc_Travaux+30'!$B$186 | K25: ='S_Cc_Travaux+30'!$B$187 | L25: ='S_Cc_Travaux+30'!$B$190 | M25: ='S_Cc_Travaux+30'!$B$191 | N25: ='S_Cc_Travaux+30'!$B$188 | O25: ='S_Cc_Travaux+30'!$B$189 | P25: ='S_Cc_Travaux+30'!$B$192 | Q25: ='S_Cc_Travaux+30'!$B$193 | R25: ='S_Cc_Travaux+30'!$B$194
A26: S_Cc_Retard12m | B26: ='S_Cc_Retard12m'!$B$178 | C26: ='S_Cc_Retard12m'!$B$179 | D26: ='S_Cc_Retard12m'!$B$180 | E26: ='S_Cc_Retard12m'!$B$181 | F26: ='S_Cc_Retard12m'!$B$182 | G26: ='S_Cc_Retard12m'!$B$183 | H26: ='S_Cc_Retard12m'!$B$184 | I26: ='S_Cc_Retard12m'!$B$185 | J26: ='S_Cc_Retard12m'!$B$186 | K26: ='S_Cc_Retard12m'!$B$187 | L26: ='S_Cc_Retard12m'!$B$190 | M26: ='S_Cc_Retard12m'!$B$191 | N26: ='S_Cc_Retard12m'!$B$188 | O26: ='S_Cc_Retard12m'!$B$189 | P26: ='S_Cc_Retard12m'!$B$192 | Q26: ='S_Cc_Retard12m'!$B$193 | R26: ='S_Cc_Retard12m'!$B$194
A27: S_Cc_Taux+2pts | B27: ='S_Cc_Taux+2pts'!$B$178 | C27: ='S_Cc_Taux+2pts'!$B$179 | D27: ='S_Cc_Taux+2pts'!$B$180 | E27: ='S_Cc_Taux+2pts'!$B$181 | F27: ='S_Cc_Taux+2pts'!$B$182 | G27: ='S_Cc_Taux+2pts'!$B$183 | H27: ='S_Cc_Taux+2pts'!$B$184 | I27: ='S_Cc_Taux+2pts'!$B$185 | J27: ='S_Cc_Taux+2pts'!$B$186 | K27: ='S_Cc_Taux+2pts'!$B$187 | L27: ='S_Cc_Taux+2pts'!$B$190 | M27: ='S_Cc_Taux+2pts'!$B$191 | N27: ='S_Cc_Taux+2pts'!$B$188 | O27: ='S_Cc_Taux+2pts'!$B$189 | P27: ='S_Cc_Taux+2pts'!$B$192 | Q27: ='S_Cc_Taux+2pts'!$B$193 | R27: ='S_Cc_Taux+2pts'!$B$194
A28: S_Cc_RetraitFP50 | B28: ='S_Cc_RetraitFP50'!$B$178 | C28: ='S_Cc_RetraitFP50'!$B$179 | D28: ='S_Cc_RetraitFP50'!$B$180 | E28: ='S_Cc_RetraitFP50'!$B$181 | F28: ='S_Cc_RetraitFP50'!$B$182 | G28: ='S_Cc_RetraitFP50'!$B$183 | H28: ='S_Cc_RetraitFP50'!$B$184 | I28: ='S_Cc_RetraitFP50'!$B$185 | J28: ='S_Cc_RetraitFP50'!$B$186 | K28: ='S_Cc_RetraitFP50'!$B$187 | L28: ='S_Cc_RetraitFP50'!$B$190 | M28: ='S_Cc_RetraitFP50'!$B$191 | N28: ='S_Cc_RetraitFP50'!$B$188 | O28: ='S_Cc_RetraitFP50'!$B$189 | P28: ='S_Cc_RetraitFP50'!$B$192 | Q28: ='S_Cc_RetraitFP50'!$B$193 | R28: ='S_Cc_RetraitFP50'!$B$194
A29: S_Cc_Annul40evt | B29: ='S_Cc_Annul40evt'!$B$178 | C29: ='S_Cc_Annul40evt'!$B$179 | D29: ='S_Cc_Annul40evt'!$B$180 | E29: ='S_Cc_Annul40evt'!$B$181 | F29: ='S_Cc_Annul40evt'!$B$182 | G29: ='S_Cc_Annul40evt'!$B$183 | H29: ='S_Cc_Annul40evt'!$B$184 | I29: ='S_Cc_Annul40evt'!$B$185 | J29: ='S_Cc_Annul40evt'!$B$186 | K29: ='S_Cc_Annul40evt'!$B$187 | L29: ='S_Cc_Annul40evt'!$B$190 | M29: ='S_Cc_Annul40evt'!$B$191 | N29: ='S_Cc_Annul40evt'!$B$188 | O29: ='S_Cc_Annul40evt'!$B$189 | P29: ='S_Cc_Annul40evt'!$B$192 | Q29: ='S_Cc_Annul40evt'!$B$193 | R29: ='S_Cc_Annul40evt'!$B$194
A30: S_Cc_Cumul | B30: ='S_Cc_Cumul'!$B$178 | C30: ='S_Cc_Cumul'!$B$179 | D30: ='S_Cc_Cumul'!$B$180 | E30: ='S_Cc_Cumul'!$B$181 | F30: ='S_Cc_Cumul'!$B$182 | G30: ='S_Cc_Cumul'!$B$183 | H30: ='S_Cc_Cumul'!$B$184 | I30: ='S_Cc_Cumul'!$B$185 | J30: ='S_Cc_Cumul'!$B$186 | K30: ='S_Cc_Cumul'!$B$187 | L30: ='S_Cc_Cumul'!$B$190 | M30: ='S_Cc_Cumul'!$B$191 | N30: ='S_Cc_Cumul'!$B$188 | O30: ='S_Cc_Cumul'!$B$189 | P30: ='S_Cc_Cumul'!$B$192 | Q30: ='S_Cc_Cumul'!$B$193 | R30: ='S_Cc_Cumul'!$B$194
A31: S_Cn_CA-30 | B31: ='S_Cn_CA-30'!$B$178 | C31: ='S_Cn_CA-30'!$B$179 | D31: ='S_Cn_CA-30'!$B$180 | E31: ='S_Cn_CA-30'!$B$181 | F31: ='S_Cn_CA-30'!$B$182 | G31: ='S_Cn_CA-30'!$B$183 | H31: ='S_Cn_CA-30'!$B$184 | I31: ='S_Cn_CA-30'!$B$185 | J31: ='S_Cn_CA-30'!$B$186 | K31: ='S_Cn_CA-30'!$B$187 | L31: ='S_Cn_CA-30'!$B$190 | M31: ='S_Cn_CA-30'!$B$191 | N31: ='S_Cn_CA-30'!$B$188 | O31: ='S_Cn_CA-30'!$B$189 | P31: ='S_Cn_CA-30'!$B$192 | Q31: ='S_Cn_CA-30'!$B$193 | R31: ='S_Cn_CA-30'!$B$194
A32: S_Cn_Travaux+30 | B32: ='S_Cn_Travaux+30'!$B$178 | C32: ='S_Cn_Travaux+30'!$B$179 | D32: ='S_Cn_Travaux+30'!$B$180 | E32: ='S_Cn_Travaux+30'!$B$181 | F32: ='S_Cn_Travaux+30'!$B$182 | G32: ='S_Cn_Travaux+30'!$B$183 | H32: ='S_Cn_Travaux+30'!$B$184 | I32: ='S_Cn_Travaux+30'!$B$185 | J32: ='S_Cn_Travaux+30'!$B$186 | K32: ='S_Cn_Travaux+30'!$B$187 | L32: ='S_Cn_Travaux+30'!$B$190 | M32: ='S_Cn_Travaux+30'!$B$191 | N32: ='S_Cn_Travaux+30'!$B$188 | O32: ='S_Cn_Travaux+30'!$B$189 | P32: ='S_Cn_Travaux+30'!$B$192 | Q32: ='S_Cn_Travaux+30'!$B$193 | R32: ='S_Cn_Travaux+30'!$B$194
A33: S_Cn_Retard12m | B33: ='S_Cn_Retard12m'!$B$178 | C33: ='S_Cn_Retard12m'!$B$179 | D33: ='S_Cn_Retard12m'!$B$180 | E33: ='S_Cn_Retard12m'!$B$181 | F33: ='S_Cn_Retard12m'!$B$182 | G33: ='S_Cn_Retard12m'!$B$183 | H33: ='S_Cn_Retard12m'!$B$184 | I33: ='S_Cn_Retard12m'!$B$185 | J33: ='S_Cn_Retard12m'!$B$186 | K33: ='S_Cn_Retard12m'!$B$187 | L33: ='S_Cn_Retard12m'!$B$190 | M33: ='S_Cn_Retard12m'!$B$191 | N33: ='S_Cn_Retard12m'!$B$188 | O33: ='S_Cn_Retard12m'!$B$189 | P33: ='S_Cn_Retard12m'!$B$192 | Q33: ='S_Cn_Retard12m'!$B$193 | R33: ='S_Cn_Retard12m'!$B$194
A34: S_Cn_Taux+2pts | B34: ='S_Cn_Taux+2pts'!$B$178 | C34: ='S_Cn_Taux+2pts'!$B$179 | D34: ='S_Cn_Taux+2pts'!$B$180 | E34: ='S_Cn_Taux+2pts'!$B$181 | F34: ='S_Cn_Taux+2pts'!$B$182 | G34: ='S_Cn_Taux+2pts'!$B$183 | H34: ='S_Cn_Taux+2pts'!$B$184 | I34: ='S_Cn_Taux+2pts'!$B$185 | J34: ='S_Cn_Taux+2pts'!$B$186 | K34: ='S_Cn_Taux+2pts'!$B$187 | L34: ='S_Cn_Taux+2pts'!$B$190 | M34: ='S_Cn_Taux+2pts'!$B$191 | N34: ='S_Cn_Taux+2pts'!$B$188 | O34: ='S_Cn_Taux+2pts'!$B$189 | P34: ='S_Cn_Taux+2pts'!$B$192 | Q34: ='S_Cn_Taux+2pts'!$B$193 | R34: ='S_Cn_Taux+2pts'!$B$194
A35: S_Cn_RetraitFP50 | B35: ='S_Cn_RetraitFP50'!$B$178 | C35: ='S_Cn_RetraitFP50'!$B$179 | D35: ='S_Cn_RetraitFP50'!$B$180 | E35: ='S_Cn_RetraitFP50'!$B$181 | F35: ='S_Cn_RetraitFP50'!$B$182 | G35: ='S_Cn_RetraitFP50'!$B$183 | H35: ='S_Cn_RetraitFP50'!$B$184 | I35: ='S_Cn_RetraitFP50'!$B$185 | J35: ='S_Cn_RetraitFP50'!$B$186 | K35: ='S_Cn_RetraitFP50'!$B$187 | L35: ='S_Cn_RetraitFP50'!$B$190 | M35: ='S_Cn_RetraitFP50'!$B$191 | N35: ='S_Cn_RetraitFP50'!$B$188 | O35: ='S_Cn_RetraitFP50'!$B$189 | P35: ='S_Cn_RetraitFP50'!$B$192 | Q35: ='S_Cn_RetraitFP50'!$B$193 | R35: ='S_Cn_RetraitFP50'!$B$194
A36: S_Cn_Annul40evt | B36: ='S_Cn_Annul40evt'!$B$178 | C36: ='S_Cn_Annul40evt'!$B$179 | D36: ='S_Cn_Annul40evt'!$B$180 | E36: ='S_Cn_Annul40evt'!$B$181 | F36: ='S_Cn_Annul40evt'!$B$182 | G36: ='S_Cn_Annul40evt'!$B$183 | H36: ='S_Cn_Annul40evt'!$B$184 | I36: ='S_Cn_Annul40evt'!$B$185 | J36: ='S_Cn_Annul40evt'!$B$186 | K36: ='S_Cn_Annul40evt'!$B$187 | L36: ='S_Cn_Annul40evt'!$B$190 | M36: ='S_Cn_Annul40evt'!$B$191 | N36: ='S_Cn_Annul40evt'!$B$188 | O36: ='S_Cn_Annul40evt'!$B$189 | P36: ='S_Cn_Annul40evt'!$B$192 | Q36: ='S_Cn_Annul40evt'!$B$193 | R36: ='S_Cn_Annul40evt'!$B$194
A37: S_Cn_Cumul | B37: ='S_Cn_Cumul'!$B$178 | C37: ='S_Cn_Cumul'!$B$179 | D37: ='S_Cn_Cumul'!$B$180 | E37: ='S_Cn_Cumul'!$B$181 | F37: ='S_Cn_Cumul'!$B$182 | G37: ='S_Cn_Cumul'!$B$183 | H37: ='S_Cn_Cumul'!$B$184 | I37: ='S_Cn_Cumul'!$B$185 | J37: ='S_Cn_Cumul'!$B$186 | K37: ='S_Cn_Cumul'!$B$187 | L37: ='S_Cn_Cumul'!$B$190 | M37: ='S_Cn_Cumul'!$B$191 | N37: ='S_Cn_Cumul'!$B$188 | O37: ='S_Cn_Cumul'!$B$189 | P37: ='S_Cn_Cumul'!$B$192 | Q37: ='S_Cn_Cumul'!$B$193 | R37: ='S_Cn_Cumul'!$B$194
A38: S_Bfsd_CA-30 | B38: ='S_Bfsd_CA-30'!$B$178 | C38: ='S_Bfsd_CA-30'!$B$179 | D38: ='S_Bfsd_CA-30'!$B$180 | E38: ='S_Bfsd_CA-30'!$B$181 | F38: ='S_Bfsd_CA-30'!$B$182 | G38: ='S_Bfsd_CA-30'!$B$183 | H38: ='S_Bfsd_CA-30'!$B$184 | I38: ='S_Bfsd_CA-30'!$B$185 | J38: ='S_Bfsd_CA-30'!$B$186 | K38: ='S_Bfsd_CA-30'!$B$187 | L38: ='S_Bfsd_CA-30'!$B$190 | M38: ='S_Bfsd_CA-30'!$B$191 | N38: ='S_Bfsd_CA-30'!$B$188 | O38: ='S_Bfsd_CA-30'!$B$189 | P38: ='S_Bfsd_CA-30'!$B$192 | Q38: ='S_Bfsd_CA-30'!$B$193 | R38: ='S_Bfsd_CA-30'!$B$194
A39: S_Bfsd_Travaux+30 | B39: ='S_Bfsd_Travaux+30'!$B$178 | C39: ='S_Bfsd_Travaux+30'!$B$179 | D39: ='S_Bfsd_Travaux+30'!$B$180 | E39: ='S_Bfsd_Travaux+30'!$B$181 | F39: ='S_Bfsd_Travaux+30'!$B$182 | G39: ='S_Bfsd_Travaux+30'!$B$183 | H39: ='S_Bfsd_Travaux+30'!$B$184 | I39: ='S_Bfsd_Travaux+30'!$B$185 | J39: ='S_Bfsd_Travaux+30'!$B$186 | K39: ='S_Bfsd_Travaux+30'!$B$187 | L39: ='S_Bfsd_Travaux+30'!$B$190 | M39: ='S_Bfsd_Travaux+30'!$B$191 | N39: ='S_Bfsd_Travaux+30'!$B$188 | O39: ='S_Bfsd_Travaux+30'!$B$189 | P39: ='S_Bfsd_Travaux+30'!$B$192 | Q39: ='S_Bfsd_Travaux+30'!$B$193 | R39: ='S_Bfsd_Travaux+30'!$B$194
A40: S_Bfsd_Retard12m | B40: ='S_Bfsd_Retard12m'!$B$178 | C40: ='S_Bfsd_Retard12m'!$B$179 | D40: ='S_Bfsd_Retard12m'!$B$180 | E40: ='S_Bfsd_Retard12m'!$B$181 | F40: ='S_Bfsd_Retard12m'!$B$182 | G40: ='S_Bfsd_Retard12m'!$B$183 | H40: ='S_Bfsd_Retard12m'!$B$184 | I40: ='S_Bfsd_Retard12m'!$B$185 | J40: ='S_Bfsd_Retard12m'!$B$186 | K40: ='S_Bfsd_Retard12m'!$B$187 | L40: ='S_Bfsd_Retard12m'!$B$190 | M40: ='S_Bfsd_Retard12m'!$B$191 | N40: ='S_Bfsd_Retard12m'!$B$188 | O40: ='S_Bfsd_Retard12m'!$B$189 | P40: ='S_Bfsd_Retard12m'!$B$192 | Q40: ='S_Bfsd_Retard12m'!$B$193 | R40: ='S_Bfsd_Retard12m'!$B$194
A41: S_Bfsd_Taux+2pts | B41: ='S_Bfsd_Taux+2pts'!$B$178 | C41: ='S_Bfsd_Taux+2pts'!$B$179 | D41: ='S_Bfsd_Taux+2pts'!$B$180 | E41: ='S_Bfsd_Taux+2pts'!$B$181 | F41: ='S_Bfsd_Taux+2pts'!$B$182 | G41: ='S_Bfsd_Taux+2pts'!$B$183 | H41: ='S_Bfsd_Taux+2pts'!$B$184 | I41: ='S_Bfsd_Taux+2pts'!$B$185 | J41: ='S_Bfsd_Taux+2pts'!$B$186 | K41: ='S_Bfsd_Taux+2pts'!$B$187 | L41: ='S_Bfsd_Taux+2pts'!$B$190 | M41: ='S_Bfsd_Taux+2pts'!$B$191 | N41: ='S_Bfsd_Taux+2pts'!$B$188 | O41: ='S_Bfsd_Taux+2pts'!$B$189 | P41: ='S_Bfsd_Taux+2pts'!$B$192 | Q41: ='S_Bfsd_Taux+2pts'!$B$193 | R41: ='S_Bfsd_Taux+2pts'!$B$194
A42: S_Bfsd_RetraitFP50 | B42: ='S_Bfsd_RetraitFP50'!$B$178 | C42: ='S_Bfsd_RetraitFP50'!$B$179 | D42: ='S_Bfsd_RetraitFP50'!$B$180 | E42: ='S_Bfsd_RetraitFP50'!$B$181 | F42: ='S_Bfsd_RetraitFP50'!$B$182 | G42: ='S_Bfsd_RetraitFP50'!$B$183 | H42: ='S_Bfsd_RetraitFP50'!$B$184 | I42: ='S_Bfsd_RetraitFP50'!$B$185 | J42: ='S_Bfsd_RetraitFP50'!$B$186 | K42: ='S_Bfsd_RetraitFP50'!$B$187 | L42: ='S_Bfsd_RetraitFP50'!$B$190 | M42: ='S_Bfsd_RetraitFP50'!$B$191 | N42: ='S_Bfsd_RetraitFP50'!$B$188 | O42: ='S_Bfsd_RetraitFP50'!$B$189 | P42: ='S_Bfsd_RetraitFP50'!$B$192 | Q42: ='S_Bfsd_RetraitFP50'!$B$193 | R42: ='S_Bfsd_RetraitFP50'!$B$194
A43: S_Bfsd_Annul40evt | B43: ='S_Bfsd_Annul40evt'!$B$178 | C43: ='S_Bfsd_Annul40evt'!$B$179 | D43: ='S_Bfsd_Annul40evt'!$B$180 | E43: ='S_Bfsd_Annul40evt'!$B$181 | F43: ='S_Bfsd_Annul40evt'!$B$182 | G43: ='S_Bfsd_Annul40evt'!$B$183 | H43: ='S_Bfsd_Annul40evt'!$B$184 | I43: ='S_Bfsd_Annul40evt'!$B$185 | J43: ='S_Bfsd_Annul40evt'!$B$186 | K43: ='S_Bfsd_Annul40evt'!$B$187 | L43: ='S_Bfsd_Annul40evt'!$B$190 | M43: ='S_Bfsd_Annul40evt'!$B$191 | N43: ='S_Bfsd_Annul40evt'!$B$188 | O43: ='S_Bfsd_Annul40evt'!$B$189 | P43: ='S_Bfsd_Annul40evt'!$B$192 | Q43: ='S_Bfsd_Annul40evt'!$B$193 | R43: ='S_Bfsd_Annul40evt'!$B$194
A44: S_Bfsd_Cumul | B44: ='S_Bfsd_Cumul'!$B$178 | C44: ='S_Bfsd_Cumul'!$B$179 | D44: ='S_Bfsd_Cumul'!$B$180 | E44: ='S_Bfsd_Cumul'!$B$181 | F44: ='S_Bfsd_Cumul'!$B$182 | G44: ='S_Bfsd_Cumul'!$B$183 | H44: ='S_Bfsd_Cumul'!$B$184 | I44: ='S_Bfsd_Cumul'!$B$185 | J44: ='S_Bfsd_Cumul'!$B$186 | K44: ='S_Bfsd_Cumul'!$B$187 | L44: ='S_Bfsd_Cumul'!$B$190 | M44: ='S_Bfsd_Cumul'!$B$191 | N44: ='S_Bfsd_Cumul'!$B$188 | O44: ='S_Bfsd_Cumul'!$B$189 | P44: ='S_Bfsd_Cumul'!$B$192 | Q44: ='S_Bfsd_Cumul'!$B$193 | R44: ='S_Bfsd_Cumul'!$B$194

Sheet A_central
A1: Scénario A — Château équestre « sport » — cas central
A2: Cellules jaunes/bleues = hypothèses éditables. Tout le reste est calculé. Colonne D (bloc hypothèses) = source ou statut (ESTIMATION = non vérifiée).
A4: 1. Calendrier, acquisition et travaux
A5: Année d'acquisition des murs (1 = immédiate) | B5: 1 | C5: année | D5: Achat immédiat (2027)
A6: Année d'ouverture commerciale (avant stress) | B6: 2 | C6: année | D6: Année 1 = travaux ; EST
A7: Prix d'acquisition | B7: 2500000 | C7: € | D7: PL : médiane de 19 annonces de châteaux ≥ 30 ha (quartiles 1,29-3,07 M€) [A1]
A8: Frais d'acquisition (droits + notaire) | B8: 0.075 | C8: % | D8: EST : DMTO ≈ 5,8-6,3 % + notaire ≈ 1,2 % ; vente SAFER : frais 8,4 % TTC mais exonération de droits possible [A1, PL]
A9: Part du prix affectable au bâti (amortissable) | B9: 0.55 | C9: % | D9: EST
A10: Travaux de restauration / mise aux normes | B10: 500000 | C10: € | D10: EST sans visite : top 5 des biens équipés 0,1-0,7 M€ [A1]
A11: Investissements équestres (boxes, carrière, manège…) | B11: 350000 | C11: € | D11: EST : marcheur 35 k€, carrière 35 €/m², barn 200 €/m² (PL [A3 H19]) + 10 box supplémentaires
A12: Investissements événementiel / hébergement | B12: 80000 | C12: € | D12: EST : salon de réception pour ventes privées, pas de salle ERP > 50 pers.
A13: Répartition travaux : année d'acquisition | B13: 0.6 | C13: % | D13: EST
A14: Répartition travaux : année +1 | B14: 0.3 | C14: % | D14: EST
A15: Répartition travaux : année +2 | B15: 0.1 | C15: % | D15: EST
A16: Gros entretien patrimonial annuel (% prix+travaux) | B16: 0.018 | C16: % | D16: ≈ 41 k€/an sur (bâti + travaux) : Demeure Historique ≥ 40 k€/an hors restauration (PL [A8]) ; Barnes 20-80 k€/an [A4 §11] ; démarre en année d'acquisition + 3
... A20: Loyer de la partie privée payé par le fondateur (hors CA d'exploitation) | B20: 0 | C20: € | D20: Correction audit M1 : aucun loyer privé compté — le logis doit être détenu à part (SCI à l'IR, hors taxe 235 ter C [A6]) et payé par le fondateur personnellement
A22: 2. Financement
A23: Apport du fondateur (année 1) | B23: 1000000 | C23: € | D23: Scénario d'apport S3 (hypothèse ; apport réel inconnu)
A24: Fonds propres apportés à l'acquisition (investisseurs ou holding) | B24: 0 | C24: € | D24: Aucun investisseur
A25: Ces fonds propres viennent-ils de la holding du fondateur ? (1/0) | B25: 0
A26: Subventions (non acquises : 0 par défaut) | B26: 0 | C26: € | D26: Aucune subvention considérée comme acquise
A27: Dette bancaire (année d'acquisition) | B27: 2400000 | C27: € | D27: NON ACQUIS — montage 1 [A2] : prêt hypothécaire 20 ans ; LTV ≈ 70 %, jugée trop élevée par l'agent 2
A28: Taux de la dette bancaire | B28: 0.04 | C28: % | D28: PL : nouveaux crédits PME 3,64 % (FBF, 06/2026) ; EX : 3,66 % (BdF, 08/2026) ; retenu 4,0 % [A2]
A29: Durée dette bancaire | B29: 20 | C29: ans | D29: A2 (Bpifrance : 15 ans avec hypothèque, PL)
A30: Différé d'amortissement (dans la durée) | B30: 1 | C30: ans | D30: EST
A31: Crédit-vendeur | B31: 0 | C31: €
A32: Taux crédit-vendeur | B32: 0.03 | C32: % | D32: EST
A33: Durée crédit-vendeur (amortissable) | B33: 12 | C33: ans | D33: EST
A34: Obligations / quasi-fonds propres (in fine) | B34: 0 | C34: €
A35: Coupon annuel des obligations | B35: 0.07 | C35: % | D35: PL : obligations Château Fontenay 7 % [A2]
A36: Année de remboursement des obligations | B36: 6 | C36: année | D36: EST
A37: Part de capital supplémentaire accordée au fondateur pour son travail (sweat equity) | B37: 0 | C37: % | D37: Fondateur seul
A38: Droits de vote du fondateur | B38: 1 | C38: %
A39: Réserve de liquidité cible | B39: 150000 | C39: € | D39: EST
A40: TRI minimal exigé par des investisseurs extérieurs | B40: 0.06 | C40: % | D40: EST : rendement minimal d'un investisseur en fonds propres illiquide (Anaxago affiche 8,7 % net, PL [A2])
A41: Le dirigeant est-il rémunéré par le domaine ? (1/0) | B41: 1 | D41: Rémunération du dirigeant incluse
A42: Part du capital du fondateur (calculée : apports au prorata + prime d'industrie, plafonnée à 100 %) | B42: =MIN(1,($B$23+$B$24*$B$25)/MAX(1,$B$23+$B$24)+$B$37)
A44: 3. Paramètres de stress (neutres = 100 % / 0)
A45: Multiplicateur de chiffre d'affaires | B45: 1 | C45: % | D45: neutre
A46: Multiplicateur du budget travaux | B46: 1 | C46: % | D46: neutre
A47: Retard d'ouverture | B47: 0 | C47: ans | D47: neutre
A48: Hausse du taux bancaire (points) | B48: 0 | C48: % | D48: neutre
A49: Part des fonds investisseurs non versée | B49: 0 | C49: % | D49: neutre
A50: Part des événements annulés | B50: 0 | C50: % | D50: neutre
A52: 4. Exploitation — hypothèses générales
A53: Montée en charge : 1re année d'exploitation | B53: 0.5 | C53: % | D53: A4 : mariages 40/70/100 % ; gîte 50/80/100 %
A54: Montée en charge : 2e année | B54: 0.8 | C54: % | D54: EST
A55: Montée en charge : 3e année | B55: 1 | C55: % | D55: EST
A56: Indexation annuelle des prix | B56: 0.02 | C56: % | D56: EST
A57: Inflation annuelle des charges | B57: 0.02 | C57: % | D57: EST : indexation identique aux prix (correction audit, biais pessimiste retiré)
A58: BFR en % du CA (négatif = acomptes clients) | B58: -0.03 | C58: % | D58: Acomptes (mariages, pensions payées d'avance) — EST
A59: Taux normal d'IS | B59: 0.25 | C59: % | D59: PL : IS 25 % au-delà de 42 500 € [A6]
A60: Taux réduit d'IS (PME, jusqu'au seuil) | B60: 0.15 | C60: % | D60: PL : 15 % jusqu'à 42 500 € (PME) [A6]
A61: Seuil du taux réduit d'IS | B61: 42500 | C61: € | D61: PL [A6]
A63: 5. Lignes de revenus (à maturité, euros de l'année d'ouverture)
A64: Libellé | B64: Volume | C64: Prix unitaire | D64: Coût var. % | E64: Événement ? | F64: Équestre ? | G64: Unité / source
A65: Pension travail (chevaux de sport, places occupées) | B65: 18 | C65: 6000 | D65: 0.29 | E65: 0 | F65: 1 | G65: PL : 600 € TTC/mois (médiane hors IdF 535 €, 3e quartile 612 €) [A3, recalcul A8] → 500 € HT à TVA 20 % (entraînement/valorisation) ; 20 places × 90 % ; coûts op. 1 729 €/an
A66: Pension box premium (places occupées) | B66: 9 | C66: 5915 | D66: 0.2 | E66: 0 | F66: 1 | G66: Cf. B ; 10 places × 90 %
A67: Pension au pré (places occupées) | B67: 14 | C67: 2616 | D67: 0.23 | E67: 0 | F67: 1 | G67: Cf. B ; 15 places × 92 %
A68: Valorisation et vente de jeunes chevaux (marge nette par cheval vendu) | B68: 3 | C68: 9975 | D68: 0.1 | E68: 0 | F68: 1 | G68: PL : cas-type 2 chevaux/an, 36,75 k€ vendus − 16,8 k€ achetés [A3 §8] ; 3/an EST ; risque élevé
A69: Organisation de concours (produit annuel) | B69: 1 | C69: 16076 | D69: 0.5 | E69: 1 | F69: 1 | G69: PL : produit moyen « organisation de concours » d'une pension travail 16 076 €/an [A3 §4] ; marge EST
A70: Ventes privées / showcases B2B (soirées) | B70: 3 | C70: 3000 | D70: 0.4 | E70: 1 | F70: 1 | G70: INC : aucun tarif de location publié [A3 §8 n°10] ; EST
A71: Gains de compétition | B71: 1 | C71: 12250 | D71: 0 | E71: 1 | F71: 1 | G71: PL : cas-type CSO 2025 12 250 € [A3 §4]
A72: Gîte 15 couchages hors mariages (nuits) | B72: 92 | C72: 450 | D72: 0.45 | E72: 0 | F72: 0 | G72: PL : fourchettes de prix [A4 §4.2] ; 92 nuits EST (occupation annuelle ≈ 33 % observée en Normandie hors saison) [A4 §4.3]
A73: Tournages / shootings (jours) | B73: 3 | C73: 2000 | D73: 0.15 | E73: 1 | F73: 0 | G73: PL : 1 500-4 000 €/jour [A4 §5] ; fréquence EST
A74: Fermage / vente d'herbe (ha) | B74: 10 | C74: 150 | D74: 0 | E74: 0 | F74: 0 | G74: PL : arrêtés Orne/Calvados 2026-27 : 50-268 €/ha [A4 §8.2]
A76: 6. Charges fixes annuelles (euros de l'année d'ouverture)
A77: Libellé | B77: Montant/an | C77: Dès l'acq. (1) / dès l'ouverture (0) | G77: Source / statut
A78: Taxe foncière | B78: 6000 | C78: 1 | G78: EX : 2,6-4,0 k€ sur 3 annonces ; EST 4-8 k€ [A4 §11]
A79: Assurance multirisque château | B79: 12000 | C79: 1 | G79: Correction audit : courtier spécialisé 15-30 k€ (fiabilité moyenne), annonces ≥ 2,5 k€ [A4 §11, A8] ; EST 12 k€
A80: Énergie (chauffage partiel, électricité, eau) | B80: 20000 | C80: 1 | G80: PL : Meung, Louvignies ; EX annonce Montluçon 18-25 k€ [A1, A4 §11] ; EST
A81: Jardinier / agent d'entretien (1 ETP au Smic chargé) | B81: 27000 | C81: 1 | G81: PL : Smic 2026 22 404 € brut/an [A4 §11] ; EST charges
A82: Divers (abonnements, petit matériel, véhicule, honoraires) | B82: 8000 | C82: 1 | G82: EST
A83: Cavalier professionnel / responsable d'écurie (chargé) | B83: 45000 | C83: 0 | G83: PL : grille 2 108-2 678 € brut (coef. 130-167) [A3 H15] ; EST charges
A84: Soigneurs / cavaliers-soigneurs (2,5 ETP chargés) | B84: 78000 | C84: 0 | G84: PL [A3 H13-H14] ; 10 chevaux au travail / ETP ; ~45 équidés
A85: Autres charges de structure équestres | B85: 35000 | C85: 0 | G85: EST : réf. structure pension travail 2 471 €/équidé [A3 §4] (salaires inclus) → calibrage
A86: Coûts fixes du gîte | B86: 4400 | C86: 0 | G86: EST [A4 §13.1]
A87: Commercial, site, salons | B87: 12000 | C87: 0 | G87: EST
A88: Comptabilité, juridique, banque, logiciels | B88: 12000 | C88: 0 | G88: EST
A89: Rémunération du dirigeant (chargée) | B89: 35000 | C89: 0 | G89: EST : minimum ; le dirigeant paie en plus 18 k€ de loyer privé
A91: 7. Calcul sur 10 ans
A92: Année | B92: Total / réf. | C92: 1 | D92: 2 | E92: 3 | F92: 4 | G92: 5 | H92: 6 | I92: 7 | J92: 8 | K92: 9 | L92: 10
A93: Année d'ouverture effective | C93: =$B$6+$B$47 | D93: =$B$6+$B$47 | E93: =$B$6+$B$47 | F93: =$B$6+$B$47 | G93: =$B$6+$B$47 | H93: =$B$6+$B$47 | I93: =$B$6+$B$47 | J93: =$B$6+$B$47 | ... L93: =$B$6+$B$47
A94: Rang de l'année d'exploitation | C94: =MAX(0,C$92-C93+1) | D94: =MAX(0,D$92-D93+1) | E94: =MAX(0,E$92-E93+1) | F94: =MAX(0,F$92-F93+1) | G94: =MAX(0,G$92-G93+1) | H94: =MAX(0,H$92-H93+1) | I94: =MAX(0,I$92-I93+1) | J94: =MAX(0,J$92-J93+1) | ... L94: =MAX(0,L$92-L93+1)
A95: Coefficient de montée en charge | C95: =IF(C94=0,0,IF(C94=1,$B$53,IF(C94=2,$B$54,IF(C94=3,$B$55,1)))) | D95: =IF(D94=0,0,IF(D94=1,$B$53,IF(D94=2,$B$54,IF(D94=3,$B$55,1)))) | E95: =IF(E94=0,0,IF(E94=1,$B$53,IF(E94=2,$B$54,IF(E94=3,$B$55,1)))) | F95: =IF(F94=0,0,IF(F94=1,$B$53,IF(F94=2,$B$54,IF(F94=3,$B$55,1)))) | G95: =IF(G94=0,0,IF(G94=1,$B$53,IF(G94=2,$B$54,IF(G94=3,$B$55,1)))) | H95: =IF(H94=0,0,IF(H94=1,$B$53,IF(H94=2,$B$54,IF(H94=3,$B$55,1)))) | I95: =IF(I94=0,0,IF(I94=1,$B$53,IF(I94=2,$B$54,IF(I94=3,$B$55,1)))) | J95: =IF(J94=0,0,IF(J94=1,$B$53,IF(J94=2,$B$54,IF(J94=3,$B$55,1)))) | ... L95: =IF(L94=0,0,IF(L94=1,$B$53,IF(L94=2,$B$54,IF(L94=3,$B$55,1))))
A96: Indice prix | C96: =(1+$B$56)^(C$92-1) | D96: =(1+$B$56)^(D$92-1) | E96: =(1+$B$56)^(E$92-1) | F96: =(1+$B$56)^(F$92-1) | G96: =(1+$B$56)^(G$92-1) | H96: =(1+$B$56)^(H$92-1) | I96: =(1+$B$56)^(I$92-1) | J96: =(1+$B$56)^(J$92-1) | ... L96: =(1+$B$56)^(L$92-1)
A97: Indice charges | C97: =(1+$B$57)^(C$92-1) | D97: =(1+$B$57)^(D$92-1) | E97: =(1+$B$57)^(E$92-1) | F97: =(1+$B$57)^(F$92-1) | G97: =(1+$B$57)^(G$92-1) | H97: =(1+$B$57)^(H$92-1) | I97: =(1+$B$57)^(I$92-1) | J97: =(1+$B$57)^(J$92-1) | ... L97: =(1+$B$57)^(L$92-1)
A98: Murs détenus (1/0) | C98: =IF(C$92>=$B$5,1,0) | D98: =IF(D$92>=$B$5,1,0) | E98: =IF(E$92>=$B$5,1,0) | F98: =IF(F$92>=$B$5,1,0) | G98: =IF(G$92>=$B$5,1,0) | H98: =IF(H$92>=$B$5,1,0) | I98: =IF(I$92>=$B$5,1,0) | J98: =IF(J$92>=$B$5,1,0) | ... L98: =IF(L$92>=$B$5,1,0)
A100: Compte de résultat
A101: Pension travail (chevaux de sport, places occupées) | B101: =SUM(C101:L101) | C101: =$B$65*$C$65*C95*C96*$B$45*(1-$E$65*$B$50) | D101: =$B$65*$C$65*D95*D96*$B$45*(1-$E$65*$B$50) | E101: =$B$65*$C$65*E95*E96*$B$45*(1-$E$65*$B$50) | F101: =$B$65*$C$65*F95*F96*$B$45*(1-$E$65*$B$50) | G101: =$B$65*$C$65*G95*G96*$B$45*(1-$E$65*$B$50) | H101: =$B$65*$C$65*H95*H96*$B$45*(1-$E$65*$B$50) | I101: =$B$65*$C$65*I95*I96*$B$45*(1-$E$65*$B$50) | J101: =$B$65*$C$65*J95*J96*$B$45*(1-$E$65*$B$50) | ... L101: =$B$65*$C$65*L95*L96*$B$45*(1-$E$65*$B$50)
A102: Pension box premium (places occupées) | B102: =SUM(C102:L102) | C102: =$B$66*$C$66*C95*C96*$B$45*(1-$E$66*$B$50) | D102: =$B$66*$C$66*D95*D96*$B$45*(1-$E$66*$B$50) | E102: =$B$66*$C$66*E95*E96*$B$45*(1-$E$66*$B$50) | F102: =$B$66*$C$66*F95*F96*$B$45*(1-$E$66*$B$50) | G102: =$B$66*$C$66*G95*G96*$B$45*(1-$E$66*$B$50) | H102: =$B$66*$C$66*H95*H96*$B$45*(1-$E$66*$B$50) | I102: =$B$66*$C$66*I95*I96*$B$45*(1-$E$66*$B$50) | J102: =$B$66*$C$66*J95*J96*$B$45*(1-$E$66*$B$50) | ... L102: =$B$66*$C$66*L95*L96*$B$45*(1-$E$66*$B$50)
A103: Pension au pré (places occupées) | B103: =SUM(C103:L103) | C103: =$B$67*$C$67*C95*C96*$B$45*(1-$E$67*$B$50) | D103: =$B$67*$C$67*D95*D96*$B$45*(1-$E$67*$B$50) | E103: =$B$67*$C$67*E95*E96*$B$45*(1-$E$67*$B$50) | F103: =$B$67*$C$67*F95*F96*$B$45*(1-$E$67*$B$50) | G103: =$B$67*$C$67*G95*G96*$B$45*(1-$E$67*$B$50) | H103: =$B$67*$C$67*H95*H96*$B$45*(1-$E$67*$B$50) | I103: =$B$67*$C$67*I95*I96*$B$45*(1-$E$67*$B$50) | J103: =$B$67*$C$67*J95*J96*$B$45*(1-$E$67*$B$50) | ... L103: =$B$67*$C$67*L95*L96*$B$45*(1-$E$67*$B$50)
A104: Valorisation et vente de jeunes chevaux (marge nette par cheval vendu) | B104: =SUM(C104:L104) | C104: =$B$68*$C$68*C95*C96*$B$45*(1-$E$68*$B$50) | D104: =$B$68*$C$68*D95*D96*$B$45*(1-$E$68*$B$50) | E104: =$B$68*$C$68*E95*E96*$B$45*(1-$E$68*$B$50) | F104: =$B$68*$C$68*F95*F96*$B$45*(1-$E$68*$B$50) | G104: =$B$68*$C$68*G95*G96*$B$45*(1-$E$68*$B$50) | H104: =$B$68*$C$68*H95*H96*$B$45*(1-$E$68*$B$50) | I104: =$B$68*$C$68*I95*I96*$B$45*(1-$E$68*$B$50) | J104: =$B$68*$C$68*J95*J96*$B$45*(1-$E$68*$B$50) | ... L104: =$B$68*$C$68*L95*L96*$B$45*(1-$E$68*$B$50)
A105: Organisation de concours (produit annuel) | B105: =SUM(C105:L105) | C105: =$B$69*$C$69*C95*C96*$B$45*(1-$E$69*$B$50) | D105: =$B$69*$C$69*D95*D96*$B$45*(1-$E$69*$B$50) | E105: =$B$69*$C$69*E95*E96*$B$45*(1-$E$69*$B$50) | F105: =$B$69*$C$69*F95*F96*$B$45*(1-$E$69*$B$50) | G105: =$B$69*$C$69*G95*G96*$B$45*(1-$E$69*$B$50) | H105: =$B$69*$C$69*H95*H96*$B$45*(1-$E$69*$B$50) | I105: =$B$69*$C$69*I95*I96*$B$45*(1-$E$69*$B$50) | J105: =$B$69*$C$69*J95*J96*$B$45*(1-$E$69*$B$50) | ... L105: =$B$69*$C$69*L95*L96*$B$45*(1-$E$69*$B$50)
A106: Ventes privées / showcases B2B (soirées) | B106: =SUM(C106:L106) | C106: =$B$70*$C$70*C95*C96*$B$45*(1-$E$70*$B$50) | D106: =$B$70*$C$70*D95*D96*$B$45*(1-$E$70*$B$50) | E106: =$B$70*$C$70*E95*E96*$B$45*(1-$E$70*$B$50) | F106: =$B$70*$C$70*F95*F96*$B$45*(1-$E$70*$B$50) | G106: =$B$70*$C$70*G95*G96*$B$45*(1-$E$70*$B$50) | H106: =$B$70*$C$70*H95*H96*$B$45*(1-$E$70*$B$50) | I106: =$B$70*$C$70*I95*I96*$B$45*(1-$E$70*$B$50) | J106: =$B$70*$C$70*J95*J96*$B$45*(1-$E$70*$B$50) | ... L106: =$B$70*$C$70*L95*L96*$B$45*(1-$E$70*$B$50)
A107: Gains de compétition | B107: =SUM(C107:L107) | C107: =$B$71*$C$71*C95*C96*$B$45*(1-$E$71*$B$50) | D107: =$B$71*$C$71*D95*D96*$B$45*(1-$E$71*$B$50) | E107: =$B$71*$C$71*E95*E96*$B$45*(1-$E$71*$B$50) | F107: =$B$71*$C$71*F95*F96*$B$45*(1-$E$71*$B$50) | G107: =$B$71*$C$71*G95*G96*$B$45*(1-$E$71*$B$50) | H107: =$B$71*$C$71*H95*H96*$B$45*(1-$E$71*$B$50) | I107: =$B$71*$C$71*I95*I96*$B$45*(1-$E$71*$B$50) | J107: =$B$71*$C$71*J95*J96*$B$45*(1-$E$71*$B$50) | ... L107: =$B$71*$C$71*L95*L96*$B$45*(1-$E$71*$B$50)
A108: Gîte 15 couchages hors mariages (nuits) | B108: =SUM(C108:L108) | C108: =$B$72*$C$72*C95*C96*$B$45*(1-$E$72*$B$50) | D108: =$B$72*$C$72*D95*D96*$B$45*(1-$E$72*$B$50) | E108: =$B$72*$C$72*E95*E96*$B$45*(1-$E$72*$B$50) | F108: =$B$72*$C$72*F95*F96*$B$45*(1-$E$72*$B$50) | G108: =$B$72*$C$72*G95*G96*$B$45*(1-$E$72*$B$50) | H108: =$B$72*$C$72*H95*H96*$B$45*(1-$E$72*$B$50) | I108: =$B$72*$C$72*I95*I96*$B$45*(1-$E$72*$B$50) | J108: =$B$72*$C$72*J95*J96*$B$45*(1-$E$72*$B$50) | ... L108: =$B$72*$C$72*L95*L96*$B$45*(1-$E$72*$B$50)
A109: Tournages / shootings (jours) | B109: =SUM(C109:L109) | C109: =$B$73*$C$73*C95*C96*$B$45*(1-$E$73*$B$50) | D109: =$B$73*$C$73*D95*D96*$B$45*(1-$E$73*$B$50) | E109: =$B$73*$C$73*E95*E96*$B$45*(1-$E$73*$B$50) | F109: =$B$73*$C$73*F95*F96*$B$45*(1-$E$73*$B$50) | G109: =$B$73*$C$73*G95*G96*$B$45*(1-$E$73*$B$50) | H109: =$B$73*$C$73*H95*H96*$B$45*(1-$E$73*$B$50) | I109: =$B$73*$C$73*I95*I96*$B$45*(1-$E$73*$B$50) | J109: =$B$73*$C$73*J95*J96*$B$45*(1-$E$73*$B$50) | ... L109: =$B$73*$C$73*L95*L96*$B$45*(1-$E$73*$B$50)
A110: Fermage / vente d'herbe (ha) | B110: =SUM(C110:L110) | C110: =$B$74*$C$74*C95*C96*$B$45*(1-$E$74*$B$50) | D110: =$B$74*$C$74*D95*D96*$B$45*(1-$E$74*$B$50) | E110: =$B$74*$C$74*E95*E96*$B$45*(1-$E$74*$B$50) | F110: =$B$74*$C$74*F95*F96*$B$45*(1-$E$74*$B$50) | G110: =$B$74*$C$74*G95*G96*$B$45*(1-$E$74*$B$50) | H110: =$B$74*$C$74*H95*H96*$B$45*(1-$E$74*$B$50) | I110: =$B$74*$C$74*I95*I96*$B$45*(1-$E$74*$B$50) | J110: =$B$74*$C$74*J95*J96*$B$45*(1-$E$74*$B$50) | ... L110: =$B$74*$C$74*L95*L96*$B$45*(1-$E$74*$B$50)
A111: Chiffre d'affaires total | B111: =SUM(C111:L111) | C111: =C101+C102+C103+C104+C105+C106+C107+C108+C109+C110 | D111: =D101+D102+D103+D104+D105+D106+D107+D108+D109+D110 | E111: =E101+E102+E103+E104+E105+E106+E107+E108+E109+E110 | F111: =F101+F102+F103+F104+F105+F106+F107+F108+F109+F110 | G111: =G101+G102+G103+G104+G105+G106+G107+G108+G109+G110 | H111: =H101+H102+H103+H104+H105+H106+H107+H108+H109+H110 | I111: =I101+I102+I103+I104+I105+I106+I107+I108+I109+I110 | J111: =J101+J102+J103+J104+J105+J106+J107+J108+J109+J110 | ... L111: =L101+L102+L103+L104+L105+L106+L107+L108+L109+L110
...

Sheet A_prudent
A1: Scénario A — Château équestre « sport » — cas prudent
A2: Cellules jaunes/bleues = hypothèses éditables. Tout le reste est calculé. Colonne D (bloc hypothèses) = source ou statut (ESTIMATION = non vérifiée).
A4: 1. Calendrier, acquisition et travaux
A5: Année d'acquisition des murs (1 = immédiate) | B5: 1 | C5: année | D5: Achat immédiat (2027)
A6: Année d'ouverture commerciale (avant stress) | B6: 2 | C6: année | D6: Année 1 = travaux ; EST
A7: Prix d'acquisition | B7: 2500000 | C7: € | D7: PL : médiane de 19 annonces de châteaux ≥ 30 ha (quartiles 1,29-3,07 M€) [A1]
A8: Frais d'acquisition (droits + notaire) | B8: 0.075 | C8: % | D8: EST : DMTO ≈ 5,8-6,3 % + notaire ≈ 1,2 % ; vente SAFER : frais 8,4 % TTC mais exonération de droits possible [A1, PL]
A9: Part du prix affectable au bâti (amortissable) | B9: 0.55 | C9: % | D9: EST
A10: Travaux de restauration / mise aux normes | B10: 625000 | C10: € | D10: EST sans visite : top 5 des biens équipés 0,1-0,7 M€ [A1]
A11: Investissements équestres (boxes, carrière, manège…) | B11: 437500 | C11: € | D11: EST : marcheur 35 k€, carrière 35 €/m², barn 200 €/m² (PL [A3 H19]) + 10 box supplémentaires
A12: Investissements événementiel / hébergement | B12: 100000 | C12: € | D12: EST : salon de réception pour ventes privées, pas de salle ERP > 50 pers.
A13: Répartition travaux : année d'acquisition | B13: 0.6 | C13: % | D13: EST
A14: Répartition travaux : année +1 | B14: 0.3 | C14: % | D14: EST
A15: Répartition travaux : année +2 | B15: 0.1 | C15: % | D15: EST
A16: Gros entretien patrimonial annuel (% prix+travaux) | B16: 0.018 | C16: % | D16: ≈ 41 k€/an sur (bâti + travaux) : Demeure Historique ≥ 40 k€/an hors restauration (PL [A8]) ; Barnes 20-80 k€/an [A4 §11] ; démarre en année d'acquisition + 3
... A20: Loyer de la partie privée payé par le fondateur (hors CA d'exploitation) | B20: 0 | C20: € | D20: Correction audit M1 : aucun loyer privé compté — le logis doit être détenu à part (SCI à l'IR, hors taxe 235 ter C [A6]) et payé par le fondateur personnellement
A22: 2. Financement
A23: Apport du fondateur (année 1) | B23: 1000000 | C23: € | D23: Scénario d'apport S3 (hypothèse ; apport réel inconnu)
A24: Fonds propres apportés à l'acquisition (investisseurs ou holding) | B24: 0 | C24: € | D24: Aucun investisseur
A25: Ces fonds propres viennent-ils de la holding du fondateur ? (1/0) | B25: 0
A26: Subventions (non acquises : 0 par défaut) | B26: 0 | C26: € | D26: Aucune subvention considérée comme acquise
A27: Dette bancaire (année d'acquisition) | B27: 2400000 | C27: € | D27: NON ACQUIS — montage 1 [A2] : prêt hypothécaire 20 ans ; LTV ≈ 70 %, jugée trop élevée par l'agent 2
A28: Taux de la dette bancaire | B28: 0.04 | C28: % | D28: PL : nouveaux crédits PME 3,64 % (FBF, 06/2026) ; EX : 3,66 % (BdF, 08/2026) ; retenu 4,0 % [A2]
A29: Durée dette bancaire | B29: 20 | C29: ans | D29: A2 (Bpifrance : 15 ans avec hypothèque, PL)
A30: Différé d'amortissement (dans la durée) | B30: 1 | C30: ans | D30: EST
A31: Crédit-vendeur | B31: 0 | C31: €
A32: Taux crédit-vendeur | B32: 0.03 | C32: % | D32: EST
A33: Durée crédit-vendeur (amortissable) | B33: 12 | C33: ans | D33: EST
A34: Obligations / quasi-fonds propres (in fine) | B34: 0 | C34: €
A35: Coupon annuel des obligations | B35: 0.07 | C35: % | D35: PL : obligations Château Fontenay 7 % [A2]
A36: Année de remboursement des obligations | B36: 6 | C36: année | D36: EST
A37: Part de capital supplémentaire accordée au fondateur pour son travail (sweat equity) | B37: 0 | C37: % | D37: Fondateur seul
A38: Droits de vote du fondateur | B38: 1 | C38: %
A39: Réserve de liquidité cible | B39: 150000 | C39: € | D39: EST
A40: TRI minimal exigé par des investisseurs extérieurs | B40: 0.06 | C40: % | D40: EST : rendement minimal d'un investisseur en fonds propres illiquide (Anaxago affiche 8,7 % net, PL [A2])
A41: Le dirigeant est-il rémunéré par le domaine ? (1/0) | B41: 1 | D41: Rémunération du dirigeant incluse
A42: Part du capital du fondateur (calculée : apports au prorata + prime d'industrie, plafonnée à 100 %) | B42: =MIN(1,($B$23+$B$24*$B$25)/MAX(1,$B$23+$B$24)+$B$37)
A44: 3. Paramètres de stress (neutres = 100 % / 0)
A45: Multiplicateur de chiffre d'affaires | B45: 1 | C45: % | D45: neutre
A46: Multiplicateur du budget travaux | B46: 1 | C46: % | D46: neutre
A47: Retard d'ouverture | B47: 0 | C47: ans | D47: neutre
A48: Hausse du taux bancaire (points) | B48: 0 | C48: % | D48: neutre
A49: Part des fonds investisseurs non versée | B49: 0 | C49: % | D49: neutre
A50: Part des événements annulés | B50: 0 | C50: % | D50: neutre
A52: 4. Exploitation — hypothèses générales
A53: Montée en charge : 1re année d'exploitation | B53: 0.4 | C53: % | D53: Cas prudent
A54: Montée en charge : 2e année | B54: 0.65 | C54: % | D54: Cas prudent
A55: Montée en charge : 3e année | B55: 0.85 | C55: % | D55: Cas prudent
A56: Indexation annuelle des prix | B56: 0.02 | C56: % | D56: EST
A57: Inflation annuelle des charges | B57: 0.02 | C57: % | D57: EST : indexation identique aux prix (correction audit, biais pessimiste retiré)
A58: BFR en % du CA (négatif = acomptes clients) | B58: -0.03 | C58: % | D58: Acomptes (mariages, pensions payées d'avance) — EST
A59: Taux normal d'IS | B59: 0.25 | C59: % | D59: PL : IS 25 % au-delà de 42 500 € [A6]
A60: Taux réduit d'IS (PME, jusqu'au seuil) | B60: 0.15 | C60: % | D60: PL : 15 % jusqu'à 42 500 € (PME) [A6]
A61: Seuil du taux réduit d'IS | B61: 42500 | C61: € | D61: PL [A6]
A63: 5. Lignes de revenus (à maturité, euros de l'année d'ouverture)
A64: Libellé | B64: Volume | C64: Prix unitaire | D64: Coût var. % | E64: Événement ? | F64: Équestre ? | G64: Unité / source
A65: Pension travail (chevaux de sport, places occupées) | B65: 14.4 | C65: 5520 | D65: 0.29 | E65: 0 | F65: 1 | G65: PL : 600 € TTC/mois (médiane hors IdF 535 €, 3e quartile 612 €) [A3, recalcul A8] → 500 € HT à TVA 20 % (entraînement/valorisation) ; 20 places × 90 % ; coûts op. 1 729 €/an
A66: Pension box premium (places occupées) | B66: 7.2 | C66: 5442 | D66: 0.2 | E66: 0 | F66: 1 | G66: Cf. B ; 10 places × 90 %
A67: Pension au pré (places occupées) | B67: 11.2 | C67: 2407 | D67: 0.23 | E67: 0 | F67: 1 | G67: Cf. B ; 15 places × 92 %
A68: Valorisation et vente de jeunes chevaux (marge nette par cheval vendu) | B68: 2.4 | C68: 9177 | D68: 0.1 | E68: 0 | F68: 1 | G68: PL : cas-type 2 chevaux/an, 36,75 k€ vendus − 16,8 k€ achetés [A3 §8] ; 3/an EST ; risque élevé
A69: Organisation de concours (produit annuel) | B69: 0.8 | C69: 14790 | D69: 0.5 | E69: 1 | F69: 1 | G69: PL : produit moyen « organisation de concours » d'une pension travail 16 076 €/an [A3 §4] ; marge EST
A70: Ventes privées / showcases B2B (soirées) | B70: 2.4 | C70: 2760 | D70: 0.4 | E70: 1 | F70: 1 | G70: INC : aucun tarif de location publié [A3 §8 n°10] ; EST
A71: Gains de compétition | B71: 0.8 | C71: 11270 | D71: 0 | E71: 1 | F71: 1 | G71: PL : cas-type CSO 2025 12 250 € [A3 §4]
A72: Gîte 15 couchages hors mariages (nuits) | B72: 73.6 | C72: 414 | D72: 0.45 | E72: 0 | F72: 0 | G72: PL : fourchettes de prix [A4 §4.2] ; 92 nuits EST (occupation annuelle ≈ 33 % observée en Normandie hors saison) [A4 §4.3]
A73: Tournages / shootings (jours) | B73: 2.4 | C73: 1840 | D73: 0.15 | E73: 1 | F73: 0 | G73: PL : 1 500-4 000 €/jour [A4 §5] ; fréquence EST
A74: Fermage / vente d'herbe (ha) | B74: 8 | C74: 138 | D74: 0 | E74: 0 | F74: 0 | G74: PL : arrêtés Orne/Calvados 2026-27 : 50-268 €/ha [A4 §8.2]
A76: 6. Charges fixes annuelles (euros de l'année d'ouverture)
A77: Libellé | B77: Montant/an | C77: Dès l'acq. (1) / dès l'ouverture (0) | G77: Source / statut
A78: Taxe foncière | B78: 6600 | C78: 1 | G78: EX : 2,6-4,0 k€ sur 3 annonces ; EST 4-8 k€ [A4 §11]
A79: Assurance multirisque château | B79: 13200 | C79: 1 | G79: Correction audit : courtier spécialisé 15-30 k€ (fiabilité moyenne), annonces ≥ 2,5 k€ [A4 §11, A8] ; EST 12 k€
A80: Énergie (chauffage partiel, électricité, eau) | B80: 22000 | C80: 1 | G80: PL : Meung, Louvignies ; EX annonce Montluçon 18-25 k€ [A1, A4 §11] ; EST
A81: Jardinier / agent d'entretien (1 ETP au Smic chargé) | B81: 29700 | C81: 1 | G81: PL : Smic 2026 22 404 € brut/an [A4 §11] ; EST charges
A82: Divers (abonnements, petit matériel, véhicule, honoraires) | B82: 8800 | C82: 1 | G82: EST
A83: Cavalier professionnel / responsable d'écurie (chargé) | B83: 49500 | C83: 0 | G83: PL : grille 2 108-2 678 € brut (coef. 130-167) [A3 H15] ; EST charges
A84: Soigneurs / cavaliers-soigneurs (2,5 ETP chargés) | B84: 85800 | C84: 0 | G84: PL [A3 H13-H14] ; 10 chevaux au travail / ETP ; ~45 équidés
A85: Autres charges de structure équestres | B85: 38500 | C85: 0 | G85: EST : réf. structure pension travail 2 471 €/équidé [A3 §4] (salaires inclus) → calibrage
A86: Coûts fixes du gîte | B86: 4840 | C86: 0 | G86: EST [A4 §13.1]
A87: Commercial, site, salons | B87: 13200 | C87: 0 | G87: EST
A88: Comptabilité, juridique, banque, logiciels | B88: 13200 | C88: 0 | G88: EST
A89: Rémunération du dirigeant (chargée) | B89: 38500 | C89: 0 | G89: EST : minimum ; le dirigeant paie en plus 18 k€ de loyer privé
A91: 7. Calcul sur 10 ans
A92: Année | B92: Total / réf. | C92: 1 | D92: 2 | E92: 3 | F92: 4 | G92: 5 | H92: 6 | I92: 7 | J92: 8 | K92: 9 | L92: 10
A93: Année d'ouverture effective | C93: =$B$6+$B$47 | D93: =$B$6+$B$47 | E93: =$B$6+$B$47 | F93: =$B$6+$B$47 | G93: =$B$6+$B$47 | H93: =$B$6+$B$47 | I93: =$B$6+$B$47 | J93: =$B$6+$B$47 | ... L93: =$B$6+$B$47
A94: Rang de l'année d'exploitation | C94: =MAX(0,C$92-C93+1) | D94: =MAX(0,D$92-D93+1) | E94: =MAX(0,E$92-E93+1) | F94: =MAX(0,F$92-F93+1) | G94: =MAX(0,G$92-G93+1) | H94: =MAX(0,H$92-H93+1) | I94: =MAX(0,I$92-I93+1) | J94: =MAX(0,J$92-J93+1) | ... L94: =MAX(0,L$92-L93+1)
A95: Coefficient de montée en charge | C95: =IF(C94=0,0,IF(C94=1,$B$53,IF(C94=2,$B$54,IF(C94=3,$B$55,1)))) | D95: =IF(D94=0,0,IF(D94=1,$B$53,IF(D94=2,$B$54,IF(D94=3,$B$55,1)))) | E95: =IF(E94=0,0,IF(E94=1,$B$53,IF(E94=2,$B$54,IF(E94=3,$B$55,1)))) | F95: =IF(F94=0,0,IF(F94=1,$B$53,IF(F94=2,$B$54,IF(F94=3,$B$55,1)))) | G95: =IF(G94=0,0,IF(G94=1,$B$53,IF(G94=2,$B$54,IF(G94=3,$B$55,1)))) | H95: =IF(H94=0,0,IF(H94=1,$B$53,IF(H94=2,$B$54,IF(H94=3,$B$55,1)))) | I95: =IF(I94=0,0,IF(I94=1,$B$53,IF(I94=2,$B$54,IF(I94=3,$B$55,1)))) | J95: =IF(J94=0,0,IF(J94=1,$B$53,IF(J94=2,$B$54,IF(J94=3,$B$55,1)))) | ... L95: =IF(L94=0,0,IF(L94=1,$B$53,IF(L94=2,$B$54,IF(L94=3,$B$55,1))))
A96: Indice prix | C96: =(1+$B$56)^(C$92-1) | D96: =(1+$B$56)^(D$92-1) | E96: =(1+$B$56)^(E$92-1) | F96: =(1+$B$56)^(F$92-1) | G96: =(1+$B$56)^(G$92-1) | H96: =(1+$B$56)^(H$92-1) | I96: =(1+$B$56)^(I$92-1) | J96: =(1+$B$56)^(J$92-1) | ... L96: =(1+$B$56)^(L$92-1)
A97: Indice charges | C97: =(1+$B$57)^(C$92-1) | D97: =(1+$B$57)^(D$92-1) | E97: =(1+$B$57)^(E$92-1) | F97: =(1+$B$57)^(F$92-1) | G97: =(1+$B$57)^(G$92-1) | H97: =(1+$B$57)^(H$92-1) | I97: =(1+$B$57)^(I$92-1) | J97: =(1+$B$57)^(J$92-1) | ... L97: =(1+$B$57)^(L$92-1)
A98: Murs détenus (1/0) | C98: =IF(C$92>=$B$5,1,0) | D98: =IF(D$92>=$B$5,1,0) | E98: =IF(E$92>=$B$5,1,0) | F98: =IF(F$92>=$B$5,1,0) | G98: =IF(G$92>=$B$5,1,0) | H98: =IF(H$92>=$B$5,1,0) | I98: =IF(I$92>=$B$5,1,0) | J98: =IF(J$92>=$B$5,1,0) | ... L98: =IF(L$92>=$B$5,1,0)
A100: Compte de résultat
A101: Pension travail (chevaux de sport, places occupées) | B101: =SUM(C101:L101) | C101: =$B$65*$C$65*C95*C96*$B$45*(1-$E$65*$B$50) | D101: =$B$65*$C$65*D95*D96*$B$45*(1-$E$65*$B$50) | E101: =$B$65*$C$65*E95*E96*$B$45*(1-$E$65*$B$50) | F101: =$B$65*$C$65*F95*F96*$B$45*(1-$E$65*$B$50) | G101: =$B$65*$C$65*G95*G96*$B$45*(1-$E$65*$B$50) | H101: =$B$65*$C$65*H95*H96*$B$45*(1-$E$65*$B$50) | I101: =$B$65*$C$65*I95*I96*$B$45*(1-$E$65*$B$50) | J101: =$B$65*$C$65*J95*J96*$B$45*(1-$E$65*$B$50) | ... L101: =$B$65*$C$65*L95*L96*$B$45*(1-$E$65*$B$50)
A102: Pension box premium (places occupées) | B102: =SUM(C102:L102) | C102: =$B$66*$C$66*C95*C96*$B$45*(1-$E$66*$B$50) | D102: =$B$66*$C$66*D95*D96*$B$45*(1-$E$66*$B$50) | E102: =$B$66*$C$66*E95*E96*$B$45*(1-$E$66*$B$50) | F102: =$B$66*$C$66*F95*F96*$B$45*(1-$E$66*$B$50) | G102: =$B$66*$C$66*G95*G96*$B$45*(1-$E$66*$B$50) | H102: =$B$66*$C$66*H95*H96*$B$45*(1-$E$66*$B$50) | I102: =$B$66*$C$66*I95*I96*$B$45*(1-$E$66*$B$50) | J102: =$B$66*$C$66*J95*J96*$B$45*(1-$E$66*$B$50) | ... L102: =$B$66*$C$66*L95*L96*$B$45*(1-$E$66*$B$50)
A103: Pension au pré (places occupées) | B103: =SUM(C103:L103) | C103: =$B$67*$C$67*C95*C96*$B$45*(1-$E$67*$B$50) | D103: =$B$67*$C$67*D95*D96*$B$45*(1-$E$67*$B$50) | E103: =$B$67*$C$67*E95*E96*$B$45*(1-$E$67*$B$50) | F103: =$B$67*$C$67*F95*F96*$B$45*(1-$E$67*$B$50) | G103: =$B$67*$C$67*G95*G96*$B$45*(1-$E$67*$B$50) | H103: =$B$67*$C$67*H95*H96*$B$45*(1-$E$67*$B$50) | I103: =$B$67*$C$67*I95*I96*$B$45*(1-$E$67*$B$50) | J103: =$B$67*$C$67*J95*J96*$B$45*(1-$E$67*$B$50) | ... L103: =$B$67*$C$67*L95*L96*$B$45*(1-$E$67*$B$50)
A104: Valorisation et vente de jeunes chevaux (marge nette par cheval vendu) | B104: =SUM(C104:L104) | C104: =$B$68*$C$68*C95*C96*$B$45*(1-$E$68*$B$50) | D104: =$B$68*$C$68*D95*D96*$B$45*(1-$E$68*$B$50) | E104: =$B$68*$C$68*E95*E96*$B$45*(1-$E$68*$B$50) | F104: =$B$68*$C$68*F95*F96*$B$45*(1-$E$68*$B$50) | G104: =$B$68*$C$68*G95*G96*$B$45*(1-$E$68*$B$50) | H104: =$B$68*$C$68*H95*H96*$B$45*(1-$E$68*$B$50) | I104: =$B$68*$C$68*I95*I96*$B$45*(1-$E$68*$B$50) | J104: =$B$68*$C$68*J95*J96*$B$45*(1-$E$68*$B$50) | ... L104: =$B$68*$C$68*L95*L96*$B$45*(1-$E$68*$B$50)
A105: Organisation de concours (produit annuel) | B105: =SUM(C105:L105) | C105: =$B$69*$C$69*C95*C96*$B$45*(1-$E$69*$B$50) | D105: =$B$69*$C$69*D95*D96*$B$45*(1-$E$69*$B$50) | E105: =$B$69*$C$69*E95*E96*$B$45*(1-$E$69*$B$50) | F105: =$B$69*$C$69*F95*F96*$B$45*(1-$E$69*$B$50) | G105: =$B$69*$C$69*G95*G96*$B$45*(1-$E$69*$B$50) | H105: =$B$69*$C$69*H95*H96*$B$45*(1-$E$69*$B$50) | I105: =$B$69*$C$69*I95*I96*$B$45*(1-$E$69*$B$50) | J105: =$B$69*$C$69*J95*J96*$B$45*(1-$E$69*$B$50) | ... L105: =$B$69*$C$69*L95*L96*$B$45*(1-$E$69*$B$50)
A106: Ventes privées / showcases B2B (soirées) | B106: =SUM(C106:L106) | C106: =$B$70*$C$70*C95*C96*$B$45*(1-$E$70*$B$50) | D106: =$B$70*$C$70*D95*D96*$B$45*(1-$E$70*$B$50) | E106: =$B$70*$C$70*E95*E96*$B$45*(1-$E$70*$B$50) | F106: =$B$70*$C$70*F95*F96*$B$45*(1-$E$70*$B$50) | G106: =$B$70*$C$70*G95*G96*$B$45*(1-$E$70*$B$50) | H106: =$B$70*$C$70*H95*H96*$B$45*(1-$E$70*$B$50) | I106: =$B$70*$C$70*I95*I96*$B$45*(1-$E$70*$B$50) | J106: =$B$70*$C$70*J95*J96*$B$45*(1-$E$70*$B$50) | ... L106: =$B$70*$C$70*L95*L96*$B$45*(1-$E$70*$B$50)
A107: Gains de compétition | B107: =SUM(C107:L107) | C107: =$B$71*$C$71*C95*C96*$B$45*(1-$E$71*$B$50) | D107: =$B$71*$C$71*D95*D96*$B$45*(1-$E$71*$B$50) | E107: =$B$71*$C$71*E95*E96*$B$45*(1-$E$71*$B$50) | F107: =$B$71*$C$71*F95*F96*$B$45*(1-$E$71*$B$50) | G107: =$B$71*$C$71*G95*G96*$B$45*(1-$E$71*$B$50) | H107: =$B$71*$C$71*H95*H96*$B$45*(1-$E$71*$B$50) | I107: =$B$71*$C$71*I95*I96*$B$45*(1-$E$71*$B$50) | J107: =$B$71*$C$71*J95*J96*$B$45*(1-$E$71*$B$50) | ... L107: =$B$71*$C$71*L95*L96*$B$45*(1-$E$71*$B$50)
A108: Gîte 15 couchages hors mariages (nuits) | B108: =SUM(C108:L108) | C108: =$B$72*$C$72*C95*C96*$B$45*(1-$E$72*$B$50) | D108: =$B$72*$C$72*D95*D96*$B$45*(1-$E$72*$B$50) | E108: =$B$72*$C$72*E95*E96*$B$45*(1-$E$72*$B$50) | F108: =$B$72*$C$72*F95*F96*$B$45*(1-$E$72*$B$50) | G108: =$B$72*$C$72*G95*G96*$B$45*(1-$E$72*$B$50) | H108: =$B$72*$C$72*H95*H96*$B$45*(1-$E$72*$B$50) | I108: =$B$72*$C$72*I95*I96*$B$45*(1-$E$72*$B$50) | J108: =$B$72*$C$72*J95*J96*$B$45*(1-$E$72*$B$50) | ... L108: =$B$72*$C$72*L95*L96*$B$45*(1-$E$72*$B$50)
A109: Tournages / shootings (jours) | B109: =SUM(C109:L109) | C109: =$B$73*$C$73*C95*C96*$B$45*(1-$E$73*$B$50) | D109: =$B$73*$C$73*D95*D96*$B$45*(1-$E$73*$B$50) | E109: =$B$73*$C$73*E95*E96*$B$45*(1-$E$73*$B$50) | F109: =$B$73*$C$73*F95*F96*$B$45*(1-$E$73*$B$50) | G109: =$B$73*$C$73*G95*G96*$B$45*(1-$E$73*$B$50) | H109: =$B$73*$C$73*H95*H96*$B$45*(1-$E$73*$B$50) | I109: =$B$73*$C$73*I95*I96*$B$45*(1-$E$73*$B$50) | J109: =$B$73*$C$73*J95*J96*$B$45*(1-$E$73*$B$50) | ... L109: =$B$73*$C$73*L95*L96*$B$45*(1-$E$73*$B$50)
A110: Fermage / vente d'herbe (ha) | B110: =SUM(C110:L110) | C110: =$B$74*$C$74*C95*C96*$B$45*(1-$E$74*$B$50) | D110: =$B$74*$C$74*D95*D96*$B$45*(1-$E$74*$B$50) | E110: =$B$74*$C$74*E95*E96*$B$45*(1-$E$74*$B$50) | F110: =$B$74*$C$74*F95*F96*$B$45*(1-$E$74*$B$50) | G110: =$B$74*$C$74*G95*G96*$B$45*(1-$E$74*$B$50) | H110: =$B$74*$C$74*H95*H96*$B$45*(1-$E$74*$B$50) | I110: =$B$74*$C$74*I95*I96*$B$45*(1-$E$74*$B$50) | J110: =$B$74*$C$74*J95*J96*$B$45*(1-$E$74*$B$50) | ... L110: =$B$74*$C$74*L95*L96*$B$45*(1-$E$74*$B$50)
A111: Chiffre d'affaires total | B111: =SUM(C111:L111) | C111: =C101+C102+C103+C104+C105+C106+C107+C108+C109+C110 | D111: =D101+D102+D103+D104+D105+D106+D107+D108+D109+D110 | E111: =E101+E102+E103+E104+E105+E106+E107+E108+E109+E110 | F111: =F101+F102+F103+F104+F105+F106+F107+F108+F109+F110 | G111: =G101+G102+G103+G104+G105+G106+G107+G108+G109+G110 | H111: =H101+H102+H103+H104+H105+H106+H107+H108+H109+H110 | I111: =I101+I102+I103+I104+I105+I106+I107+I108+I109+I110 | J111: =J101+J102+J103+J104+J105+J106+J107+J108+J109+J110 | ... L111: =L101+L102+L103+L104+L105+L106+L107+L108+L109+L110
...

Sheet A_optimiste
A1: Scénario A — Château équestre « sport » — cas optimiste
A2: Cellules jaunes/bleues = hypothèses éditables. Tout le reste est calculé. Colonne D (bloc hypothèses) = source ou statut (ESTIMATION = non vérifiée).
A4: 1. Calendrier, acquisition et travaux
A5: Année d'acquisition des murs (1 = immédiate) | B5: 1 | C5: année | D5: Achat immédiat (2027)
A6: Année d'ouverture commerciale (avant stress) | B6: 2 | C6: année | D6: Année 1 = travaux ; EST
A7: Prix d'acquisition | B7: 2500000 | C7: € | D7: PL : médiane de 19 annonces de châteaux ≥ 30 ha (quartiles 1,29-3,07 M€) [A1]
A8: Frais d'acquisition (droits + notaire) | B8: 0.075 | C8: % | D8: EST : DMTO ≈ 5,8-6,3 % + notaire ≈ 1,2 % ; vente SAFER : frais 8,4 % TTC mais exonération de droits possible [A1, PL]
A9: Part du prix affectable au bâti (amortissable) | B9: 0.55 | C9: % | D9: EST
A10: Travaux de restauration / mise aux normes | B10: 500000 | C10: € | D10: EST sans visite : top 5 des biens équipés 0,1-0,7 M€ [A1]
A11: Investissements équestres (boxes, carrière, manège…) | B11: 350000 | C11: € | D11: EST : marcheur 35 k€, carrière 35 €/m², barn 200 €/m² (PL [A3 H19]) + 10 box supplémentaires
A12: Investissements événementiel / hébergement | B12: 80000 | C12: € | D12: EST : salon de réception pour ventes privées, pas de salle ERP > 50 pers.
A13: Répartition travaux : année d'acquisition | B13: 0.6 | C13: % | D13: EST
A14: Répartition travaux : année +1 | B14: 0.3 | C14: % | D14: EST
A15: Répartition travaux : année +2 | B15: 0.1 | C15: % | D15: EST
A16: Gros entretien patrimonial annuel (% prix+travaux) | B16: 0.018 | C16: % | D16: ≈ 41 k€/an sur (bâti + travaux) : Demeure Historique ≥ 40 k€/an hors restauration (PL [A8]) ; Barnes 20-80 k€/an [A4 §11] ; démarre en année d'acquisition + 3
... A20: Loyer de la partie privée payé par le fondateur (hors CA d'exploitation) | B20: 0 | C20: € | D20: Correction audit M1 : aucun loyer privé compté — le logis doit être détenu à part (SCI à l'IR, hors taxe 235 ter C [A6]) et payé par le fondateur personnellement
A22: 2. Financement
A23: Apport du fondateur (année 1) | B23: 1000000 | C23: € | D23: Scénario d'apport S3 (hypothèse ; apport réel inconnu)
A24: Fonds propres apportés à l'acquisition (investisseurs ou holding) | B24: 0 | C24: € | D24: Aucun investisseur
A25: Ces fonds propres viennent-ils de la holding du fondateur ? (1/0) | B25: 0
A26: Subventions (non acquises : 0 par défaut) | B26: 0 | C26: € | D26: Aucune subvention considérée comme acquise
A27: Dette bancaire (année d'acquisition) | B27: 2400000 | C27: € | D27: NON ACQUIS — montage 1 [A2] : prêt hypothécaire 20 ans ; LTV ≈ 70 %, jugée trop élevée par l'agent 2
A28: Taux de la dette bancaire | B28: 0.04 | C28: % | D28: PL : nouveaux crédits PME 3,64 % (FBF, 06/2026) ; EX : 3,66 % (BdF, 08/2026) ; retenu 4,0 % [A2]
A29: Durée dette bancaire | B29: 20 | C29: ans | D29: A2 (Bpifrance : 15 ans avec hypothèque, PL)
A30: Différé d'amortissement (dans la durée) | B30: 1 | C30: ans | D30: EST
A31: Crédit-vendeur | B31: 0 | C31: €
A32: Taux crédit-vendeur | B32: 0.03 | C32: % | D32: EST
A33: Durée crédit-vendeur (amortissable) | B33: 12 | C33: ans | D33: EST
A34: Obligations / quasi-fonds propres (in fine) | B34: 0 | C34: €
A35: Coupon annuel des obligations | B35: 0.07 | C35: % | D35: PL : obligations Château Fontenay 7 % [A2]
A36: Année de remboursement des obligations | B36: 6 | C36: année | D36: EST
A37: Part de capital supplémentaire accordée au fondateur pour son travail (sweat equity) | B37: 0 | C37: % | D37: Fondateur seul
A38: Droits de vote du fondateur | B38: 1 | C38: %
A39: Réserve de liquidité cible | B39: 150000 | C39: € | D39: EST
A40: TRI minimal exigé par des investisseurs extérieurs | B40: 0.06 | C40: % | D40: EST : rendement minimal d'un investisseur en fonds propres illiquide (Anaxago affiche 8,7 % net, PL [A2])
A41: Le dirigeant est-il rémunéré par le domaine ? (1/0) | B41: 1 | D41: Rémunération du dirigeant incluse
A42: Part du capital du fondateur (calculée : apports au prorata + prime d'industrie, plafonnée à 100 %) | B42: =MIN(1,($B$23+$B$24*$B$25)/MAX(1,$B$23+$B$24)+$B$37)
A44: 3. Paramètres de stress (neutres = 100 % / 0)
A45: Multiplicateur de chiffre d'affaires | B45: 1 | C45: % | D45: neutre
A46: Multiplicateur du budget travaux | B46: 1 | C46: % | D46: neutre
A47: Retard d'ouverture | B47: 0 | C47: ans | D47: neutre
A48: Hausse du taux bancaire (points) | B48: 0 | C48: % | D48: neutre
A49: Part des fonds investisseurs non versée | B49: 0 | C49: % | D49: neutre
A50: Part des événements annulés | B50: 0 | C50: % | D50: neutre
A52: 4. Exploitation — hypothèses générales
A53: Montée en charge : 1re année d'exploitation | B53: 0.6 | C53: % | D53: Cas optimiste
A54: Montée en charge : 2e année | B54: 0.9 | C54: % | D54: Cas optimiste
A55: Montée en charge : 3e année | B55: 1 | C55: % | D55: Cas optimiste
A56: Indexation annuelle des prix | B56: 0.02 | C56: % | D56: EST
A57: Inflation annuelle des charges | B57: 0.02 | C57: % | D57: EST : indexation identique aux prix (correction audit, biais pessimiste retiré)
A58: BFR en % du CA (négatif = acomptes clients) | B58: -0.03 | C58: % | D58: Acomptes (mariages, pensions payées d'avance) — EST
A59: Taux normal d'IS | B59: 0.25 | C59: % | D59: PL : IS 25 % au-delà de 42 500 € [A6]
A60: Taux réduit d'IS (PME, jusqu'au seuil) | B60: 0.15 | C60: % | D60: PL : 15 % jusqu'à 42 500 € (PME) [A6]
A61: Seuil du taux réduit d'IS | B61: 42500 | C61: € | D61: PL [A6]
A63: 5. Lignes de revenus (à maturité, euros de l'année d'ouverture)
A64: Libellé | B64: Volume | C64: Prix unitaire | D64: Coût var. % | E64: Événement ? | F64: Équestre ? | G64: Unité / source
A65: Pension travail (chevaux de sport, places occupées) | B65: 20.7 | C65: 6480 | D65: 0.29 | E65: 0 | F65: 1 | G65: PL : 600 € TTC/mois (médiane hors IdF 535 €, 3e quartile 612 €) [A3, recalcul A8] → 500 € HT à TVA 20 % (entraînement/valorisation) ; 20 places × 90 % ; coûts op. 1 729 €/an
A66: Pension box premium (places occupées) | B66: 10.3 | C66: 6388 | D66: 0.2 | E66: 0 | F66: 1 | G66: Cf. B ; 10 places × 90 %
A67: Pension au pré (places occupées) | B67: 16.1 | C67: 2825 | D67: 0.23 | E67: 0 | F67: 1 | G67: Cf. B ; 15 places × 92 %
A68: Valorisation et vente de jeunes chevaux (marge nette par cheval vendu) | B68: 3.4 | C68: 10773 | D68: 0.1 | E68: 0 | F68: 1 | G68: PL : cas-type 2 chevaux/an, 36,75 k€ vendus − 16,8 k€ achetés [A3 §8] ; 3/an EST ; risque élevé
A69: Organisation de concours (produit annuel) | B69: 1.1 | C69: 17362 | D69: 0.5 | E69: 1 | F69: 1 | G69: PL : produit moyen « organisation de concours » d'une pension travail 16 076 €/an [A3 §4] ; marge EST
A70: Ventes privées / showcases B2B (soirées) | B70: 3.4 | C70: 3240 | D70: 0.4 | E70: 1 | F70: 1 | G70: INC : aucun tarif de location publié [A3 §8 n°10] ; EST
A71: Gains de compétition | B71: 1.1 | C71: 13230 | D71: 0 | E71: 1 | F71: 1 | G71: PL : cas-type CSO 2025 12 250 € [A3 §4]
A72: Gîte 15 couchages hors mariages (nuits) | B72: 105.8 | C72: 486 | D72: 0.45 | E72: 0 | F72: 0 | G72: PL : fourchettes de prix [A4 §4.2] ; 92 nuits EST (occupation annuelle ≈ 33 % observée en Normandie hors saison) [A4 §4.3]
A73: Tournages / shootings (jours) | B73: 3.4 | C73: 2160 | D73: 0.15 | E73: 1 | F73: 0 | G73: PL : 1 500-4 000 €/jour [A4 §5] ; fréquence EST
A74: Fermage / vente d'herbe (ha) | B74: 11.5 | C74: 162 | D74: 0 | E74: 0 | F74: 0 | G74: PL : arrêtés Orne/Calvados 2026-27 : 50-268 €/ha [A4 §8.2]
A76: 6. Charges fixes annuelles (euros de l'année d'ouverture)
A77: Libellé | B77: Montant/an | C77: Dès l'acq. (1) / dès l'ouverture (0) | G77: Source / statut
A78: Taxe foncière | B78: 5700 | C78: 1 | G78: EX : 2,6-4,0 k€ sur 3 annonces ; EST 4-8 k€ [A4 §11]
A79: Assurance multirisque château | B79: 11400 | C79: 1 | G79: Correction audit : courtier spécialisé 15-30 k€ (fiabilité moyenne), annonces ≥ 2,5 k€ [A4 §11, A8] ; EST 12 k€
A80: Énergie (chauffage partiel, électricité, eau) | B80: 19000 | C80: 1 | G80: PL : Meung, Louvignies ; EX annonce Montluçon 18-25 k€ [A1, A4 §11] ; EST
A81: Jardinier / agent d'entretien (1 ETP au Smic chargé) | B81: 25650 | C81: 1 | G81: PL : Smic 2026 22 404 € brut/an [A4 §11] ; EST charges
A82: Divers (abonnements, petit matériel, véhicule, honoraires) | B82: 7600 | C82: 1 | G82: EST
A83: Cavalier professionnel / responsable d'écurie (chargé) | B83: 42750 | C83: 0 | G83: PL : grille 2 108-2 678 € brut (coef. 130-167) [A3 H15] ; EST charges
A84: Soigneurs / cavaliers-soigneurs (2,5 ETP chargés) | B84: 74100 | C84: 0 | G84: PL [A3 H13-H14] ; 10 chevaux au travail / ETP ; ~45 équidés
A85: Autres charges de structure équestres | B85: 33250 | C85: 0 | G85: EST : réf. structure pension travail 2 471 €/équidé [A3 §4] (salaires inclus) → calibrage
A86: Coûts fixes du gîte | B86: 4180 | C86: 0 | G86: EST [A4 §13.1]
A87: Commercial, site, salons | B87: 11400 | C87: 0 | G87: EST
A88: Comptabilité, juridique, banque, logiciels | B88: 11400 | C88: 0 | G88: EST
A89: Rémunération du dirigeant (chargée) | B89: 33250 | C89: 0 | G89: EST : minimum ; le dirigeant paie en plus 18 k€ de loyer privé
A91: 7. Calcul sur 10 ans
A92: Année | B92: Total / réf. | C92: 1 | D92: 2 | E92: 3 | F92: 4 | G92: 5 | H92: 6 | I92: 7 | J92: 8 | K92: 9 | L92: 10
A93: Année d'ouverture effective | C93: =$B$6+$B$47 | D93: =$B$6+$B$47 | E93: =$B$6+$B$47 | F93: =$B$6+$B$47 | G93: =$B$6+$B$47 | H93: =$B$6+$B$47 | I93: =$B$6+$B$47 | J93: =$B$6+$B$47 | ... L93: =$B$6+$B$47
A94: Rang de l'année d'exploitation | C94: =MAX(0,C$92-C93+1) | D94: =MAX(0,D$92-D93+1) | E94: =MAX(0,E$92-E93+1) | F94: =MAX(0,F$92-F93+1) | G94: =MAX(0,G$92-G93+1) | H94: =MAX(0,H$92-H93+1) | I94: =MAX(0,I$92-I93+1) | J94: =MAX(0,J$92-J93+1) | ... L94: =MAX(0,L$92-L93+1)
A95: Coefficient de montée en charge | C95: =IF(C94=0,0,IF(C94=1,$B$53,IF(C94=2,$B$54,IF(C94=3,$B$55,1)))) | D95: =IF(D94=0,0,IF(D94=1,$B$53,IF(D94=2,$B$54,IF(D94=3,$B$55,1)))) | E95: =IF(E94=0,0,IF(E94=1,$B$53,IF(E94=2,$B$54,IF(E94=3,$B$55,1)))) | F95: =IF(F94=0,0,IF(F94=1,$B$53,IF(F94=2,$B$54,IF(F94=3,$B$55,1)))) | G95: =IF(G94=0,0,IF(G94=1,$B$53,IF(G94=2,$B$54,IF(G94=3,$B$55,1)))) | H95: =IF(H94=0,0,IF(H94=1,$B$53,IF(H94=2,$B$54,IF(H94=3,$B$55,1)))) | I95: =IF(I94=0,0,IF(I94=1,$B$53,IF(I94=2,$B$54,IF(I94=3,$B$55,1)))) | J95: =IF(J94=0,0,IF(J94=1,$B$53,IF(J94=2,$B$54,IF(J94=3,$B$55,1)))) | ... L95: =IF(L94=0,0,IF(L94=1,$B$53,IF(L94=2,$B$54,IF(L94=3,$B$55,1))))
A96: Indice prix | C96: =(1+$B$56)^(C$92-1) | D96: =(1+$B$56)^(D$92-1) | E96: =(1+$B$56)^(E$92-1) | F96: =(1+$B$56)^(F$92-1) | G96: =(1+$B$56)^(G$92-1) | H96: =(1+$B$56)^(H$92-1) | I96: =(1+$B$56)^(I$92-1) | J96: =(1+$B$56)^(J$92-1) | ... L96: =(1+$B$56)^(L$92-1)
A97: Indice charges | C97: =(1+$B$57)^(C$92-1) | D97: =(1+$B$57)^(D$92-1) | E97: =(1+$B$57)^(E$92-1) | F97: =(1+$B$57)^(F$92-1) | G97: =(1+$B$57)^(G$92-1) | H97: =(1+$B$57)^(H$92-1) | I97: =(1+$B$57)^(I$92-1) | J97: =(1+$B$57)^(J$92-1) | ... L97: =(1+$B$57)^(L$92-1)
A98: Murs détenus (1/0) | C98: =IF(C$92>=$B$5,1,0) | D98: =IF(D$92>=$B$5,1,0) | E98: =IF(E$92>=$B$5,1,0) | F98: =IF(F$92>=$B$5,1,0) | G98: =IF(G$92>=$B$5,1,0) | H98: =IF(H$92>=$B$5,1,0) | I98: =IF(I$92>=$B$5,1,0) | J98: =IF(J$92>=$B$5,1,0) | ... L98: =IF(L$92>=$B$5,1,0)
A100: Compte de résultat
A101: Pension travail (chevaux de sport, places occupées) | B101: =SUM(C101:L101) | C101: =$B$65*$C$65*C95*C96*$B$45*(1-$E$65*$B$50) | D101: =$B$65*$C$65*D95*D96*$B$45*(1-$E$65*$B$50) | E101: =$B$65*$C$65*E95*E96*$B$45*(1-$E$65*$B$50) | F101: =$B$65*$C$65*F95*F96*$B$45*(1-$E$65*$B$50) | G101: =$B$65*$C$65*G95*G96*$B$45*(1-$E$65*$B$50) | H101: =$B$65*$C$65*H95*H96*$B$45*(1-$E$65*$B$50) | I101: =$B$65*$C$65*I95*I96*$B$45*(1-$E$65*$B$50) | J101: =$B$65*$C$65*J95*J96*$B$45*(1-$E$65*$B$50) | ... L101: =$B$65*$C$65*L95*L96*$B$45*(1-$E$65*$B$50)
A102: Pension box premium (places occupées) | B102: =SUM(C102:L102) | C102: =$B$66*$C$66*C95*C96*$B$45*(1-$E$66*$B$50) | D102: =$B$66*$C$66*D95*D96*$B$45*(1-$E$66*$B$50) | E102: =$B$66*$C$66*E95*E96*$B$45*(1-$E$66*$B$50) | F102: =$B$66*$C$66*F95*F96*$B$45*(1-$E$66*$B$50) | G102: =$B$66*$C$66*G95*G96*$B$45*(1-$E$66*$B$50) | H102: =$B$66*$C$66*H95*H96*$B$45*(1-$E$66*$B$50) | I102: =$B$66*$C$66*I95*I96*$B$45*(1-$E$66*$B$50) | J102: =$B$66*$C$66*J95*J96*$B$45*(1-$E$66*$B$50) | ... L102: =$B$66*$C$66*L95*L96*$B$45*(1-$E$66*$B$50)
A103: Pension au pré (places occupées) | B103: =SUM(C103:L103) | C103: =$B$67*$C$67*C95*C96*$B$45*(1-$E$67*$B$50) | D103: =$B$67*$C$67*D95*D96*$B$45*(1-$E$67*$B$50) | E103: =$B$67*$C$67*E95*E96*$B$45*(1-$E$67*$B$50) | F103: =$B$67*$C$67*F95*F96*$B$45*(1-$E$67*$B$50) | G103: =$B$67*$C$67*G95*G96*$B$45*(1-$E$67*$B$50) | H103: =$B$67*$C$67*H95*H96*$B$45*(1-$E$67*$B$50) | I103: =$B$67*$C$67*I95*I96*$B$45*(1-$E$67*$B$50) | J103: =$B$67*$C$67*J95*J96*$B$45*(1-$E$67*$B$50) | ... L103: =$B$67*$C$67*L95*L96*$B$45*(1-$E$67*$B$50)
A104: Valorisation et vente de jeunes chevaux (marge nette par cheval vendu) | B104: =SUM(C104:L104) | C104: =$B$68*$C$68*C95*C96*$B$45*(1-$E$68*$B$50) | D104: =$B$68*$C$68*D95*D96*$B$45*(1-$E$68*$B$50) | E104: =$B$68*$C$68*E95*E96*$B$45*(1-$E$68*$B$50) | F104: =$B$68*$C$68*F95*F96*$B$45*(1-$E$68*$B$50) | G104: =$B$68*$C$68*G95*G96*$B$45*(1-$E$68*$B$50) | H104: =$B$68*$C$68*H95*H96*$B$45*(1-$E$68*$B$50) | I104: =$B$68*$C$68*I95*I96*$B$45*(1-$E$68*$B$50) | J104: =$B$68*$C$68*J95*J96*$B$45*(1-$E$68*$B$50) | ... L104: =$B$68*$C$68*L95*L96*$B$45*(1-$E$68*$B$50)
A105: Organisation de concours (produit annuel) | B105: =SUM(C105:L105) | C105: =$B$69*$C$69*C95*C96*$B$45*(1-$E$69*$B$50) | D105: =$B$69*$C$69*D95*D96*$B$45*(1-$E$69*$B$50) | E105: =$B$69*$C$69*E95*E96*$B$45*(1-$E$69*$B$50) | F105: =$B$69*$C$69*F95*F96*$B$45*(1-$E$69*$B$50) | G105: =$B$69*$C$69*G95*G96*$B$45*(1-$E$69*$B$50) | H105: =$B$69*$C$69*H95*H96*$B$45*(1-$E$69*$B$50) | I105: =$B$69*$C$69*I95*I96*$B$45*(1-$E$69*$B$50) | J105: =$B$69*$C$69*J95*J96*$B$45*(1-$E$69*$B$50) | ... L105: =$B$69*$C$69*L95*L96*$B$45*(1-$E$69*$B$50)
A106: Ventes privées / showcases B2B (soirées) | B106: =SUM(C106:L106) | C106: =$B$70*$C$70*C95*C96*$B$45*(1-$E$70*$B$50) | D106: =$B$70*$C$70*D95*D96*$B$45*(1-$E$70*$B$50) | E106: =$B$70*$C$70*E95*E96*$B$45*(1-$E$70*$B$50) | F106: =$B$70*$C$70*F95*F96*$B$45*(1-$E$70*$B$50) | G106: =$B$70*$C$70*G95*G96*$B$45*(1-$E$70*$B$50) | H106: =$B$70*$C$70*H95*H96*$B$45*(1-$E$70*$B$50) | I106: =$B$70*$C$70*I95*I96*$B$45*(1-$E$70*$B$50) | J106: =$B$70*$C$70*J95*J96*$B$45*(1-$E$70*$B$50) | ... L106: =$B$70*$C$70*L95*L96*$B$45*(1-$E$70*$B$50)
A107: Gains de compétition | B107: =SUM(C107:L107) | C107: =$B$71*$C$71*C95*C96*$B$45*(1-$E$71*$B$50) | D107: =$B$71*$C$71*D95*D96*$B$45*(1-$E$71*$B$50) | E107: =$B$71*$C$71*E95*E96*$B$45*(1-$E$71*$B$50) | F107: =$B$71*$C$71*F95*F96*$B$45*(1-$E$71*$B$50) | G107: =$B$71*$C$71*G95*G96*$B$45*(1-$E$71*$B$50) | H107: =$B$71*$C$71*H95*H96*$B$45*(1-$E$71*$B$50) | I107: =$B$71*$C$71*I95*I96*$B$45*(1-$E$71*$B$50) | J107: =$B$71*$C$71*J95*J96*$B$45*(1-$E$71*$B$50) | ... L107: =$B$71*$C$71*L95*L96*$B$45*(1-$E$71*$B$50)
A108: Gîte 15 couchages hors mariages (nuits) | B108: =SUM(C108:L108) | C108: =$B$72*$C$72*C95*C96*$B$45*(1-$E$72*$B$50) | D108: =$B$72*$C$72*D95*D96*$B$45*(1-$E$72*$B$50) | E108: =$B$72*$C$72*E95*E96*$B$45*(1-$E$72*$B$50) | F108: =$B$72*$C$72*F95*F96*$B$45*(1-$E$72*$B$50) | G108: =$B$72*$C$72*G95*G96*$B$45*(1-$E$72*$B$50) | H108: =$B$72*$C$72*H95*H96*$B$45*(1-$E$72*$B$50) | I108: =$B$72*$C$72*I95*I96*$B$45*(1-$E$72*$B$50) | J108: =$B$72*$C$72*J95*J96*$B$45*(1-$E$72*$B$50) | ... L108: =$B$72*$C$72*L95*L96*$B$45*(1-$E$72*$B$50)
A109: Tournages / shootings (jours) | B109: =SUM(C109:L109) | C109: =$B$73*$C$73*C95*C96*$B$45*(1-$E$73*$B$50) | D109: =$B$73*$C$73*D95*D96*$B$45*(1-$E$73*$B$50) | E109: =$B$73*$C$73*E95*E96*$B$45*(1-$E$73*$B$50) | F109: =$B$73*$C$73*F95*F96*$B$45*(1-$E$73*$B$50) | G109: =$B$73*$C$73*G95*G96*$B$45*(1-$E$73*$B$50) | H109: =$B$73*$C$73*H95*H96*$B$45*(1-$E$73*$B$50) | I109: =$B$73*$C$73*I95*I96*$B$45*(1-$E$73*$B$50) | J109: =$B$73*$C$73*J95*J96*$B$45*(1-$E$73*$B$50) | ... L109: =$B$73*$C$73*L95*L96*$B$45*(1-$E$73*$B$50)
A110: Fermage / vente d'herbe (ha) | B110: =SUM(C110:L110) | C110: =$B$74*$C$74*C95*C96*$B$45*(1-$E$74*$B$50) | D110: =$B$74*$C$74*D95*D96*$B$45*(1-$E$74*$B$50) | E110: =$B$74*$C$74*E95*E96*$B$45*(1-$E$74*$B$50) | F110: =$B$74*$C$74*F95*F96*$B$45*(1-$E$74*$B$50) | G110: =$B$74*$C$74*G95*G96*$B$45*(1-$E$74*$B$50) | H110: =$B$74*$C$74*H95*H96*$B$45*(1-$E$74*$B$50) | I110: =$B$74*$C$74*I95*I96*$B$45*(1-$E$74*$B$50) | J110: =$B$74*$C$74*J95*J96*$B$45*(1-$E$74*$B$50) | ... L110: =$B$74*$C$74*L95*L96*$B$45*(1-$E$74*$B$50)
A111: Chiffre d'affaires total | B111: =SUM(C111:L111) | C111: =C101+C102+C103+C104+C105+C106+C107+C108+C109+C110 | D111: =D101+D102+D103+D104+D105+D106+D107+D108+D109+D110 | E111: =E101+E102+E103+E104+E105+E106+E107+E108+E109+E110 | F111: =F101+F102+F103+F104+F105+F106+F107+F108+F109+F110 | G111: =G101+G102+G103+G104+G105+G106+G107+G108+G109+G110 | H111: =H101+H102+H103+H104+H105+H106+H107+H108+H109+H110 | I111: =I101+I102+I103+I104+I105+I106+I107+I108+I109+I110 | J111: =J101+J102+J103+J104+J105+J106+J107+J108+J109+J110 | ... L111: =L101+L102+L103+L104+L105+L106+L107+L108+L109+L110
...

Sheet B_central
A1: Scénario B — Château multiactivité — cas central
A2: Cellules jaunes/bleues = hypothèses éditables. Tout le reste est calculé. Colonne D (bloc hypothèses) = source ou statut (ESTIMATION = non vérifiée).
A4: 1. Calendrier, acquisition et travaux
A5: Année d'acquisition des murs (1 = immédiate) | B5: 1 | C5: année | D5: Achat immédiat (2027)
A6: Année d'ouverture commerciale (avant stress) | B6: 2 | C6: année | D6: Année 1 = travaux ; EST
A7: Prix d'acquisition | B7: 2500000 | C7: € | D7: PL : médiane de 19 annonces de châteaux ≥ 30 ha (quartiles 1,29-3,07 M€) [A1]
A8: Frais d'acquisition (droits + notaire) | B8: 0.075 | C8: % | D8: EST : DMTO ≈ 5,8-6,3 % + notaire ≈ 1,2 % ; vente SAFER : frais 8,4 % TTC mais exonération de droits possible [A1, PL]
A9: Part du prix affectable au bâti (amortissable) | B9: 0.55 | C9: % | D9: EST
A10: Travaux de restauration / mise aux normes | B10: 500000 | C10: € | D10: EST sans visite : top 5 des biens équipés 0,1-0,7 M€ [A1]
A11: Investissements équestres (boxes, carrière, manège…) | B11: 150000 | C11: € | D11: EST : remise à niveau d'écuries existantes (une écurie neuve de 30 box coûterait 0,78-0,83 M€ HT [A3 H20])
A12: Investissements événementiel / hébergement | B12: 250000 | C12: € | D12: EST : mise aux normes d'une salle existante + aménagement du gîte (neuf : 570 k€-1,24 M€ [A4 §13.2])
A13: Répartition travaux : année d'acquisition | B13: 0.6 | C13: % | D13: EST
A14: Répartition travaux : année +1 | B14: 0.3 | C14: % | D14: EST
A15: Répartition travaux : année +2 | B15: 0.1 | C15: % | D15: EST
A16: Gros entretien patrimonial annuel (% prix+travaux) | B16: 0.018 | C16: % | D16: ≈ 41 k€/an sur (bâti + travaux) : Demeure Historique ≥ 40 k€/an hors restauration (PL [A8]) ; Barnes 20-80 k€/an [A4 §11] ; démarre en année d'acquisition + 3
... A20: Loyer de la partie privée payé par le fondateur (hors CA d'exploitation) | B20: 0 | C20: € | D20: Correction audit M1 : aucun loyer privé compté — le logis doit être détenu à part (SCI à l'IR, hors taxe 235 ter C [A6]) et payé par le fondateur personnellement
A22: 2. Financement
A23: Apport du fondateur (année 1) | B23: 1000000 | C23: € | D23: Scénario d'apport S3 (hypothèse ; apport réel inconnu)
A24: Fonds propres apportés à l'acquisition (investisseurs ou holding) | B24: 0 | C24: € | D24: Aucun investisseur
A25: Ces fonds propres viennent-ils de la holding du fondateur ? (1/0) | B25: 0
A26: Subventions (non acquises : 0 par défaut) | B26: 0 | C26: € | D26: Aucune subvention considérée comme acquise
A27: Dette bancaire (année d'acquisition) | B27: 2400000 | C27: € | D27: NON ACQUIS — montage 1 [A2] : prêt hypothécaire 20 ans ; LTV ≈ 70 %, jugée trop élevée par l'agent 2
A28: Taux de la dette bancaire | B28: 0.04 | C28: % | D28: PL : nouveaux crédits PME 3,64 % (FBF, 06/2026) ; EX : 3,66 % (BdF, 08/2026) ; retenu 4,0 % [A2]
A29: Durée dette bancaire | B29: 20 | C29: ans | D29: A2 (Bpifrance : 15 ans avec hypothèque, PL)
A30: Différé d'amortissement (dans la durée) | B30: 1 | C30: ans | D30: EST
A31: Crédit-vendeur | B31: 0 | C31: €
A32: Taux crédit-vendeur | B32: 0.03 | C32: % | D32: EST
A33: Durée crédit-vendeur (amortissable) | B33: 12 | C33: ans | D33: EST
A34: Obligations / quasi-fonds propres (in fine) | B34: 0 | C34: €
A35: Coupon annuel des obligations | B35: 0.07 | C35: % | D35: PL : obligations Château Fontenay 7 % [A2]
A36: Année de remboursement des obligations | B36: 6 | C36: année | D36: EST
A37: Part de capital supplémentaire accordée au fondateur pour son travail (sweat equity) | B37: 0 | C37: % | D37: Fondateur seul
A38: Droits de vote du fondateur | B38: 1 | C38: %
A39: Réserve de liquidité cible | B39: 150000 | C39: € | D39: EST
A40: TRI minimal exigé par des investisseurs extérieurs | B40: 0.06 | C40: % | D40: EST : rendement minimal d'un investisseur en fonds propres illiquide (Anaxago affiche 8,7 % net, PL [A2])
A41: Le dirigeant est-il rémunéré par le domaine ? (1/0) | B41: 1 | D41: Rémunération du dirigeant incluse
A42: Part du capital du fondateur (calculée : apports au prorata + prime d'industrie, plafonnée à 100 %) | B42: =MIN(1,($B$23+$B$24*$B$25)/MAX(1,$B$23+$B$24)+$B$37)
A44: 3. Paramètres de stress (neutres = 100 % / 0)
A45: Multiplicateur de chiffre d'affaires | B45: 1 | C45: % | D45: neutre
A46: Multiplicateur du budget travaux | B46: 1 | C46: % | D46: neutre
A47: Retard d'ouverture | B47: 0 | C47: ans | D47: neutre
A48: Hausse du taux bancaire (points) | B48: 0 | C48: % | D48: neutre
A49: Part des fonds investisseurs non versée | B49: 0 | C49: % | D49: neutre
A50: Part des événements annulés | B50: 0 | C50: % | D50: neutre
A52: 4. Exploitation — hypothèses générales
A53: Montée en charge : 1re année d'exploitation | B53: 0.5 | C53: % | D53: A4 : mariages 40/70/100 % ; gîte 50/80/100 %
A54: Montée en charge : 2e année | B54: 0.8 | C54: % | D54: EST
A55: Montée en charge : 3e année | B55: 1 | C55: % | D55: EST
A56: Indexation annuelle des prix | B56: 0.02 | C56: % | D56: EST
A57: Inflation annuelle des charges | B57: 0.02 | C57: % | D57: EST : indexation identique aux prix (correction audit, biais pessimiste retiré)
A58: BFR en % du CA (négatif = acomptes clients) | B58: -0.03 | C58: % | D58: Acomptes (mariages, pensions payées d'avance) — EST
A59: Taux normal d'IS | B59: 0.25 | C59: % | D59: PL : IS 25 % au-delà de 42 500 € [A6]
A60: Taux réduit d'IS (PME, jusqu'au seuil) | B60: 0.15 | C60: % | D60: PL : 15 % jusqu'à 42 500 € (PME) [A6]
A61: Seuil du taux réduit d'IS | B61: 42500 | C61: € | D61: PL [A6]
A63: 5. Lignes de revenus (à maturité, euros de l'année d'ouverture)
A64: Libellé | B64: Volume | C64: Prix unitaire | D64: Coût var. % | E64: Événement ? | F64: Équestre ? | G64: Unité / source
A65: Pension box premium (places occupées) | B65: 22 | C65: 5118 | D65: 0.23 | E65: 0 | F65: 1 | G65: PL : 450 € TTC/mois = 3e quartile hors IdF (médiane 375 €, 10 % des offres ≥ 520 €) [A3, recalcul A8] → 426,5 € HT à TVA 5,5 % ; 24 box × 92 % ; coûts directs 1 200 €/an EST
A66: Pension au pré (places occupées) | B66: 23 | C66: 2502 | D66: 0.245 | E66: 0 | F66: 1 | G66: PL : 220 € TTC/mois (médianes 200-240 €) → 208,5 € HT [A3 H3] ; 25 places × 92 % ; coûts 613 €/an [A3 §4]
A67: Pension retraite / convalescence (places occupées) | B67: 9 | C67: 2100 | D67: 0.24 | E67: 0 | F67: 1 | G67: PL : 210 € TTC/mois, TVA 20 % → 175 € HT [A3 H4] ; 10 places × 90 %
A68: Mariages (location du lieu + hébergement 15 couchages) | B68: 12 | C68: 4197 | D68: 0.43 | E68: 1 | F68: 0 | G68: PL : médiane 3 400 € TTC location (17 châteaux) + 1 500 € TTC hébergement → 4 197 € HT [A4 §13.1] ; 12/an EST ; coût variable 1 450 € + 8 %
A69: Gîte 15 couchages hors mariages (nuits) | B69: 92 | C69: 450 | D69: 0.45 | E69: 0 | F69: 0 | G69: PL : fourchettes de prix [A4 §4.2] ; 92 nuits EST (occupation annuelle ≈ 33 % observée en Normandie hors saison) [A4 §4.3]
A70: Séminaires à la journée (jours) | B70: 12 | C70: 800 | D70: 0.19 | E70: 1 | F70: 0 | G70: PL : salle 1 000 €/jour (Feugerets) ; 800 € HT retenu [A4 §3]
A71: Tournages / shootings (jours) | B71: 3 | C71: 2000 | D71: 0.15 | E71: 1 | F71: 0 | G71: PL : 1 500-4 000 €/jour [A4 §5] ; fréquence EST
A72: Fermage / vente d'herbe (ha) | B72: 10 | C72: 150 | D72: 0 | E72: 0 | F72: 0 | G72: PL : arrêtés Orne/Calvados 2026-27 : 50-268 €/ha [A4 §8.2]
A74: 6. Charges fixes annuelles (euros de l'année d'ouverture)
A75: Libellé | B75: Montant/an | C75: Dès l'acq. (1) / dès l'ouverture (0) | G75: Source / statut
A76: Taxe foncière | B76: 6000 | C76: 1 | G76: EX : 2,6-4,0 k€ sur 3 annonces ; EST 4-8 k€ [A4 §11]
A77: Assurance multirisque château | B77: 12000 | C77: 1 | G77: Correction audit : courtier spécialisé 15-30 k€ (fiabilité moyenne), annonces ≥ 2,5 k€ [A4 §11, A8] ; EST 12 k€
A78: Énergie (chauffage partiel, électricité, eau) | B78: 20000 | C78: 1 | G78: PL : Meung, Louvignies ; EX annonce Montluçon 18-25 k€ [A1, A4 §11] ; EST
A79: Jardinier / agent d'entretien (1 ETP au Smic chargé) | B79: 27000 | C79: 1 | G79: PL : Smic 2026 22 404 € brut/an [A4 §11] ; EST charges
A80: Divers (abonnements, petit matériel, véhicule, honoraires) | B80: 8000 | C80: 1 | G80: EST
A81: Soigneurs (3 ETP au Smic chargés) | B81: 90000 | C81: 0 | G81: PL : Smic 1 867 €/mois, grille IDCC 7026 inférieure ; 1 ETP / 17-20 équidés [A3 H13-H14] ; ~54 équidés → 3 ETP (correction audit M5)
A82: Autres charges de structure équestres (entretien installations, matériel, assurance RC, énergie écuries) | B82: 30000 | C82: 0 | G82: Calibré pour un EBE équestre ≈ 37 % (réf. pension hébergement 36-38 %, PL [A3 H10])
A83: Coûts fixes mariages (coordination, nettoyage, publicité) | B83: 11000 | C83: 0 | G83: EST [A4 §13.1]
A84: Coûts fixes du gîte | B84: 4400 | C84: 0 | G84: EST [A4 §13.1]
A85: Commercial, site, salons | B85: 12000 | C85: 0 | G85: EST
A86: Comptabilité, juridique, banque, logiciels | B86: 12000 | C86: 0 | G86: EST
A87: Rémunération du dirigeant (chargée) | B87: 35000 | C87: 0 | G87: EST : minimum ; le dirigeant paie en plus 18 k€ de loyer privé
A89: 7. Calcul sur 10 ans
A90: Année | B90: Total / réf. | C90: 1 | D90: 2 | E90: 3 | F90: 4 | G90: 5 | H90: 6 | I90: 7 | J90: 8 | K90: 9 | L90: 10
A91: Année d'ouverture effective | C91: =$B$6+$B$47 | D91: =$B$6+$B$47 | E91: =$B$6+$B$47 | F91: =$B$6+$B$47 | G91: =$B$6+$B$47 | H91: =$B$6+$B$47 | I91: =$B$6+$B$47 | J91: =$B$6+$B$47 | ... L91: =$B$6+$B$47
A92: Rang de l'année d'exploitation | C92: =MAX(0,C$90-C91+1) | D92: =MAX(0,D$90-D91+1) | E92: =MAX(0,E$90-E91+1) | F92: =MAX(0,F$90-F91+1) | G92: =MAX(0,G$90-G91+1) | H92: =MAX(0,H$90-H91+1) | I92: =MAX(0,I$90-I91+1) | J92: =MAX(0,J$90-J91+1) | ... L92: =MAX(0,L$90-L91+1)
A93: Coefficient de montée en charge | C93: =IF(C92=0,0,IF(C92=1,$B$53,IF(C92=2,$B$54,IF(C92=3,$B$55,1)))) | D93: =IF(D92=0,0,IF(D92=1,$B$53,IF(D92=2,$B$54,IF(D92=3,$B$55,1)))) | E93: =IF(E92=0,0,IF(E92=1,$B$53,IF(E92=2,$B$54,IF(E92=3,$B$55,1)))) | F93: =IF(F92=0,0,IF(F92=1,$B$53,IF(F92=2,$B$54,IF(F92=3,$B$55,1)))) | G93: =IF(G92=0,0,IF(G92=1,$B$53,IF(G92=2,$B$54,IF(G92=3,$B$55,1)))) | H93: =IF(H92=0,0,IF(H92=1,$B$53,IF(H92=2,$B$54,IF(H92=3,$B$55,1)))) | I93: =IF(I92=0,0,IF(I92=1,$B$53,IF(I92=2,$B$54,IF(I92=3,$B$55,1)))) | J93: =IF(J92=0,0,IF(J92=1,$B$53,IF(J92=2,$B$54,IF(J92=3,$B$55,1)))) | ... L93: =IF(L92=0,0,IF(L92=1,$B$53,IF(L92=2,$B$54,IF(L92=3,$B$55,1))))
A94: Indice prix | C94: =(1+$B$56)^(C$90-1) | D94: =(1+$B$56)^(D$90-1) | E94: =(1+$B$56)^(E$90-1) | F94: =(1+$B$56)^(F$90-1) | G94: =(1+$B$56)^(G$90-1) | H94: =(1+$B$56)^(H$90-1) | I94: =(1+$B$56)^(I$90-1) | J94: =(1+$B$56)^(J$90-1) | ... L94: =(1+$B$56)^(L$90-1)
A95: Indice charges | C95: =(1+$B$57)^(C$90-1) | D95: =(1+$B$57)^(D$90-1) | E95: =(1+$B$57)^(E$90-1) | F95: =(1+$B$57)^(F$90-1) | G95: =(1+$B$57)^(G$90-1) | H95: =(1+$B$57)^(H$90-1) | I95: =(1+$B$57)^(I$90-1) | J95: =(1+$B$57)^(J$90-1) | ... L95: =(1+$B$57)^(L$90-1)
A96: Murs détenus (1/0) | C96: =IF(C$90>=$B$5,1,0) | D96: =IF(D$90>=$B$5,1,0) | E96: =IF(E$90>=$B$5,1,0) | F96: =IF(F$90>=$B$5,1,0) | G96: =IF(G$90>=$B$5,1,0) | H96: =IF(H$90>=$B$5,1,0) | I96: =IF(I$90>=$B$5,1,0) | J96: =IF(J$90>=$B$5,1,0) | ... L96: =IF(L$90>=$B$5,1,0)
A98: Compte de résultat
A99: Pension box premium (places occupées) | B99: =SUM(C99:L99) | C99: =$B$65*$C$65*C93*C94*$B$45*(1-$E$65*$B$50) | D99: =$B$65*$C$65*D93*D94*$B$45*(1-$E$65*$B$50) | E99: =$B$65*$C$65*E93*E94*$B$45*(1-$E$65*$B$50) | F99: =$B$65*$C$65*F93*F94*$B$45*(1-$E$65*$B$50) | G99: =$B$65*$C$65*G93*G94*$B$45*(1-$E$65*$B$50) | H99: =$B$65*$C$65*H93*H94*$B$45*(1-$E$65*$B$50) | I99: =$B$65*$C$65*I93*I94*$B$45*(1-$E$65*$B$50) | J99: =$B$65*$C$65*J93*J94*$B$45*(1-$E$65*$B$50) | ... L99: =$B$65*$C$65*L93*L94*$B$45*(1-$E$65*$B$50)
A100: Pension au pré (places occupées) | B100: =SUM(C100:L100) | C100: =$B$66*$C$66*C93*C94*$B$45*(1-$E$66*$B$50) | D100: =$B$66*$C$66*D93*D94*$B$45*(1-$E$66*$B$50) | E100: =$B$66*$C$66*E93*E94*$B$45*(1-$E$66*$B$50) | F100: =$B$66*$C$66*F93*F94*$B$45*(1-$E$66*$B$50) | G100: =$B$66*$C$66*G93*G94*$B$45*(1-$E$66*$B$50) | H100: =$B$66*$C$66*H93*H94*$B$45*(1-$E$66*$B$50) | I100: =$B$66*$C$66*I93*I94*$B$45*(1-$E$66*$B$50) | J100: =$B$66*$C$66*J93*J94*$B$45*(1-$E$66*$B$50) | ... L100: =$B$66*$C$66*L93*L94*$B$45*(1-$E$66*$B$50)
A101: Pension retraite / convalescence (places occupées) | B101: =SUM(C101:L101) | C101: =$B$67*$C$67*C93*C94*$B$45*(1-$E$67*$B$50) | D101: =$B$67*$C$67*D93*D94*$B$45*(1-$E$67*$B$50) | E101: =$B$67*$C$67*E93*E94*$B$45*(1-$E$67*$B$50) | F101: =$B$67*$C$67*F93*F94*$B$45*(1-$E$67*$B$50) | G101: =$B$67*$C$67*G93*G94*$B$45*(1-$E$67*$B$50) | H101: =$B$67*$C$67*H93*H94*$B$45*(1-$E$67*$B$50) | I101: =$B$67*$C$67*I93*I94*$B$45*(1-$E$67*$B$50) | J101: =$B$67*$C$67*J93*J94*$B$45*(1-$E$67*$B$50) | ... L101: =$B$67*$C$67*L93*L94*$B$45*(1-$E$67*$B$50)
A102: Mariages (location du lieu + hébergement 15 couchages) | B102: =SUM(C102:L102) | C102: =$B$68*$C$68*C93*C94*$B$45*(1-$E$68*$B$50) | D102: =$B$68*$C$68*D93*D94*$B$45*(1-$E$68*$B$50) | E102: =$B$68*$C$68*E93*E94*$B$45*(1-$E$68*$B$50) | F102: =$B$68*$C$68*F93*F94*$B$45*(1-$E$68*$B$50) | G102: =$B$68*$C$68*G93*G94*$B$45*(1-$E$68*$B$50) | H102: =$B$68*$C$68*H93*H94*$B$45*(1-$E$68*$B$50) | I102: =$B$68*$C$68*I93*I94*$B$45*(1-$E$68*$B$50) | J102: =$B$68*$C$68*J93*J94*$B$45*(1-$E$68*$B$50) | ... L102: =$B$68*$C$68*L93*L94*$B$45*(1-$E$68*$B$50)
A103: Gîte 15 couchages hors mariages (nuits) | B103: =SUM(C103:L103) | C103: =$B$69*$C$69*C93*C94*$B$45*(1-$E$69*$B$50) | D103: =$B$69*$C$69*D93*D94*$B$45*(1-$E$69*$B$50) | E103: =$B$69*$C$69*E93*E94*$B$45*(1-$E$69*$B$50) | F103: =$B$69*$C$69*F93*F94*$B$45*(1-$E$69*$B$50) | G103: =$B$69*$C$69*G93*G94*$B$45*(1-$E$69*$B$50) | H103: =$B$69*$C$69*H93*H94*$B$45*(1-$E$69*$B$50) | I103: =$B$69*$C$69*I93*I94*$B$45*(1-$E$69*$B$50) | J103: =$B$69*$C$69*J93*J94*$B$45*(1-$E$69*$B$50) | ... L103: =$B$69*$C$69*L93*L94*$B$45*(1-$E$69*$B$50)
A104: Séminaires à la journée (jours) | B104: =SUM(C104:L104) | C104: =$B$70*$C$70*C93*C94*$B$45*(1-$E$70*$B$50) | D104: =$B$70*$C$70*D93*D94*$B$45*(1-$E$70*$B$50) | E104: =$B$70*$C$70*E93*E94*$B$45*(1-$E$70*$B$50) | F104: =$B$70*$C$70*F93*F94*$B$45*(1-$E$70*$B$50) | G104: =$B$70*$C$70*G93*G94*$B$45*(1-$E$70*$B$50) | H104: =$B$70*$C$70*H93*H94*$B$45*(1-$E$70*$B$50) | I104: =$B$70*$C$70*I93*I94*$B$45*(1-$E$70*$B$50) | J104: =$B$70*$C$70*J93*J94*$B$45*(1-$E$70*$B$50) | ... L104: =$B$70*$C$70*L93*L94*$B$45*(1-$E$70*$B$50)
A105: Tournages / shootings (jours) | B105: =SUM(C105:L105) | C105: =$B$71*$C$71*C93*C94*$B$45*(1-$E$71*$B$50) | D105: =$B$71*$C$71*D93*D94*$B$45*(1-$E$71*$B$50) | E105: =$B$71*$C$71*E93*E94*$B$45*(1-$E$71*$B$50) | F105: =$B$71*$C$71*F93*F94*$B$45*(1-$E$71*$B$50) | G105: =$B$71*$C$71*G93*G94*$B$45*(1-$E$71*$B$50) | H105: =$B$71*$C$71*H93*H94*$B$45*(1-$E$71*$B$50) | I105: =$B$71*$C$71*I93*I94*$B$45*(1-$E$71*$B$50) | J105: =$B$71*$C$71*J93*J94*$B$45*(1-$E$71*$B$50) | ... L105: =$B$71*$C$71*L93*L94*$B$45*(1-$E$71*$B$50)
A106: Fermage / vente d'herbe (ha) | B106: =SUM(C106:L106) | C106: =$B$72*$C$72*C93*C94*$B$45*(1-$E$72*$B$50) | D106: =$B$72*$C$72*D93*D94*$B$45*(1-$E$72*$B$50) | E106: =$B$72*$C$72*E93*E94*$B$45*(1-$E$72*$B$50) | F106: =$B$72*$C$72*F93*F94*$B$45*(1-$E$72*$B$50) | G106: =$B$72*$C$72*G93*G94*$B$45*(1-$E$72*$B$50) | H106: =$B$72*$C$72*H93*H94*$B$45*(1-$E$72*$B$50) | I106: =$B$72*$C$72*I93*I94*$B$45*(1-$E$72*$B$50) | J106: =$B$72*$C$72*J93*J94*$B$45*(1-$E$72*$B$50) | ... L106: =$B$72*$C$72*L93*L94*$B$45*(1-$E$72*$B$50)
A107: Chiffre d'affaires total | B107: =SUM(C107:L107) | C107: =C99+C100+C101+C102+C103+C104+C105+C106 | D107: =D99+D100+D101+D102+D103+D104+D105+D106 | E107: =E99+E100+E101+E102+E103+E104+E105+E106 | F107: =F99+F100+F101+F102+F103+F104+F105+F106 | G107: =G99+G100+G101+G102+G103+G104+G105+G106 | H107: =H99+H100+H101+H102+H103+H104+H105+H106 | I107: =I99+I100+I101+I102+I103+I104+I105+I106 | J107: =J99+J100+J101+J102+J103+J104+J105+J106 | ... L107: =L99+L100+L101+L102+L103+L104+L105+L106
A108: dont équestre | B108: =SUM(C108:L108) | C108: =C99*$F$65+C100*$F$66+C101*$F$67+C102*$F$68+C103*$F$69+C104*$F$70+C105*$F$71+C106*$F$72 | D108: =D99*$F$65+D100*$F$66+D101*$F$67+D102*$F$68+D103*$F$69+D104*$F$70+D105*$F$71+D106*$F$72 | E108: =E99*$F$65+E100*$F$66+E101*$F$67+E102*$F$68+E103*$F$69+E104*$F$70+E105*$F$71+E106*$F$72 | F108: =F99*$F$65+F100*$F$66+F101*$F$67+F102*$F$68+F103*$F$69+F104*$F$70+F105*$F$71+F106*$F$72 | G108: =G99*$F$65+G100*$F$66+G101*$F$67+G102*$F$68+G103*$F$69+G104*$F$70+G105*$F$71+G106*$F$72 | H108: =H99*$F$65+H100*$F$66+H101*$F$67+H102*$F$68+H103*$F$69+H104*$F$70+H105*$F$71+H106*$F$72 | I108: =I99*$F$65+I100*$F$66+I101*$F$67+I102*$F$68+I103*$F$69+I104*$F$70+I105*$F$71+I106*$F$72 | J108: =J99*$F$65+J100*$F$66+J101*$F$67+J102*$F$68+J103*$F$69+J104*$F$70+J105*$F$71+J106*$F$72 | ... L108: =L99*$F$65+L100*$F$66+L101*$F$67+L102*$F$68+L103*$F$69+L104*$F$70+L105*$F$71+L106*$F$72
A109: Part équestre du CA | C109: =IF(C107=0,0,C108/C107) | D109: =IF(D107=0,0,D108/D107) | E109: =IF(E107=0,0,E108/E107) | F109: =IF(F107=0,0,F108/F107) | G109: =IF(G107=0,0,G108/G107) | H109: =IF(H107=0,0,H108/H107) | I109: =IF(I107=0,0,I108/I107) | J109: =IF(J107=0,0,J108/J107) | ... L109: =IF(L107=0,0,L108/L107)
A110: Coûts variables | B110: =SUM(C110:L110) | C110: =-(C99*$D$65+C100*$D$66+C101*$D$67+C102*$D$68+C103*$D$69+C104*$D$70+C105*$D$71+C106*$D$72) | D110: =-(D99*$D$65+D100*$D$66+D101*$D$67+D102*$D$68+D103*$D$69+D104*$D$70+D105*$D$71+D106*$D$72) | E110: =-(E99*$D$65+E100*$D$66+E101*$D$67+E102*$D$68+E103*$D$69+E104*$D$70+E105*$D$71+E106*$D$72) | F110: =-(F99*$D$65+F100*$D$66+F101*$D$67+F102*$D$68+F103*$D$69+F104*$D$70+F105*$D$71+F106*$D$72) | G110: =-(G99*$D$65+G100*$D$66+G101*$D$67+G102*$D$68+G103*$D$69+G104*$D$70+G105*$D$71+G106*$D$72) | H110: =-(H99*$D$65+H100*$D$66+H101*$D$67+H102*$D$68+H103*$D$69+H104*$D$70+H105*$D$71+H106*$D$72) | I110: =-(I99*$D$65+I100*$D$66+I101*$D$67+I102*$D$68+I103*$D$69+I104*$D$70+I105*$D$71+I106*$D$72) | J110: =-(J99*$D$65+J100*$D$66+J101*$D$67+J102*$D$68+J103*$D$69+J104*$D$70+J105*$D$71+J106*$D$72) | ... L110: =-(L99*$D$65+L100*$D$66+L101*$D$67+L102*$D$68+L103*$D$69+L104*$D$70+L105*$D$71+L106*$D$72)
A111: Marge sur coûts variables | B111: =SUM(C111:L111) | C111: =C107+C110 | D111: =D107+D110 | E111: =E107+E110 | F111: =F107+F110 | G111: =G107+G110 | H111: =H107+H110 | I111: =I107+I110 | J111: =J107+J110 | ... L111: =L107+L110
...

Sheet B_prudent
A1: Scénario B — Château multiactivité — cas prudent
A2: Cellules jaunes/bleues = hypothèses éditables. Tout le reste est calculé. Colonne D (bloc hypothèses) = source ou statut (ESTIMATION = non vérifiée).
A4: 1. Calendrier, acquisition et travaux
A5: Année d'acquisition des murs (1 = immédiate) | B5: 1 | C5: année | D5: Achat immédiat (2027)
A6: Année d'ouverture commerciale (avant stress) | B6: 2 | C6: année | D6: Année 1 = travaux ; EST
A7: Prix d'acquisition | B7: 2500000 | C7: € | D7: PL : médiane de 19 annonces de châteaux ≥ 30 ha (quartiles 1,29-3,07 M€) [A1]
A8: Frais d'acquisition (droits + notaire) | B8: 0.075 | C8: % | D8: EST : DMTO ≈ 5,8-6,3 % + notaire ≈ 1,2 % ; vente SAFER : frais 8,4 % TTC mais exonération de droits possible [A1, PL]
A9: Part du prix affectable au bâti (amortissable) | B9: 0.55 | C9: % | D9: EST
A10: Travaux de restauration / mise aux normes | B10: 625000 | C10: € | D10: EST sans visite : top 5 des biens équipés 0,1-0,7 M€ [A1]
A11: Investissements équestres (boxes, carrière, manège…) | B11: 187500 | C11: € | D11: EST : remise à niveau d'écuries existantes (une écurie neuve de 30 box coûterait 0,78-0,83 M€ HT [A3 H20])
A12: Investissements événementiel / hébergement | B12: 312500 | C12: € | D12: EST : mise aux normes d'une salle existante + aménagement du gîte (neuf : 570 k€-1,24 M€ [A4 §13.2])
A13: Répartition travaux : année d'acquisition | B13: 0.6 | C13: % | D13: EST
A14: Répartition travaux : année +1 | B14: 0.3 | C14: % | D14: EST
A15: Répartition travaux : année +2 | B15: 0.1 | C15: % | D15: EST
A16: Gros entretien patrimonial annuel (% prix+travaux) | B16: 0.018 | C16: % | D16: ≈ 41 k€/an sur (bâti + travaux) : Demeure Historique ≥ 40 k€/an hors restauration (PL [A8]) ; Barnes 20-80 k€/an [A4 §11] ; démarre en année d'acquisition + 3
... A20: Loyer de la partie privée payé par le fondateur (hors CA d'exploitation) | B20: 0 | C20: € | D20: Correction audit M1 : aucun loyer privé compté — le logis doit être détenu à part (SCI à l'IR, hors taxe 235 ter C [A6]) et payé par le fondateur personnellement
A22: 2. Financement
A23: Apport du fondateur (année 1) | B23: 1000000 | C23: € | D23: Scénario d'apport S3 (hypothèse ; apport réel inconnu)
A24: Fonds propres apportés à l'acquisition (investisseurs ou holding) | B24: 0 | C24: € | D24: Aucun investisseur
A25: Ces fonds propres viennent-ils de la holding du fondateur ? (1/0) | B25: 0
A26: Subventions (non acquises : 0 par défaut) | B26: 0 | C26: € | D26: Aucune subvention considérée comme acquise
A27: Dette bancaire (année d'acquisition) | B27: 2400000 | C27: € | D27: NON ACQUIS — montage 1 [A2] : prêt hypothécaire 20 ans ; LTV ≈ 70 %, jugée trop élevée par l'agent 2
A28: Taux de la dette bancaire | B28: 0.04 | C28: % | D28: PL : nouveaux crédits PME 3,64 % (FBF, 06/2026) ; EX : 3,66 % (BdF, 08/2026) ; retenu 4,0 % [A2]
A29: Durée dette bancaire | B29: 20 | C29: ans | D29: A2 (Bpifrance : 15 ans avec hypothèque, PL)
A30: Différé d'amortissement (dans la durée) | B30: 1 | C30: ans | D30: EST
A31: Crédit-vendeur | B31: 0 | C31: €
A32: Taux crédit-vendeur | B32: 0.03 | C32: % | D32: EST
A33: Durée crédit-vendeur (amortissable) | B33: 12 | C33: ans | D33: EST
A34: Obligations / quasi-fonds propres (in fine) | B34: 0 | C34: €
A35: Coupon annuel des obligations | B35: 0.07 | C35: % | D35: PL : obligations Château Fontenay 7 % [A2]
A36: Année de remboursement des obligations | B36: 6 | C36: année | D36: EST
A37: Part de capital supplémentaire accordée au fondateur pour son travail (sweat equity) | B37: 0 | C37: % | D37: Fondateur seul
A38: Droits de vote du fondateur | B38: 1 | C38: %
A39: Réserve de liquidité cible | B39: 150000 | C39: € | D39: EST
A40: TRI minimal exigé par des investisseurs extérieurs | B40: 0.06 | C40: % | D40: EST : rendement minimal d'un investisseur en fonds propres illiquide (Anaxago affiche 8,7 % net, PL [A2])
A41: Le dirigeant est-il rémunéré par le domaine ? (1/0) | B41: 1 | D41: Rémunération du dirigeant incluse
A42: Part du capital du fondateur (calculée : apports au prorata + prime d'industrie, plafonnée à 100 %) | B42: =MIN(1,($B$23+$B$24*$B$25)/MAX(1,$B$23+$B$24)+$B$37)
A44: 3. Paramètres de stress (neutres = 100 % / 0)
A45: Multiplicateur de chiffre d'affaires | B45: 1 | C45: % | D45: neutre
A46: Multiplicateur du budget travaux | B46: 1 | C46: % | D46: neutre
A47: Retard d'ouverture | B47: 0 | C47: ans | D47: neutre
A48: Hausse du taux bancaire (points) | B48: 0 | C48: % | D48: neutre
A49: Part des fonds investisseurs non versée | B49: 0 | C49: % | D49: neutre
A50: Part des événements annulés | B50: 0 | C50: % | D50: neutre
A52: 4. Exploitation — hypothèses générales
A53: Montée en charge : 1re année d'exploitation | B53: 0.4 | C53: % | D53: Cas prudent
A54: Montée en charge : 2e année | B54: 0.65 | C54: % | D54: Cas prudent
A55: Montée en charge : 3e année | B55: 0.85 | C55: % | D55: Cas prudent
A56: Indexation annuelle des prix | B56: 0.02 | C56: % | D56: EST
A57: Inflation annuelle des charges | B57: 0.02 | C57: % | D57: EST : indexation identique aux prix (correction audit, biais pessimiste retiré)
A58: BFR en % du CA (négatif = acomptes clients) | B58: -0.03 | C58: % | D58: Acomptes (mariages, pensions payées d'avance) — EST
A59: Taux normal d'IS | B59: 0.25 | C59: % | D59: PL : IS 25 % au-delà de 42 500 € [A6]
A60: Taux réduit d'IS (PME, jusqu'au seuil) | B60: 0.15 | C60: % | D60: PL : 15 % jusqu'à 42 500 € (PME) [A6]
A61: Seuil du taux réduit d'IS | B61: 42500 | C61: € | D61: PL [A6]
A63: 5. Lignes de revenus (à maturité, euros de l'année d'ouverture)
A64: Libellé | B64: Volume | C64: Prix unitaire | D64: Coût var. % | E64: Événement ? | F64: Équestre ? | G64: Unité / source
A65: Pension box premium (places occupées) | B65: 17.6 | C65: 4709 | D65: 0.23 | E65: 0 | F65: 1 | G65: PL : 450 € TTC/mois = 3e quartile hors IdF (médiane 375 €, 10 % des offres ≥ 520 €) [A3, recalcul A8] → 426,5 € HT à TVA 5,5 % ; 24 box × 92 % ; coûts directs 1 200 €/an EST
A66: Pension au pré (places occupées) | B66: 18.4 | C66: 2302 | D66: 0.245 | E66: 0 | F66: 1 | G66: PL : 220 € TTC/mois (médianes 200-240 €) → 208,5 € HT [A3 H3] ; 25 places × 92 % ; coûts 613 €/an [A3 §4]
A67: Pension retraite / convalescence (places occupées) | B67: 7.2 | C67: 1932 | D67: 0.24 | E67: 0 | F67: 1 | G67: PL : 210 € TTC/mois, TVA 20 % → 175 € HT [A3 H4] ; 10 places × 90 %
A68: Mariages (location du lieu + hébergement 15 couchages) | B68: 9.6 | C68: 3861 | D68: 0.43 | E68: 1 | F68: 0 | G68: PL : médiane 3 400 € TTC location (17 châteaux) + 1 500 € TTC hébergement → 4 197 € HT [A4 §13.1] ; 12/an EST ; coût variable 1 450 € + 8 %
A69: Gîte 15 couchages hors mariages (nuits) | B69: 73.6 | C69: 414 | D69: 0.45 | E69: 0 | F69: 0 | G69: PL : fourchettes de prix [A4 §4.2] ; 92 nuits EST (occupation annuelle ≈ 33 % observée en Normandie hors saison) [A4 §4.3]
A70: Séminaires à la journée (jours) | B70: 9.6 | C70: 736 | D70: 0.19 | E70: 1 | F70: 0 | G70: PL : salle 1 000 €/jour (Feugerets) ; 800 € HT retenu [A4 §3]
A71: Tournages / shootings (jours) | B71: 2.4 | C71: 1840 | D71: 0.15 | E71: 1 | F71: 0 | G71: PL : 1 500-4 000 €/jour [A4 §5] ; fréquence EST
A72: Fermage / vente d'herbe (ha) | B72: 8 | C72: 138 | D72: 0 | E72: 0 | F72: 0 | G72: PL : arrêtés Orne/Calvados 2026-27 : 50-268 €/ha [A4 §8.2]
A74: 6. Charges fixes annuelles (euros de l'année d'ouverture)
A75: Libellé | B75: Montant/an | C75: Dès l'acq. (1) / dès l'ouverture (0) | G75: Source / statut
A76: Taxe foncière | B76: 6600 | C76: 1 | G76: EX : 2,6-4,0 k€ sur 3 annonces ; EST 4-8 k€ [A4 §11]
A77: Assurance multirisque château | B77: 13200 | C77: 1 | G77: Correction audit : courtier spécialisé 15-30 k€ (fiabilité moyenne), annonces ≥ 2,5 k€ [A4 §11, A8] ; EST 12 k€
A78: Énergie (chauffage partiel, électricité, eau) | B78: 22000 | C78: 1 | G78: PL : Meung, Louvignies ; EX annonce Montluçon 18-25 k€ [A1, A4 §11] ; EST
A79: Jardinier / agent d'entretien (1 ETP au Smic chargé) | B79: 29700 | C79: 1 | G79: PL : Smic 2026 22 404 € brut/an [A4 §11] ; EST charges
A80: Divers (abonnements, petit matériel, véhicule, honoraires) | B80: 8800 | C80: 1 | G80: EST
A81: Soigneurs (3 ETP au Smic chargés) | B81: 99000 | C81: 0 | G81: PL : Smic 1 867 €/mois, grille IDCC 7026 inférieure ; 1 ETP / 17-20 équidés [A3 H13-H14] ; ~54 équidés → 3 ETP (correction audit M5)
A82: Autres charges de structure équestres (entretien installations, matériel, assurance RC, énergie écuries) | B82: 33000 | C82: 0 | G82: Calibré pour un EBE équestre ≈ 37 % (réf. pension hébergement 36-38 %, PL [A3 H10])
A83: Coûts fixes mariages (coordination, nettoyage, publicité) | B83: 12100 | C83: 0 | G83: EST [A4 §13.1]
A84: Coûts fixes du gîte | B84: 4840 | C84: 0 | G84: EST [A4 §13.1]
A85: Commercial, site, salons | B85: 13200 | C85: 0 | G85: EST
A86: Comptabilité, juridique, banque, logiciels | B86: 13200 | C86: 0 | G86: EST
A87: Rémunération du dirigeant (chargée) | B87: 38500 | C87: 0 | G87: EST : minimum ; le dirigeant paie en plus 18 k€ de loyer privé
A89: 7. Calcul sur 10 ans
A90: Année | B90: Total / réf. | C90: 1 | D90: 2 | E90: 3 | F90: 4 | G90: 5 | H90: 6 | I90: 7 | J90: 8 | K90: 9 | L90: 10
A91: Année d'ouverture effective | C91: =$B$6+$B$47 | D91: =$B$6+$B$47 | E91: =$B$6+$B$47 | F91: =$B$6+$B$47 | G91: =$B$6+$B$47 | H91: =$B$6+$B$47 | I91: =$B$6+$B$47 | J91: =$B$6+$B$47 | ... L91: =$B$6+$B$47
A92: Rang de l'année d'exploitation | C92: =MAX(0,C$90-C91+1) | D92: =MAX(0,D$90-D91+1) | E92: =MAX(0,E$90-E91+1) | F92: =MAX(0,F$90-F91+1) | G92: =MAX(0,G$90-G91+1) | H92: =MAX(0,H$90-H91+1) | I92: =MAX(0,I$90-I91+1) | J92: =MAX(0,J$90-J91+1) | ... L92: =MAX(0,L$90-L91+1)
A93: Coefficient de montée en charge | C93: =IF(C92=0,0,IF(C92=1,$B$53,IF(C92=2,$B$54,IF(C92=3,$B$55,1)))) | D93: =IF(D92=0,0,IF(D92=1,$B$53,IF(D92=2,$B$54,IF(D92=3,$B$55,1)))) | E93: =IF(E92=0,0,IF(E92=1,$B$53,IF(E92=2,$B$54,IF(E92=3,$B$55,1)))) | F93: =IF(F92=0,0,IF(F92=1,$B$53,IF(F92=2,$B$54,IF(F92=3,$B$55,1)))) | G93: =IF(G92=0,0,IF(G92=1,$B$53,IF(G92=2,$B$54,IF(G92=3,$B$55,1)))) | H93: =IF(H92=0,0,IF(H92=1,$B$53,IF(H92=2,$B$54,IF(H92=3,$B$55,1)))) | I93: =IF(I92=0,0,IF(I92=1,$B$53,IF(I92=2,$B$54,IF(I92=3,$B$55,1)))) | J93: =IF(J92=0,0,IF(J92=1,$B$53,IF(J92=2,$B$54,IF(J92=3,$B$55,1)))) | ... L93: =IF(L92=0,0,IF(L92=1,$B$53,IF(L92=2,$B$54,IF(L92=3,$B$55,1))))
A94: Indice prix | C94: =(1+$B$56)^(C$90-1) | D94: =(1+$B$56)^(D$90-1) | E94: =(1+$B$56)^(E$90-1) | F94: =(1+$B$56)^(F$90-1) | G94: =(1+$B$56)^(G$90-1) | H94: =(1+$B$56)^(H$90-1) | I94: =(1+$B$56)^(I$90-1) | J94: =(1+$B$56)^(J$90-1) | ... L94: =(1+$B$56)^(L$90-1)
A95: Indice charges | C95: =(1+$B$57)^(C$90-1) | D95: =(1+$B$57)^(D$90-1) | E95: =(1+$B$57)^(E$90-1) | F95: =(1+$B$57)^(F$90-1) | G95: =(1+$B$57)^(G$90-1) | H95: =(1+$B$57)^(H$90-1) | I95: =(1+$B$57)^(I$90-1) | J95: =(1+$B$57)^(J$90-1) | ... L95: =(1+$B$57)^(L$90-1)
A96: Murs détenus (1/0) | C96: =IF(C$90>=$B$5,1,0) | D96: =IF(D$90>=$B$5,1,0) | E96: =IF(E$90>=$B$5,1,0) | F96: =IF(F$90>=$B$5,1,0) | G96: =IF(G$90>=$B$5,1,0) | H96: =IF(H$90>=$B$5,1,0) | I96: =IF(I$90>=$B$5,1,0) | J96: =IF(J$90>=$B$5,1,0) | ... L96: =IF(L$90>=$B$5,1,0)
A98: Compte de résultat
A99: Pension box premium (places occupées) | B99: =SUM(C99:L99) | C99: =$B$65*$C$65*C93*C94*$B$45*(1-$E$65*$B$50) | D99: =$B$65*$C$65*D93*D94*$B$45*(1-$E$65*$B$50) | E99: =$B$65*$C$65*E93*E94*$B$45*(1-$E$65*$B$50) | F99: =$B$65*$C$65*F93*F94*$B$45*(1-$E$65*$B$50) | G99: =$B$65*$C$65*G93*G94*$B$45*(1-$E$65*$B$50) | H99: =$B$65*$C$65*H93*H94*$B$45*(1-$E$65*$B$50) | I99: =$B$65*$C$65*I93*I94*$B$45*(1-$E$65*$B$50) | J99: =$B$65*$C$65*J93*J94*$B$45*(1-$E$65*$B$50) | ... L99: =$B$65*$C$65*L93*L94*$B$45*(1-$E$65*$B$50)
A100: Pension au pré (places occupées) | B100: =SUM(C100:L100) | C100: =$B$66*$C$66*C93*C94*$B$45*(1-$E$66*$B$50) | D100: =$B$66*$C$66*D93*D94*$B$45*(1-$E$66*$B$50) | E100: =$B$66*$C$66*E93*E94*$B$45*(1-$E$66*$B$50) | F100: =$B$66*$C$66*F93*F94*$B$45*(1-$E$66*$B$50) | G100: =$B$66*$C$66*G93*G94*$B$45*(1-$E$66*$B$50) | H100: =$B$66*$C$66*H93*H94*$B$45*(1-$E$66*$B$50) | I100: =$B$66*$C$66*I93*I94*$B$45*(1-$E$66*$B$50) | J100: =$B$66*$C$66*J93*J94*$B$45*(1-$E$66*$B$50) | ... L100: =$B$66*$C$66*L93*L94*$B$45*(1-$E$66*$B$50)
A101: Pension retraite / convalescence (places occupées) | B101: =SUM(C101:L101) | C101: =$B$67*$C$67*C93*C94*$B$45*(1-$E$67*$B$50) | D101: =$B$67*$C$67*D93*D94*$B$45*(1-$E$67*$B$50) | E101: =$B$67*$C$67*E93*E94*$B$45*(1-$E$67*$B$50) | F101: =$B$67*$C$67*F93*F94*$B$45*(1-$E$67*$B$50) | G101: =$B$67*$C$67*G93*G94*$B$45*(1-$E$67*$B$50) | H101: =$B$67*$C$67*H93*H94*$B$45*(1-$E$67*$B$50) | I101: =$B$67*$C$67*I93*I94*$B$45*(1-$E$67*$B$50) | J101: =$B$67*$C$67*J93*J94*$B$45*(1-$E$67*$B$50) | ... L101: =$B$67*$C$67*L93*L94*$B$45*(1-$E$67*$B$50)
A102: Mariages (location du lieu + hébergement 15 couchages) | B102: =SUM(C102:L102) | C102: =$B$68*$C$68*C93*C94*$B$45*(1-$E$68*$B$50) | D102: =$B$68*$C$68*D93*D94*$B$45*(1-$E$68*$B$50) | E102: =$B$68*$C$68*E93*E94*$B$45*(1-$E$68*$B$50) | F102: =$B$68*$C$68*F93*F94*$B$45*(1-$E$68*$B$50) | G102: =$B$68*$C$68*G93*G94*$B$45*(1-$E$68*$B$50) | H102: =$B$68*$C$68*H93*H94*$B$45*(1-$E$68*$B$50) | I102: =$B$68*$C$68*I93*I94*$B$45*(1-$E$68*$B$50) | J102: =$B$68*$C$68*J93*J94*$B$45*(1-$E$68*$B$50) | ... L102: =$B$68*$C$68*L93*L94*$B$45*(1-$E$68*$B$50)
A103: Gîte 15 couchages hors mariages (nuits) | B103: =SUM(C103:L103) | C103: =$B$69*$C$69*C93*C94*$B$45*(1-$E$69*$B$50) | D103: =$B$69*$C$69*D93*D94*$B$45*(1-$E$69*$B$50) | E103: =$B$69*$C$69*E93*E94*$B$45*(1-$E$69*$B$50) | F103: =$B$69*$C$69*F93*F94*$B$45*(1-$E$69*$B$50) | G103: =$B$69*$C$69*G93*G94*$B$45*(1-$E$69*$B$50) | H103: =$B$69*$C$69*H93*H94*$B$45*(1-$E$69*$B$50) | I103: =$B$69*$C$69*I93*I94*$B$45*(1-$E$69*$B$50) | J103: =$B$69*$C$69*J93*J94*$B$45*(1-$E$69*$B$50) | ... L103: =$B$69*$C$69*L93*L94*$B$45*(1-$E$69*$B$50)
A104: Séminaires à la journée (jours) | B104: =SUM(C104:L104) | C104: =$B$70*$C$70*C93*C94*$B$45*(1-$E$70*$B$50) | D104: =$B$70*$C$70*D93*D94*$B$45*(1-$E$70*$B$50) | E104: =$B$70*$C$70*E93*E94*$B$45*(1-$E$70*$B$50) | F104: =$B$70*$C$70*F93*F94*$B$45*(1-$E$70*$B$50) | G104: =$B$70*$C$70*G93*G94*$B$45*(1-$E$70*$B$50) | H104: =$B$70*$C$70*H93*H94*$B$45*(1-$E$70*$B$50) | I104: =$B$70*$C$70*I93*I94*$B$45*(1-$E$70*$B$50) | J104: =$B$70*$C$70*J93*J94*$B$45*(1-$E$70*$B$50) | ... L104: =$B$70*$C$70*L93*L94*$B$45*(1-$E$70*$B$50)
A105: Tournages / shootings (jours) | B105: =SUM(C105:L105) | C105: =$B$71*$C$71*C93*C94*$B$45*(1-$E$71*$B$50) | D105: =$B$71*$C$71*D93*D94*$B$45*(1-$E$71*$B$50) | E105: =$B$71*$C$71*E93*E94*$B$45*(1-$E$71*$B$50) | F105: =$B$71*$C$71*F93*F94*$B$45*(1-$E$71*$B$50) | G105: =$B$71*$C$71*G93*G94*$B$45*(1-$E$71*$B$50) | H105: =$B$71*$C$71*H93*H94*$B$45*(1-$E$71*$B$50) | I105: =$B$71*$C$71*I93*I94*$B$45*(1-$E$71*$B$50) | J105: =$B$71*$C$71*J93*J94*$B$45*(1-$E$71*$B$50) | ... L105: =$B$71*$C$71*L93*L94*$B$45*(1-$E$71*$B$50)
A106: Fermage / vente d'herbe (ha) | B106: =SUM(C106:L106) | C106: =$B$72*$C$72*C93*C94*$B$45*(1-$E$72*$B$50) | D106: =$B$72*$C$72*D93*D94*$B$45*(1-$E$72*$B$50) | E106: =$B$72*$C$72*E93*E94*$B$45*(1-$E$72*$B$50) | F106: =$B$72*$C$72*F93*F94*$B$45*(1-$E$72*$B$50) | G106: =$B$72*$C$72*G93*G94*$B$45*(1-$E$72*$B$50) | H106: =$B$72*$C$72*H93*H94*$B$45*(1-$E$72*$B$50) | I106: =$B$72*$C$72*I93*I94*$B$45*(1-$E$72*$B$50) | J106: =$B$72*$C$72*J93*J94*$B$45*(1-$E$72*$B$50) | ... L106: =$B$72*$C$72*L93*L94*$B$45*(1-$E$72*$B$50)
A107: Chiffre d'affaires total | B107: =SUM(C107:L107) | C107: =C99+C100+C101+C102+C103+C104+C105+C106 | D107: =D99+D100+D101+D102+D103+D104+D105+D106 | E107: =E99+E100+E101+E102+E103+E104+E105+E106 | F107: =F99+F100+F101+F102+F103+F104+F105+F106 | G107: =G99+G100+G101+G102+G103+G104+G105+G106 | H107: =H99+H100+H101+H102+H103+H104+H105+H106 | I107: =I99+I100+I101+I102+I103+I104+I105+I106 | J107: =J99+J100+J101+J102+J103+J104+J105+J106 | ... L107: =L99+L100+L101+L102+L103+L104+L105+L106
A108: dont équestre | B108: =SUM(C108:L108) | C108: =C99*$F$65+C100*$F$66+C101*$F$67+C102*$F$68+C103*$F$69+C104*$F$70+C105*$F$71+C106*$F$72 | D108: =D99*$F$65+D100*$F$66+D101*$F$67+D102*$F$68+D103*$F$69+D104*$F$70+D105*$F$71+D106*$F$72 | E108: =E99*$F$65+E100*$F$66+E101*$F$67+E102*$F$68+E103*$F$69+E104*$F$70+E105*$F$71+E106*$F$72 | F108: =F99*$F$65+F100*$F$66+F101*$F$67+F102*$F$68+F103*$F$69+F104*$F$70+F105*$F$71+F106*$F$72 | G108: =G99*$F$65+G100*$F$66+G101*$F$67+G102*$F$68+G103*$F$69+G104*$F$70+G105*$F$71+G106*$F$72 | H108: =H99*$F$65+H100*$F$66+H101*$F$67+H102*$F$68+H103*$F$69+H104*$F$70+H105*$F$71+H106*$F$72 | I108: =I99*$F$65+I100*$F$66+I101*$F$67+I102*$F$68+I103*$F$69+I104*$F$70+I105*$F$71+I106*$F$72 | J108: =J99*$F$65+J100*$F$66+J101*$F$67+J102*$F$68+J103*$F$69+J104*$F$70+J105*$F$71+J106*$F$72 | ... L108: =L99*$F$65+L100*$F$66+L101*$F$67+L102*$F$68+L103*$F$69+L104*$F$70+L105*$F$71+L106*$F$72
A109: Part équestre du CA | C109: =IF(C107=0,0,C108/C107) | D109: =IF(D107=0,0,D108/D107) | E109: =IF(E107=0,0,E108/E107) | F109: =IF(F107=0,0,F108/F107) | G109: =IF(G107=0,0,G108/G107) | H109: =IF(H107=0,0,H108/H107) | I109: =IF(I107=0,0,I108/I107) | J109: =IF(J107=0,0,J108/J107) | ... L109: =IF(L107=0,0,L108/L107)
A110: Coûts variables | B110: =SUM(C110:L110) | C110: =-(C99*$D$65+C100*$D$66+C101*$D$67+C102*$D$68+C103*$D$69+C104*$D$70+C105*$D$71+C106*$D$72) | D110: =-(D99*$D$65+D100*$D$66+D101*$D$67+D102*$D$68+D103*$D$69+D104*$D$70+D105*$D$71+D106*$D$72) | E110: =-(E99*$D$65+E100*$D$66+E101*$D$67+E102*$D$68+E103*$D$69+E104*$D$70+E105*$D$71+E106*$D$72) | F110: =-(F99*$D$65+F100*$D$66+F101*$D$67+F102*$D$68+F103*$D$69+F104*$D$70+F105*$D$71+F106*$D$72) | G110: =-(G99*$D$65+G100*$D$66+G101*$D$67+G102*$D$68+G103*$D$69+G104*$D$70+G105*$D$71+G106*$D$72) | H110: =-(H99*$D$65+H100*$D$66+H101*$D$67+H102*$D$68+H103*$D$69+H104*$D$70+H105*$D$71+H106*$D$72) | I110: =-(I99*$D$65+I100*$D$66+I101*$D$67+I102*$D$68+I103*$D$69+I104*$D$70+I105*$D$71+I106*$D$72) | J110: =-(J99*$D$65+J100*$D$66+J101*$D$67+J102*$D$68+J103*$D$69+J104*$D$70+J105*$D$71+J106*$D$72) | ... L110: =-(L99*$D$65+L100*$D$66+L101*$D$67+L102*$D$68+L103*$D$69+L104*$D$70+L105*$D$71+L106*$D$72)
A111: Marge sur coûts variables | B111: =SUM(C111:L111) | C111: =C107+C110 | D111: =D107+D110 | E111: =E107+E110 | F111: =F107+F110 | G111: =G107+G110 | H111: =H107+H110 | I111: =I107+I110 | J111: =J107+J110 | ... L111: =L107+L110
...

Sheet B_optimiste
A1: Scénario B — Château multiactivité — cas optimiste
A2: Cellules jaunes/bleues = hypothèses éditables. Tout le reste est calculé. Colonne D (bloc hypothèses) = source ou statut (ESTIMATION = non vérifiée).
A4: 1. Calendrier, acquisition et travaux
A5: Année d'acquisition des murs (1 = immédiate) | B5: 1 | C5: année | D5: Achat immédiat (2027)
A6: Année d'ouverture commerciale (avant stress) | B6: 2 | C6: année | D6: Année 1 = travaux ; EST
A7: Prix d'acquisition | B7: 2500000 | C7: € | D7: PL : médiane de 19 annonces de châteaux ≥ 30 ha (quartiles 1,29-3,07 M€) [A1]
A8: Frais d'acquisition (droits + notaire) | B8: 0.075 | C8: % | D8: EST : DMTO ≈ 5,8-6,3 % + notaire ≈ 1,2 % ; vente SAFER : frais 8,4 % TTC mais exonération de droits possible [A1, PL]
A9: Part du prix affectable au bâti (amortissable) | B9: 0.55 | C9: % | D9: EST
A10: Travaux de restauration / mise aux normes | B10: 500000 | C10: € | D10: EST sans visite : top 5 des biens équipés 0,1-0,7 M€ [A1]
A11: Investissements équestres (boxes, carrière, manège…) | B11: 150000 | C11: € | D11: EST : remise à niveau d'écuries existantes (une écurie neuve de 30 box coûterait 0,78-0,83 M€ HT [A3 H20])
A12: Investissements événementiel / hébergement | B12: 250000 | C12: € | D12: EST : mise aux normes d'une salle existante + aménagement du gîte (neuf : 570 k€-1,24 M€ [A4 §13.2])
A13: Répartition travaux : année d'acquisition | B13: 0.6 | C13: % | D13: EST
A14: Répartition travaux : année +1 | B14: 0.3 | C14: % | D14: EST
A15: Répartition travaux : année +2 | B15: 0.1 | C15: % | D15: EST
A16: Gros entretien patrimonial annuel (% prix+travaux) | B16: 0.018 | C16: % | D16: ≈ 41 k€/an sur (bâti + travaux) : Demeure Historique ≥ 40 k€/an hors restauration (PL [A8]) ; Barnes 20-80 k€/an [A4 §11] ; démarre en année d'acquisition + 3
... A20: Loyer de la partie privée payé par le fondateur (hors CA d'exploitation) | B20: 0 | C20: € | D20: Correction audit M1 : aucun loyer privé compté — le logis doit être détenu à part (SCI à l'IR, hors taxe 235 ter C [A6]) et payé par le fondateur personnellement
A22: 2. Financement
A23: Apport du fondateur (année 1) | B23: 1000000 | C23: € | D23: Scénario d'apport S3 (hypothèse ; apport réel inconnu)
A24: Fonds propres apportés à l'acquisition (investisseurs ou holding) | B24: 0 | C24: € | D24: Aucun investisseur
A25: Ces fonds propres viennent-ils de la holding du fondateur ? (1/0) | B25: 0
A26: Subventions (non acquises : 0 par défaut) | B26: 0 | C26: € | D26: Aucune subvention considérée comme acquise
A27: Dette bancaire (année d'acquisition) | B27: 2400000 | C27: € | D27: NON ACQUIS — montage 1 [A2] : prêt hypothécaire 20 ans ; LTV ≈ 70 %, jugée trop élevée par l'agent 2
A28: Taux de la dette bancaire | B28: 0.04 | C28: % | D28: PL : nouveaux crédits PME 3,64 % (FBF, 06/2026) ; EX : 3,66 % (BdF, 08/2026) ; retenu 4,0 % [A2]
A29: Durée dette bancaire | B29: 20 | C29: ans | D29: A2 (Bpifrance : 15 ans avec hypothèque, PL)
A30: Différé d'amortissement (dans la durée) | B30: 1 | C30: ans | D30: EST
A31: Crédit-vendeur | B31: 0 | C31: €
A32: Taux crédit-vendeur | B32: 0.03 | C32: % | D32: EST
A33: Durée crédit-vendeur (amortissable) | B33: 12 | C33: ans | D33: EST
A34: Obligations / quasi-fonds propres (in fine) | B34: 0 | C34: €
A35: Coupon annuel des obligations | B35: 0.07 | C35: % | D35: PL : obligations Château Fontenay 7 % [A2]
A36: Année de remboursement des obligations | B36: 6 | C36: année | D36: EST
A37: Part de capital supplémentaire accordée au fondateur pour son travail (sweat equity) | B37: 0 | C37: % | D37: Fondateur seul
A38: Droits de vote du fondateur | B38: 1 | C38: %
A39: Réserve de liquidité cible | B39: 150000 | C39: € | D39: EST
A40: TRI minimal exigé par des investisseurs extérieurs | B40: 0.06 | C40: % | D40: EST : rendement minimal d'un investisseur en fonds propres illiquide (Anaxago affiche 8,7 % net, PL [A2])
A41: Le dirigeant est-il rémunéré par le domaine ? (1/0) | B41: 1 | D41: Rémunération du dirigeant incluse
A42: Part du capital du fondateur (calculée : apports au prorata + prime d'industrie, plafonnée à 100 %) | B42: =MIN(1,($B$23+$B$24*$B$25)/MAX(1,$B$23+$B$24)+$B$37)
A44: 3. Paramètres de stress (neutres = 100 % / 0)
A45: Multiplicateur de chiffre d'affaires | B45: 1 | C45: % | D45: neutre
A46: Multiplicateur du budget travaux | B46: 1 | C46: % | D46: neutre
A47: Retard d'ouverture | B47: 0 | C47: ans | D47: neutre
A48: Hausse du taux bancaire (points) | B48: 0 | C48: % | D48: neutre
A49: Part des fonds investisseurs non versée | B49: 0 | C49: % | D49: neutre
A50: Part des événements annulés | B50: 0 | C50: % | D50: neutre
A52: 4. Exploitation — hypothèses générales
A53: Montée en charge : 1re année d'exploitation | B53: 0.6 | C53: % | D53: Cas optimiste
A54: Montée en charge : 2e année | B54: 0.9 | C54: % | D54: Cas optimiste
A55: Montée en charge : 3e année | B55: 1 | C55: % | D55: Cas optimiste
A56: Indexation annuelle des prix | B56: 0.02 | C56: % | D56: EST
A57: Inflation annuelle des charges | B57: 0.02 | C57: % | D57: EST : indexation identique aux prix (correction audit, biais pessimiste retiré)
A58: BFR en % du CA (négatif = acomptes clients) | B58: -0.03 | C58: % | D58: Acomptes (mariages, pensions payées d'avance) — EST
A59: Taux normal d'IS | B59: 0.25 | C59: % | D59: PL : IS 25 % au-delà de 42 500 € [A6]
A60: Taux réduit d'IS (PME, jusqu'au seuil) | B60: 0.15 | C60: % | D60: PL : 15 % jusqu'à 42 500 € (PME) [A6]
A61: Seuil du taux réduit d'IS | B61: 42500 | C61: € | D61: PL [A6]
A63: 5. Lignes de revenus (à maturité, euros de l'année d'ouverture)
A64: Libellé | B64: Volume | C64: Prix unitaire | D64: Coût var. % | E64: Événement ? | F64: Équestre ? | G64: Unité / source
A65: Pension box premium (places occupées) | B65: 25.3 | C65: 5527 | D65: 0.23 | E65: 0 | F65: 1 | G65: PL : 450 € TTC/mois = 3e quartile hors IdF (médiane 375 €, 10 % des offres ≥ 520 €) [A3, recalcul A8] → 426,5 € HT à TVA 5,5 % ; 24 box × 92 % ; coûts directs 1 200 €/an EST
A66: Pension au pré (places occupées) | B66: 26.4 | C66: 2702 | D66: 0.245 | E66: 0 | F66: 1 | G66: PL : 220 € TTC/mois (médianes 200-240 €) → 208,5 € HT [A3 H3] ; 25 places × 92 % ; coûts 613 €/an [A3 §4]
A67: Pension retraite / convalescence (places occupées) | B67: 10.3 | C67: 2268 | D67: 0.24 | E67: 0 | F67: 1 | G67: PL : 210 € TTC/mois, TVA 20 % → 175 € HT [A3 H4] ; 10 places × 90 %
A68: Mariages (location du lieu + hébergement 15 couchages) | B68: 13.8 | C68: 4533 | D68: 0.43 | E68: 1 | F68: 0 | G68: PL : médiane 3 400 € TTC location (17 châteaux) + 1 500 € TTC hébergement → 4 197 € HT [A4 §13.1] ; 12/an EST ; coût variable 1 450 € + 8 %
A69: Gîte 15 couchages hors mariages (nuits) | B69: 105.8 | C69: 486 | D69: 0.45 | E69: 0 | F69: 0 | G69: PL : fourchettes de prix [A4 §4.2] ; 92 nuits EST (occupation annuelle ≈ 33 % observée en Normandie hors saison) [A4 §4.3]
A70: Séminaires à la journée (jours) | B70: 13.8 | C70: 864 | D70: 0.19 | E70: 1 | F70: 0 | G70: PL : salle 1 000 €/jour (Feugerets) ; 800 € HT retenu [A4 §3]
A71: Tournages / shootings (jours) | B71: 3.4 | C71: 2160 | D71: 0.15 | E71: 1 | F71: 0 | G71: PL : 1 500-4 000 €/jour [A4 §5] ; fréquence EST
A72: Fermage / vente d'herbe (ha) | B72: 11.5 | C72: 162 | D72: 0 | E72: 0 | F72: 0 | G72: PL : arrêtés Orne/Calvados 2026-27 : 50-268 €/ha [A4 §8.2]
A74: 6. Charges fixes annuelles (euros de l'année d'ouverture)
A75: Libellé | B75: Montant/an | C75: Dès l'acq. (1) / dès l'ouverture (0) | G75: Source / statut
A76: Taxe foncière | B76: 5700 | C76: 1 | G76: EX : 2,6-4,0 k€ sur 3 annonces ; EST 4-8 k€ [A4 §11]
A77: Assurance multirisque château | B77: 11400 | C77: 1 | G77: Correction audit : courtier spécialisé 15-30 k€ (fiabilité moyenne), annonces ≥ 2,5 k€ [A4 §11, A8] ; EST 12 k€
A78: Énergie (chauffage partiel, électricité, eau) | B78: 19000 | C78: 1 | G78: PL : Meung, Louvignies ; EX annonce Montluçon 18-25 k€ [A1, A4 §11] ; EST
A79: Jardinier / agent d'entretien (1 ETP au Smic chargé) | B79: 25650 | C79: 1 | G79: PL : Smic 2026 22 404 € brut/an [A4 §11] ; EST charges
A80: Divers (abonnements, petit matériel, véhicule, honoraires) | B80: 7600 | C80: 1 | G80: EST
A81: Soigneurs (3 ETP au Smic chargés) | B81: 85500 | C81: 0 | G81: PL : Smic 1 867 €/mois, grille IDCC 7026 inférieure ; 1 ETP / 17-20 équidés [A3 H13-H14] ; ~54 équidés → 3 ETP (correction audit M5)
A82: Autres charges de structure équestres (entretien installations, matériel, assurance RC, énergie écuries) | B82: 28500 | C82: 0 | G82: Calibré pour un EBE équestre ≈ 37 % (réf. pension hébergement 36-38 %, PL [A3 H10])
A83: Coûts fixes mariages (coordination, nettoyage, publicité) | B83: 10450 | C83: 0 | G83: EST [A4 §13.1]
A84: Coûts fixes du gîte | B84: 4180 | C84: 0 | G84: EST [A4 §13.1]
A85: Commercial, site, salons | B85: 11400 | C85: 0 | G85: EST
A86: Comptabilité, juridique, banque, logiciels | B86: 11400 | C86: 0 | G86: EST
A87: Rémunération du dirigeant (chargée) | B87: 33250 | C87: 0 | G87: EST : minimum ; le dirigeant paie en plus 18 k€ de loyer privé
A89: 7. Calcul sur 10 ans
A90: Année | B90: Total / réf. | C90: 1 | D90: 2 | E90: 3 | F90: 4 | G90: 5 | H90: 6 | I90: 7 | J90: 8 | K90: 9 | L90: 10
A91: Année d'ouverture effective | C91: =$B$6+$B$47 | D91: =$B$6+$B$47 | E91: =$B$6+$B$47 | F91: =$B$6+$B$47 | G91: =$B$6+$B$47 | H91: =$B$6+$B$47 | I91: =$B$6+$B$47 | J91: =$B$6+$B$47 | ... L91: =$B$6+$B$47
A92: Rang de l'année d'exploitation | C92: =MAX(0,C$90-C91+1) | D92: =MAX(0,D$90-D91+1) | E92: =MAX(0,E$90-E91+1) | F92: =MAX(0,F$90-F91+1) | G92: =MAX(0,G$90-G91+1) | H92: =MAX(0,H$90-H91+1) | I92: =MAX(0,I$90-I91+1) | J92: =MAX(0,J$90-J91+1) | ... L92: =MAX(0,L$90-L91+1)
A93: Coefficient de montée en charge | C93: =IF(C92=0,0,IF(C92=1,$B$53,IF(C92=2,$B$54,IF(C92=3,$B$55,1)))) | D93: =IF(D92=0,0,IF(D92=1,$B$53,IF(D92=2,$B$54,IF(D92=3,$B$55,1)))) | E93: =IF(E92=0,0,IF(E92=1,$B$53,IF(E92=2,$B$54,IF(E92=3,$B$55,1)))) | F93: =IF(F92=0,0,IF(F92=1,$B$53,IF(F92=2,$B$54,IF(F92=3,$B$55,1)))) | G93: =IF(G92=0,0,IF(G92=1,$B$53,IF(G92=2,$B$54,IF(G92=3,$B$55,1)))) | H93: =IF(H92=0,0,IF(H92=1,$B$53,IF(H92=2,$B$54,IF(H92=3,$B$55,1)))) | I93: =IF(I92=0,0,IF(I92=1,$B$53,IF(I92=2,$B$54,IF(I92=3,$B$55,1)))) | J93: =IF(J92=0,0,IF(J92=1,$B$53,IF(J92=2,$B$54,IF(J92=3,$B$55,1)))) | ... L93: =IF(L92=0,0,IF(L92=1,$B$53,IF(L92=2,$B$54,IF(L92=3,$B$55,1))))
A94: Indice prix | C94: =(1+$B$56)^(C$90-1) | D94: =(1+$B$56)^(D$90-1) | E94: =(1+$B$56)^(E$90-1) | F94: =(1+$B$56)^(F$90-1) | G94: =(1+$B$56)^(G$90-1) | H94: =(1+$B$56)^(H$90-1) | I94: =(1+$B$56)^(I$90-1) | J94: =(1+$B$56)^(J$90-1) | ... L94: =(1+$B$56)^(L$90-1)
A95: Indice charges | C95: =(1+$B$57)^(C$90-1) | D95: =(1+$B$57)^(D$90-1) | E95: =(1+$B$57)^(E$90-1) | F95: =(1+$B$57)^(F$90-1) | G95: =(1+$B$57)^(G$90-1) | H95: =(1+$B$57)^(H$90-1) | I95: =(1+$B$57)^(I$90-1) | J95: =(1+$B$57)^(J$90-1) | ... L95: =(1+$B$57)^(L$90-1)
A96: Murs détenus (1/0) | C96: =IF(C$90>=$B$5,1,0) | D96: =IF(D$90>=$B$5,1,0) | E96: =IF(E$90>=$B$5,1,0) | F96: =IF(F$90>=$B$5,1,0) | G96: =IF(G$90>=$B$5,1,0) | H96: =IF(H$90>=$B$5,1,0) | I96: =IF(I$90>=$B$5,1,0) | J96: =IF(J$90>=$B$5,1,0) | ... L96: =IF(L$90>=$B$5,1,0)
A98: Compte de résultat
A99: Pension box premium (places occupées) | B99: =SUM(C99:L99) | C99: =$B$65*$C$65*C93*C94*$B$45*(1-$E$65*$B$50) | D99: =$B$65*$C$65*D93*D94*$B$45*(1-$E$65*$B$50) | E99: =$B$65*$C$65*E93*E94*$B$45*(1-$E$65*$B$50) | F99: =$B$65*$C$65*F93*F94*$B$45*(1-$E$65*$B$50) | G99: =$B$65*$C$65*G93*G94*$B$45*(1-$E$65*$B$50) | H99: =$B$65*$C$65*H93*H94*$B$45*(1-$E$65*$B$50) | I99: =$B$65*$C$65*I93*I94*$B$45*(1-$E$65*$B$50) | J99: =$B$65*$C$65*J93*J94*$B$45*(1-$E$65*$B$50) | ... L99: =$B$65*$C$65*L93*L94*$B$45*(1-$E$65*$B$50)
A100: Pension au pré (places occupées) | B100: =SUM(C100:L100) | C100: =$B$66*$C$66*C93*C94*$B$45*(1-$E$66*$B$50) | D100: =$B$66*$C$66*D93*D94*$B$45*(1-$E$66*$B$50) | E100: =$B$66*$C$66*E93*E94*$B$45*(1-$E$66*$B$50) | F100: =$B$66*$C$66*F93*F94*$B$45*(1-$E$66*$B$50) | G100: =$B$66*$C$66*G93*G94*$B$45*(1-$E$66*$B$50) | H100: =$B$66*$C$66*H93*H94*$B$45*(1-$E$66*$B$50) | I100: =$B$66*$C$66*I93*I94*$B$45*(1-$E$66*$B$50) | J100: =$B$66*$C$66*J93*J94*$B$45*(1-$E$66*$B$50) | ... L100: =$B$66*$C$66*L93*L94*$B$45*(1-$E$66*$B$50)
A101: Pension retraite / convalescence (places occupées) | B101: =SUM(C101:L101) | C101: =$B$67*$C$67*C93*C94*$B$45*(1-$E$67*$B$50) | D101: =$B$67*$C$67*D93*D94*$B$45*(1-$E$67*$B$50) | E101: =$B$67*$C$67*E93*E94*$B$45*(1-$E$67*$B$50) | F101: =$B$67*$C$67*F93*F94*$B$45*(1-$E$67*$B$50) | G101: =$B$67*$C$67*G93*G94*$B$45*(1-$E$67*$B$50) | H101: =$B$67*$C$67*H93*H94*$B$45*(1-$E$67*$B$50) | I101: =$B$67*$C$67*I93*I94*$B$45*(1-$E$67*$B$50) | J101: =$B$67*$C$67*J93*J94*$B$45*(1-$E$67*$B$50) | ... L101: =$B$67*$C$67*L93*L94*$B$45*(1-$E$67*$B$50)
A102: Mariages (location du lieu + hébergement 15 couchages) | B102: =SUM(C102:L102) | C102: =$B$68*$C$68*C93*C94*$B$45*(1-$E$68*$B$50) | D102: =$B$68*$C$68*D93*D94*$B$45*(1-$E$68*$B$50) | E102: =$B$68*$C$68*E93*E94*$B$45*(1-$E$68*$B$50) | F102: =$B$68*$C$68*F93*F94*$B$45*(1-$E$68*$B$50) | G102: =$B$68*$C$68*G93*G94*$B$45*(1-$E$68*$B$50) | H102: =$B$68*$C$68*H93*H94*$B$45*(1-$E$68*$B$50) | I102: =$B$68*$C$68*I93*I94*$B$45*(1-$E$68*$B$50) | J102: =$B$68*$C$68*J93*J94*$B$45*(1-$E$68*$B$50) | ... L102: =$B$68*$C$68*L93*L94*$B$45*(1-$E$68*$B$50)
A103: Gîte 15 couchages hors mariages (nuits) | B103: =SUM(C103:L103) | C103: =$B$69*$C$69*C93*C94*$B$45*(1-$E$69*$B$50) | D103: =$B$69*$C$69*D93*D94*$B$45*(1-$E$69*$B$50) | E103: =$B$69*$C$69*E93*E94*$B$45*(1-$E$69*$B$50) | F103: =$B$69*$C$69*F93*F94*$B$45*(1-$E$69*$B$50) | G103: =$B$69*$C$69*G93*G94*$B$45*(1-$E$69*$B$50) | H103: =$B$69*$C$69*H93*H94*$B$45*(1-$E$69*$B$50) | I103: =$B$69*$C$69*I93*I94*$B$45*(1-$E$69*$B$50) | J103: =$B$69*$C$69*J93*J94*$B$45*(1-$E$69*$B$50) | ... L103: =$B$69*$C$69*L93*L94*$B$45*(1-$E$69*$B$50)
A104: Séminaires à la journée (jours) | B104: =SUM(C104:L104) | C104: =$B$70*$C$70*C93*C94*$B$45*(1-$E$70*$B$50) | D104: =$B$70*$C$70*D93*D94*$B$45*(1-$E$70*$B$50) | E104: =$B$70*$C$70*E93*E94*$B$45*(1-$E$70*$B$50) | F104: =$B$70*$C$70*F93*F94*$B$45*(1-$E$70*$B$50) | G104: =$B$70*$C$70*G93*G94*$B$45*(1-$E$70*$B$50) | H104: =$B$70*$C$70*H93*H94*$B$45*(1-$E$70*$B$50) | I104: =$B$70*$C$70*I93*I94*$B$45*(1-$E$70*$B$50) | J104: =$B$70*$C$70*J93*J94*$B$45*(1-$E$70*$B$50) | ... L104: =$B$70*$C$70*L93*L94*$B$45*(1-$E$70*$B$50)
A105: Tournages / shootings (jours) | B105: =SUM(C105:L105) | C105: =$B$71*$C$71*C93*C94*$B$45*(1-$E$71*$B$50) | D105: =$B$71*$C$71*D93*D94*$B$45*(1-$E$71*$B$50) | E105: =$B$71*$C$71*E93*E94*$B$45*(1-$E$71*$B$50) | F105: =$B$71*$C$71*F93*F94*$B$45*(1-$E$71*$B$50) | G105: =$B$71*$C$71*G93*G94*$B$45*(1-$E$71*$B$50) | H105: =$B$71*$C$71*H93*H94*$B$45*(1-$E$71*$B$50) | I105: =$B$71*$C$71*I93*I94*$B$45*(1-$E$71*$B$50) | J105: =$B$71*$C$71*J93*J94*$B$45*(1-$E$71*$B$50) | ... L105: =$B$71*$C$71*L93*L94*$B$45*(1-$E$71*$B$50)
A106: Fermage / vente d'herbe (ha) | B106: =SUM(C106:L106) | C106: =$B$72*$C$72*C93*C94*$B$45*(1-$E$72*$B$50) | D106: =$B$72*$C$72*D93*D94*$B$45*(1-$E$72*$B$50) | E106: =$B$72*$C$72*E93*E94*$B$45*(1-$E$72*$B$50) | F106: =$B$72*$C$72*F93*F94*$B$45*(1-$E$72*$B$50) | G106: =$B$72*$C$72*G93*G94*$B$45*(1-$E$72*$B$50) | H106: =$B$72*$C$72*H93*H94*$B$45*(1-$E$72*$B$50) | I106: =$B$72*$C$72*I93*I94*$B$45*(1-$E$72*$B$50) | J106: =$B$72*$C$72*J93*J94*$B$45*(1-$E$72*$B$50) | ... L106: =$B$72*$C$72*L93*L94*$B$45*(1-$E$72*$B$50)
A107: Chiffre d'affaires total | B107: =SUM(C107:L107) | C107: =C99+C100+C101+C102+C103+C104+C105+C106 | D107: =D99+D100+D101+D102+D103+D104+D105+D106 | E107: =E99+E100+E101+E102+E103+E104+E105+E106 | F107: =F99+F100+F101+F102+F103+F104+F105+F106 | G107: =G99+G100+G101+G102+G103+G104+G105+G106 | H107: =H99+H100+H101+H102+H103+H104+H105+H106 | I107: =I99+I100+I101+I102+I103+I104+I105+I106 | J107: =J99+J100+J101+J102+J103+J104+J105+J106 | ... L107: =L99+L100+L101+L102+L103+L104+L105+L106
A108: dont équestre | B108: =SUM(C108:L108) | C108: =C99*$F$65+C100*$F$66+C101*$F$67+C102*$F$68+C103*$F$69+C104*$F$70+C105*$F$71+C106*$F$72 | D108: =D99*$F$65+D100*$F$66+D101*$F$67+D102*$F$68+D103*$F$69+D104*$F$70+D105*$F$71+D106*$F$72 | E108: =E99*$F$65+E100*$F$66+E101*$F$67+E102*$F$68+E103*$F$69+E104*$F$70+E105*$F$71+E106*$F$72 | F108: =F99*$F$65+F100*$F$66+F101*$F$67+F102*$F$68+F103*$F$69+F104*$F$70+F105*$F$71+F106*$F$72 | G108: =G99*$F$65+G100*$F$66+G101*$F$67+G102*$F$68+G103*$F$69+G104*$F$70+G105*$F$71+G106*$F$72 | H108: =H99*$F$65+H100*$F$66+H101*$F$67+H102*$F$68+H103*$F$69+H104*$F$70+H105*$F$71+H106*$F$72 | I108: =I99*$F$65+I100*$F$66+I101*$F$67+I102*$F$68+I103*$F$69+I104*$F$70+I105*$F$71+I106*$F$72 | J108: =J99*$F$65+J100*$F$66+J101*$F$67+J102*$F$68+J103*$F$69+J104*$F$70+J105*$F$71+J106*$F$72 | ... L108: =L99*$F$65+L100*$F$66+L101*$F$67+L102*$F$68+L103*$F$69+L104*$F$70+L105*$F$71+L106*$F$72
A109: Part équestre du CA | C109: =IF(C107=0,0,C108/C107) | D109: =IF(D107=0,0,D108/D107) | E109: =IF(E107=0,0,E108/E107) | F109: =IF(F107=0,0,F108/F107) | G109: =IF(G107=0,0,G108/G107) | H109: =IF(H107=0,0,H108/H107) | I109: =IF(I107=0,0,I108/I107) | J109: =IF(J107=0,0,J108/J107) | ... L109: =IF(L107=0,0,L108/L107)
A110: Coûts variables | B110: =SUM(C110:L110) | C110: =-(C99*$D$65+C100*$D$66+C101*$D$67+C102*$D$68+C103*$D$69+C104*$D$70+C105*$D$71+C106*$D$72) | D110: =-(D99*$D$65+D100*$D$66+D101*$D$67+D102*$D$68+D103*$D$69+D104*$D$70+D105*$D$71+D106*$D$72) | E110: =-(E99*$D$65+E100*$D$66+E101*$D$67+E102*$D$68+E103*$D$69+E104*$D$70+E105*$D$71+E106*$D$72) | F110: =-(F99*$D$65+F100*$D$66+F101*$D$67+F102*$D$68+F103*$D$69+F104*$D$70+F105*$D$71+F106*$D$72) | G110: =-(G99*$D$65+G100*$D$66+G101*$D$67+G102*$D$68+G103*$D$69+G104*$D$70+G105*$D$71+G106*$D$72) | H110: =-(H99*$D$65+H100*$D$66+H101*$D$67+H102*$D$68+H103*$D$69+H104*$D$70+H105*$D$71+H106*$D$72) | I110: =-(I99*$D$65+I100*$D$66+I101*$D$67+I102*$D$68+I103*$D$69+I104*$D$70+I105*$D$71+I106*$D$72) | J110: =-(J99*$D$65+J100*$D$66+J101*$D$67+J102*$D$68+J103*$D$69+J104*$D$70+J105*$D$71+J106*$D$72) | ... L110: =-(L99*$D$65+L100*$D$66+L101*$D$67+L102*$D$68+L103*$D$69+L104*$D$70+L105*$D$71+L106*$D$72)
A111: Marge sur coûts variables | B111: =SUM(C111:L111) | C111: =C107+C110 | D111: =D107+D110 | E111: =E107+E110 | F111: =F107+F110 | G111: =G107+G110 | H111: =H107+H110 | I111: =I107+I110 | J111: =J107+J110 | ... L111: =L107+L110
...

Sheet B_club_deal
A1: B — Club deal : apport 250 k€, investisseurs majoritaires (montage 2) — cas central
A2: Cellules jaunes/bleues = hypothèses éditables. Tout le reste est calculé. Colonne D (bloc hypothèses) = source ou statut (ESTIMATION = non vérifiée).
A4: 1. Calendrier, acquisition et travaux
A5: Année d'acquisition des murs (1 = immédiate) | B5: 1 | C5: année | D5: Achat immédiat (2027)
A6: Année d'ouverture commerciale (avant stress) | B6: 2 | C6: année | D6: Année 1 = travaux ; EST
A7: Prix d'acquisition | B7: 2500000 | C7: € | D7: PL : médiane de 19 annonces de châteaux ≥ 30 ha (quartiles 1,29-3,07 M€) [A1]
A8: Frais d'acquisition (droits + notaire) | B8: 0.075 | C8: % | D8: EST : DMTO ≈ 5,8-6,3 % + notaire ≈ 1,2 % ; vente SAFER : frais 8,4 % TTC mais exonération de droits possible [A1, PL]
A9: Part du prix affectable au bâti (amortissable) | B9: 0.55 | C9: % | D9: EST
A10: Travaux de restauration / mise aux normes | B10: 500000 | C10: € | D10: EST sans visite : top 5 des biens équipés 0,1-0,7 M€ [A1]
A11: Investissements équestres (boxes, carrière, manège…) | B11: 150000 | C11: € | D11: EST : remise à niveau d'écuries existantes (une écurie neuve de 30 box coûterait 0,78-0,83 M€ HT [A3 H20])
A12: Investissements événementiel / hébergement | B12: 250000 | C12: € | D12: EST : mise aux normes d'une salle existante + aménagement du gîte (neuf : 570 k€-1,24 M€ [A4 §13.2])
A13: Répartition travaux : année d'acquisition | B13: 0.6 | C13: % | D13: EST
A14: Répartition travaux : année +1 | B14: 0.3 | C14: % | D14: EST
A15: Répartition travaux : année +2 | B15: 0.1 | C15: % | D15: EST
A16: Gros entretien patrimonial annuel (% prix+travaux) | B16: 0.018 | C16: % | D16: ≈ 41 k€/an sur (bâti + travaux) : Demeure Historique ≥ 40 k€/an hors restauration (PL [A8]) ; Barnes 20-80 k€/an [A4 §11] ; démarre en année d'acquisition + 3
... A20: Loyer de la partie privée payé par le fondateur (hors CA d'exploitation) | B20: 0 | C20: € | D20: Correction audit M1 : aucun loyer privé compté — le logis doit être détenu à part (SCI à l'IR, hors taxe 235 ter C [A6]) et payé par le fondateur personnellement
A22: 2. Financement
A23: Apport du fondateur (année 1) | B23: 250000 | C23: € | D23: Scénario d'apport S2
A24: Fonds propres apportés à l'acquisition (investisseurs ou holding) | B24: 1640000 | C24: € | D24: NON ACQUIS — investisseurs à trouver [A2 montage 2]
A25: Ces fonds propres viennent-ils de la holding du fondateur ? (1/0) | B25: 0
A26: Subventions (non acquises : 0 par défaut) | B26: 0 | C26: € | D26: Aucune subvention considérée comme acquise
A27: Dette bancaire (année d'acquisition) | B27: 1800000 | C27: € | D27: NON ACQUIS — LTV ≈ 50 % [A2 montage 2]
A28: Taux de la dette bancaire | B28: 0.04 | C28: % | D28: PL : nouveaux crédits PME 3,64 % (FBF, 06/2026) ; EX : 3,66 % (BdF, 08/2026) ; retenu 4,0 % [A2]
A29: Durée dette bancaire | B29: 20 | C29: ans | D29: A2 (Bpifrance : 15 ans avec hypothèque, PL)
A30: Différé d'amortissement (dans la durée) | B30: 1 | C30: ans | D30: EST
A31: Crédit-vendeur | B31: 0 | C31: €
A32: Taux crédit-vendeur | B32: 0.03 | C32: % | D32: EST
A33: Durée crédit-vendeur (amortissable) | B33: 12 | C33: ans | D33: EST
A34: Obligations / quasi-fonds propres (in fine) | B34: 0 | C34: €
A35: Coupon annuel des obligations | B35: 0.07 | C35: % | D35: PL : obligations Château Fontenay 7 % [A2]
A36: Année de remboursement des obligations | B36: 6 | C36: année | D36: EST
A37: Part de capital supplémentaire accordée au fondateur pour son travail (sweat equity) | B37: 0.05 | C37: % | D37: EST : promote négociée
A38: Droits de vote du fondateur | B38: 0.1 | C38: % | D38: Investisseurs majoritaires [A2]
A39: Réserve de liquidité cible | B39: 150000 | C39: € | D39: EST
A40: TRI minimal exigé par des investisseurs extérieurs | B40: 0.06 | C40: % | D40: EST : rendement minimal d'un investisseur en fonds propres illiquide (Anaxago affiche 8,7 % net, PL [A2])
A41: Le dirigeant est-il rémunéré par le domaine ? (1/0) | B41: 1 | D41: Rémunération du dirigeant incluse
A42: Part du capital du fondateur (calculée : apports au prorata + prime d'industrie, plafonnée à 100 %) | B42: =MIN(1,($B$23+$B$24*$B$25)/MAX(1,$B$23+$B$24)+$B$37)
A44: 3. Paramètres de stress (neutres = 100 % / 0)
A45: Multiplicateur de chiffre d'affaires | B45: 1 | C45: % | D45: neutre
A46: Multiplicateur du budget travaux | B46: 1 | C46: % | D46: neutre
A47: Retard d'ouverture | B47: 0 | C47: ans | D47: neutre
A48: Hausse du taux bancaire (points) | B48: 0 | C48: % | D48: neutre
A49: Part des fonds investisseurs non versée | B49: 0 | C49: % | D49: neutre
A50: Part des événements annulés | B50: 0 | C50: % | D50: neutre
A52: 4. Exploitation — hypothèses générales
A53: Montée en charge : 1re année d'exploitation | B53: 0.5 | C53: % | D53: A4 : mariages 40/70/100 % ; gîte 50/80/100 %
A54: Montée en charge : 2e année | B54: 0.8 | C54: % | D54: EST
A55: Montée en charge : 3e année | B55: 1 | C55: % | D55: EST
A56: Indexation annuelle des prix | B56: 0.02 | C56: % | D56: EST
A57: Inflation annuelle des charges | B57: 0.02 | C57: % | D57: EST : indexation identique aux prix (correction audit, biais pessimiste retiré)
A58: BFR en % du CA (négatif = acomptes clients) | B58: -0.03 | C58: % | D58: Acomptes (mariages, pensions payées d'avance) — EST
A59: Taux normal d'IS | B59: 0.25 | C59: % | D59: PL : IS 25 % au-delà de 42 500 € [A6]
A60: Taux réduit d'IS (PME, jusqu'au seuil) | B60: 0.15 | C60: % | D60: PL : 15 % jusqu'à 42 500 € (PME) [A6]
A61: Seuil du taux réduit d'IS | B61: 42500 | C61: € | D61: PL [A6]
A63: 5. Lignes de revenus (à maturité, euros de l'année d'ouverture)
A64: Libellé | B64: Volume | C64: Prix unitaire | D64: Coût var. % | E64: Événement ? | F64: Équestre ? | G64: Unité / source
A65: Pension box premium (places occupées) | B65: 22 | C65: 5118 | D65: 0.23 | E65: 0 | F65: 1 | G65: PL : 450 € TTC/mois = 3e quartile hors IdF (médiane 375 €, 10 % des offres ≥ 520 €) [A3, recalcul A8] → 426,5 € HT à TVA 5,5 % ; 24 box × 92 % ; coûts directs 1 200 €/an EST
A66: Pension au pré (places occupées) | B66: 23 | C66: 2502 | D66: 0.245 | E66: 0 | F66: 1 | G66: PL : 220 € TTC/mois (médianes 200-240 €) → 208,5 € HT [A3 H3] ; 25 places × 92 % ; coûts 613 €/an [A3 §4]
A67: Pension retraite / convalescence (places occupées) | B67: 9 | C67: 2100 | D67: 0.24 | E67: 0 | F67: 1 | G67: PL : 210 € TTC/mois, TVA 20 % → 175 € HT [A3 H4] ; 10 places × 90 %
A68: Mariages (location du lieu + hébergement 15 couchages) | B68: 12 | C68: 4197 | D68: 0.43 | E68: 1 | F68: 0 | G68: PL : médiane 3 400 € TTC location (17 châteaux) + 1 500 € TTC hébergement → 4 197 € HT [A4 §13.1] ; 12/an EST ; coût variable 1 450 € + 8 %
A69: Gîte 15 couchages hors mariages (nuits) | B69: 92 | C69: 450 | D69: 0.45 | E69: 0 | F69: 0 | G69: PL : fourchettes de prix [A4 §4.2] ; 92 nuits EST (occupation annuelle ≈ 33 % observée en Normandie hors saison) [A4 §4.3]
A70: Séminaires à la journée (jours) | B70: 12 | C70: 800 | D70: 0.19 | E70: 1 | F70: 0 | G70: PL : salle 1 000 €/jour (Feugerets) ; 800 € HT retenu [A4 §3]
A71: Tournages / shootings (jours) | B71: 3 | C71: 2000 | D71: 0.15 | E71: 1 | F71: 0 | G71: PL : 1 500-4 000 €/jour [A4 §5] ; fréquence EST
A72: Fermage / vente d'herbe (ha) | B72: 10 | C72: 150 | D72: 0 | E72: 0 | F72: 0 | G72: PL : arrêtés Orne/Calvados 2026-27 : 50-268 €/ha [A4 §8.2]
A74: 6. Charges fixes annuelles (euros de l'année d'ouverture)
A75: Libellé | B75: Montant/an | C75: Dès l'acq. (1) / dès l'ouverture (0) | G75: Source / statut
A76: Taxe foncière | B76: 6000 | C76: 1 | G76: EX : 2,6-4,0 k€ sur 3 annonces ; EST 4-8 k€ [A4 §11]
A77: Assurance multirisque château | B77: 12000 | C77: 1 | G77: Correction audit : courtier spécialisé 15-30 k€ (fiabilité moyenne), annonces ≥ 2,5 k€ [A4 §11, A8] ; EST 12 k€
A78: Énergie (chauffage partiel, électricité, eau) | B78: 20000 | C78: 1 | G78: PL : Meung, Louvignies ; EX annonce Montluçon 18-25 k€ [A1, A4 §11] ; EST
A79: Jardinier / agent d'entretien (1 ETP au Smic chargé) | B79: 27000 | C79: 1 | G79: PL : Smic 2026 22 404 € brut/an [A4 §11] ; EST charges
A80: Divers (abonnements, petit matériel, véhicule, honoraires) | B80: 8000 | C80: 1 | G80: EST
A81: Soigneurs (3 ETP au Smic chargés) | B81: 90000 | C81: 0 | G81: PL : Smic 1 867 €/mois, grille IDCC 7026 inférieure ; 1 ETP / 17-20 équidés [A3 H13-H14] ; ~54 équidés → 3 ETP (correction audit M5)
A82: Autres charges de structure équestres (entretien installations, matériel, assurance RC, énergie écuries) | B82: 30000 | C82: 0 | G82: Calibré pour un EBE équestre ≈ 37 % (réf. pension hébergement 36-38 %, PL [A3 H10])
A83: Coûts fixes mariages (coordination, nettoyage, publicité) | B83: 11000 | C83: 0 | G83: EST [A4 §13.1]
A84: Coûts fixes du gîte | B84: 4400 | C84: 0 | G84: EST [A4 §13.1]
A85: Commercial, site, salons | B85: 12000 | C85: 0 | G85: EST
A86: Comptabilité, juridique, banque, logiciels | B86: 12000 | C86: 0 | G86: EST
A87: Rémunération du dirigeant (chargée) | B87: 35000 | C87: 0 | G87: EST : minimum ; le dirigeant paie en plus 18 k€ de loyer privé
A89: 7. Calcul sur 10 ans
A90: Année | B90: Total / réf. | C90: 1 | D90: 2 | E90: 3 | F90: 4 | G90: 5 | H90: 6 | I90: 7 | J90: 8 | K90: 9 | L90: 10
A91: Année d'ouverture effective | C91: =$B$6+$B$47 | D91: =$B$6+$B$47 | E91: =$B$6+$B$47 | F91: =$B$6+$B$47 | G91: =$B$6+$B$47 | H91: =$B$6+$B$47 | I91: =$B$6+$B$47 | J91: =$B$6+$B$47 | ... L91: =$B$6+$B$47
A92: Rang de l'année d'exploitation | C92: =MAX(0,C$90-C91+1) | D92: =MAX(0,D$90-D91+1) | E92: =MAX(0,E$90-E91+1) | F92: =MAX(0,F$90-F91+1) | G92: =MAX(0,G$90-G91+1) | H92: =MAX(0,H$90-H91+1) | I92: =MAX(0,I$90-I91+1) | J92: =MAX(0,J$90-J91+1) | ... L92: =MAX(0,L$90-L91+1)
A93: Coefficient de montée en charge | C93: =IF(C92=0,0,IF(C92=1,$B$53,IF(C92=2,$B$54,IF(C92=3,$B$55,1)))) | D93: =IF(D92=0,0,IF(D92=1,$B$53,IF(D92=2,$B$54,IF(D92=3,$B$55,1)))) | E93: =IF(E92=0,0,IF(E92=1,$B$53,IF(E92=2,$B$54,IF(E92=3,$B$55,1)))) | F93: =IF(F92=0,0,IF(F92=1,$B$53,IF(F92=2,$B$54,IF(F92=3,$B$55,1)))) | G93: =IF(G92=0,0,IF(G92=1,$B$53,IF(G92=2,$B$54,IF(G92=3,$B$55,1)))) | H93: =IF(H92=0,0,IF(H92=1,$B$53,IF(H92=2,$B$54,IF(H92=3,$B$55,1)))) | I93: =IF(I92=0,0,IF(I92=1,$B$53,IF(I92=2,$B$54,IF(I92=3,$B$55,1)))) | J93: =IF(J92=0,0,IF(J92=1,$B$53,IF(J92=2,$B$54,IF(J92=3,$B$55,1)))) | ... L93: =IF(L92=0,0,IF(L92=1,$B$53,IF(L92=2,$B$54,IF(L92=3,$B$55,1))))
A94: Indice prix | C94: =(1+$B$56)^(C$90-1) | D94: =(1+$B$56)^(D$90-1) | E94: =(1+$B$56)^(E$90-1) | F94: =(1+$B$56)^(F$90-1) | G94: =(1+$B$56)^(G$90-1) | H94: =(1+$B$56)^(H$90-1) | I94: =(1+$B$56)^(I$90-1) | J94: =(1+$B$56)^(J$90-1) | ... L94: =(1+$B$56)^(L$90-1)
A95: Indice charges | C95: =(1+$B$57)^(C$90-1) | D95: =(1+$B$57)^(D$90-1) | E95: =(1+$B$57)^(E$90-1) | F95: =(1+$B$57)^(F$90-1) | G95: =(1+$B$57)^(G$90-1) | H95: =(1+$B$57)^(H$90-1) | I95: =(1+$B$57)^(I$90-1) | J95: =(1+$B$57)^(J$90-1) | ... L95: =(1+$B$57)^(L$90-1)
A96: Murs détenus (1/0) | C96: =IF(C$90>=$B$5,1,0) | D96: =IF(D$90>=$B$5,1,0) | E96: =IF(E$90>=$B$5,1,0) | F96: =IF(F$90>=$B$5,1,0) | G96: =IF(G$90>=$B$5,1,0) | H96: =IF(H$90>=$B$5,1,0) | I96: =IF(I$90>=$B$5,1,0) | J96: =IF(J$90>=$B$5,1,0) | ... L96: =IF(L$90>=$B$5,1,0)
A98: Compte de résultat
A99: Pension box premium (places occupées) | B99: =SUM(C99:L99) | C99: =$B$65*$C$65*C93*C94*$B$45*(1-$E$65*$B$50) | D99: =$B$65*$C$65*D93*D94*$B$45*(1-$E$65*$B$50) | E99: =$B$65*$C$65*E93*E94*$B$45*(1-$E$65*$B$50) | F99: =$B$65*$C$65*F93*F94*$B$45*(1-$E$65*$B$50) | G99: =$B$65*$C$65*G93*G94*$B$45*(1-$E$65*$B$50) | H99: =$B$65*$C$65*H93*H94*$B$45*(1-$E$65*$B$50) | I99: =$B$65*$C$65*I93*I94*$B$45*(1-$E$65*$B$50) | J99: =$B$65*$C$65*J93*J94*$B$45*(1-$E$65*$B$50) | ... L99: =$B$65*$C$65*L93*L94*$B$45*(1-$E$65*$B$50)
A100: Pension au pré (places occupées) | B100: =SUM(C100:L100) | C100: =$B$66*$C$66*C93*C94*$B$45*(1-$E$66*$B$50) | D100: =$B$66*$C$66*D93*D94*$B$45*(1-$E$66*$B$50) | E100: =$B$66*$C$66*E93*E94*$B$45*(1-$E$66*$B$50) | F100: =$B$66*$C$66*F93*F94*$B$45*(1-$E$66*$B$50) | G100: =$B$66*$C$66*G93*G94*$B$45*(1-$E$66*$B$50) | H100: =$B$66*$C$66*H93*H94*$B$45*(1-$E$66*$B$50) | I100: =$B$66*$C$66*I93*I94*$B$45*(1-$E$66*$B$50) | J100: =$B$66*$C$66*J93*J94*$B$45*(1-$E$66*$B$50) | ... L100: =$B$66*$C$66*L93*L94*$B$45*(1-$E$66*$B$50)
A101: Pension retraite / convalescence (places occupées) | B101: =SUM(C101:L101) | C101: =$B$67*$C$67*C93*C94*$B$45*(1-$E$67*$B$50) | D101: =$B$67*$C$67*D93*D94*$B$45*(1-$E$67*$B$50) | E101: =$B$67*$C$67*E93*E94*$B$45*(1-$E$67*$B$50) | F101: =$B$67*$C$67*F93*F94*$B$45*(1-$E$67*$B$50) | G101: =$B$67*$C$67*G93*G94*$B$45*(1-$E$67*$B$50) | H101: =$B$67*$C$67*H93*H94*$B$45*(1-$E$67*$B$50) | I101: =$B$67*$C$67*I93*I94*$B$45*(1-$E$67*$B$50) | J101: =$B$67*$C$67*J93*J94*$B$45*(1-$E$67*$B$50) | ... L101: =$B$67*$C$67*L93*L94*$B$45*(1-$E$67*$B$50)
A102: Mariages (location du lieu + hébergement 15 couchages) | B102: =SUM(C102:L102) | C102: =$B$68*$C$68*C93*C94*$B$45*(1-$E$68*$B$50) | D102: =$B$68*$C$68*D93*D94*$B$45*(1-$E$68*$B$50) | E102: =$B$68*$C$68*E93*E94*$B$45*(1-$E$68*$B$50) | F102: =$B$68*$C$68*F93*F94*$B$45*(1-$E$68*$B$50) | G102: =$B$68*$C$68*G93*G94*$B$45*(1-$E$68*$B$50) | H102: =$B$68*$C$68*H93*H94*$B$45*(1-$E$68*$B$50) | I102: =$B$68*$C$68*I93*I94*$B$45*(1-$E$68*$B$50) | J102: =$B$68*$C$68*J93*J94*$B$45*(1-$E$68*$B$50) | ... L102: =$B$68*$C$68*L93*L94*$B$45*(1-$E$68*$B$50)
A103: Gîte 15 couchages hors mariages (nuits) | B103: =SUM(C103:L103) | C103: =$B$69*$C$69*C93*C94*$B$45*(1-$E$69*$B$50) | D103: =$B$69*$C$69*D93*D94*$B$45*(1-$E$69*$B$50) | E103: =$B$69*$C$69*E93*E94*$B$45*(1-$E$69*$B$50) | F103: =$B$69*$C$69*F93*F94*$B$45*(1-$E$69*$B$50) | G103: =$B$69*$C$69*G93*G94*$B$45*(1-$E$69*$B$50) | H103: =$B$69*$C$69*H93*H94*$B$45*(1-$E$69*$B$50) | I103: =$B$69*$C$69*I93*I94*$B$45*(1-$E$69*$B$50) | J103: =$B$69*$C$69*J93*J94*$B$45*(1-$E$69*$B$50) | ... L103: =$B$69*$C$69*L93*L94*$B$45*(1-$E$69*$B$50)
A104: Séminaires à la journée (jours) | B104: =SUM(C104:L104) | C104: =$B$70*$C$70*C93*C94*$B$45*(1-$E$70*$B$50) | D104: =$B$70*$C$70*D93*D94*$B$45*(1-$E$70*$B$50) | E104: =$B$70*$C$70*E93*E94*$B$45*(1-$E$70*$B$50) | F104: =$B$70*$C$70*F93*F94*$B$45*(1-$E$70*$B$50) | G104: =$B$70*$C$70*G93*G94*$B$45*(1-$E$70*$B$50) | H104: =$B$70*$C$70*H93*H94*$B$45*(1-$E$70*$B$50) | I104: =$B$70*$C$70*I93*I94*$B$45*(1-$E$70*$B$50) | J104: =$B$70*$C$70*J93*J94*$B$45*(1-$E$70*$B$50) | ... L104: =$B$70*$C$70*L93*L94*$B$45*(1-$E$70*$B$50)
A105: Tournages / shootings (jours) | B105: =SUM(C105:L105) | C105: =$B$71*$C$71*C93*C94*$B$45*(1-$E$71*$B$50) | D105: =$B$71*$C$71*D93*D94*$B$45*(1-$E$71*$B$50) | E105: =$B$71*$C$71*E93*E94*$B$45*(1-$E$71*$B$50) | F105: =$B$71*$C$71*F93*F94*$B$45*(1-$E$71*$B$50) | G105: =$B$71*$C$71*G93*G94*$B$45*(1-$E$71*$B$50) | H105: =$B$71*$C$71*H93*H94*$B$45*(1-$E$71*$B$50) | I105: =$B$71*$C$71*I93*I94*$B$45*(1-$E$71*$B$50) | J105: =$B$71*$C$71*J93*J94*$B$45*(1-$E$71*$B$50) | ... L105: =$B$71*$C$71*L93*L94*$B$45*(1-$E$71*$B$50)
A106: Fermage / vente d'herbe (ha) | B106: =SUM(C106:L106) | C106: =$B$72*$C$72*C93*C94*$B$45*(1-$E$72*$B$50) | D106: =$B$72*$C$72*D93*D94*$B$45*(1-$E$72*$B$50) | E106: =$B$72*$C$72*E93*E94*$B$45*(1-$E$72*$B$50) | F106: =$B$72*$C$72*F93*F94*$B$45*(1-$E$72*$B$50) | G106: =$B$72*$C$72*G93*G94*$B$45*(1-$E$72*$B$50) | H106: =$B$72*$C$72*H93*H94*$B$45*(1-$E$72*$B$50) | I106: =$B$72*$C$72*I93*I94*$B$45*(1-$E$72*$B$50) | J106: =$B$72*$C$72*J93*J94*$B$45*(1-$E$72*$B$50) | ... L106: =$B$72*$C$72*L93*L94*$B$45*(1-$E$72*$B$50)
A107: Chiffre d'affaires total | B107: =SUM(C107:L107) | C107: =C99+C100+C101+C102+C103+C104+C105+C106 | D107: =D99+D100+D101+D102+D103+D104+D105+D106 | E107: =E99+E100+E101+E102+E103+E104+E105+E106 | F107: =F99+F100+F101+F102+F103+F104+F105+F106 | G107: =G99+G100+G101+G102+G103+G104+G105+G106 | H107: =H99+H100+H101+H102+H103+H104+H105+H106 | I107: =I99+I100+I101+I102+I103+I104+I105+I106 | J107: =J99+J100+J101+J102+J103+J104+J105+J106 | ... L107: =L99+L100+L101+L102+L103+L104+L105+L106
A108: dont équestre | B108: =SUM(C108:L108) | C108: =C99*$F$65+C100*$F$66+C101*$F$67+C102*$F$68+C103*$F$69+C104*$F$70+C105*$F$71+C106*$F$72 | D108: =D99*$F$65+D100*$F$66+D101*$F$67+D102*$F$68+D103*$F$69+D104*$F$70+D105*$F$71+D106*$F$72 | E108: =E99*$F$65+E100*$F$66+E101*$F$67+E102*$F$68+E103*$F$69+E104*$F$70+E105*$F$71+E106*$F$72 | F108: =F99*$F$65+F100*$F$66+F101*$F$67+F102*$F$68+F103*$F$69+F104*$F$70+F105*$F$71+F106*$F$72 | G108: =G99*$F$65+G100*$F$66+G101*$F$67+G102*$F$68+G103*$F$69+G104*$F$70+G105*$F$71+G106*$F$72 | H108: =H99*$F$65+H100*$F$66+H101*$F$67+H102*$F$68+H103*$F$69+H104*$F$70+H105*$F$71+H106*$F$72 | I108: =I99*$F$65+I100*$F$66+I101*$F$67+I102*$F$68+I103*$F$69+I104*$F$70+I105*$F$71+I106*$F$72 | J108: =J99*$F$65+J100*$F$66+J101*$F$67+J102*$F$68+J103*$F$69+J104*$F$70+J105*$F$71+J106*$F$72 | ... L108: =L99*$F$65+L100*$F$66+L101*$F$67+L102*$F$68+L103*$F$69+L104*$F$70+L105*$F$71+L106*$F$72
A109: Part équestre du CA | C109: =IF(C107=0,0,C108/C107) | D109: =IF(D107=0,0,D108/D107) | E109: =IF(E107=0,0,E108/E107) | F109: =IF(F107=0,0,F108/F107) | G109: =IF(G107=0,0,G108/G107) | H109: =IF(H107=0,0,H108/H107) | I109: =IF(I107=0,0,I108/I107) | J109: =IF(J107=0,0,J108/J107) | ... L109: =IF(L107=0,0,L108/L107)
A110: Coûts variables | B110: =SUM(C110:L110) | C110: =-(C99*$D$65+C100*$D$66+C101*$D$67+C102*$D$68+C103*$D$69+C104*$D$70+C105*$D$71+C106*$D$72) | D110: =-(D99*$D$65+D100*$D$66+D101*$D$67+D102*$D$68+D103*$D$69+D104*$D$70+D105*$D$71+D106*$D$72) | E110: =-(E99*$D$65+E100*$D$66+E101*$D$67+E102*$D$68+E103*$D$69+E104*$D$70+E105*$D$71+E106*$D$72) | F110: =-(F99*$D$65+F100*$D$66+F101*$D$67+F102*$D$68+F103*$D$69+F104*$D$70+F105*$D$71+F106*$D$72) | G110: =-(G99*$D$65+G100*$D$66+G101*$D$67+G102*$D$68+G103*$D$69+G104*$D$70+G105*$D$71+G106*$D$72) | H110: =-(H99*$D$65+H100*$D$66+H101*$D$67+H102*$D$68+H103*$D$69+H104*$D$70+H105*$D$71+H106*$D$72) | I110: =-(I99*$D$65+I100*$D$66+I101*$D$67+I102*$D$68+I103*$D$69+I104*$D$70+I105*$D$71+I106*$D$72) | J110: =-(J99*$D$65+J100*$D$66+J101*$D$67+J102*$D$68+J103*$D$69+J104*$D$70+J105*$D$71+J106*$D$72) | ... L110: =-(L99*$D$65+L100*$D$66+L101*$D$67+L102*$D$68+L103*$D$69+L104*$D$70+L105*$D$71+L106*$D$72)
A111: Marge sur coûts variables | B111: =SUM(C111:L111) | C111: =C107+C110 | D111: =D107+D110 | E111: =E107+E110 | F111: =F107+F110 | G111: =G107+G110 | H111: =H107+H110 | I111: =I107+I110 | J111: =J107+J110 | ... L111: =L107+L110
...

Sheet B_credit_vendeur
A1: B — Crédit-vendeur : apport 250 k€, crédit-vendeur 1,0 M€ sur 5 ans aux conditions de marché (montage 3) — cas central
A2: Cellules jaunes/bleues = hypothèses éditables. Tout le reste est calculé. Colonne D (bloc hypothèses) = source ou statut (ESTIMATION = non vérifiée).
A4: 1. Calendrier, acquisition et travaux
A5: Année d'acquisition des murs (1 = immédiate) | B5: 1 | C5: année | D5: Achat immédiat (2027)
A6: Année d'ouverture commerciale (avant stress) | B6: 2 | C6: année | D6: Année 1 = travaux ; EST
A7: Prix d'acquisition | B7: 2500000 | C7: € | D7: PL : médiane de 19 annonces de châteaux ≥ 30 ha (quartiles 1,29-3,07 M€) [A1]
A8: Frais d'acquisition (droits + notaire) | B8: 0.075 | C8: % | D8: EST : DMTO ≈ 5,8-6,3 % + notaire ≈ 1,2 % ; vente SAFER : frais 8,4 % TTC mais exonération de droits possible [A1, PL]
A9: Part du prix affectable au bâti (amortissable) | B9: 0.55 | C9: % | D9: EST
A10: Travaux de restauration / mise aux normes | B10: 500000 | C10: € | D10: EST sans visite : top 5 des biens équipés 0,1-0,7 M€ [A1]
A11: Investissements équestres (boxes, carrière, manège…) | B11: 150000 | C11: € | D11: EST : remise à niveau d'écuries existantes (une écurie neuve de 30 box coûterait 0,78-0,83 M€ HT [A3 H20])
A12: Investissements événementiel / hébergement | B12: 250000 | C12: € | D12: EST : mise aux normes d'une salle existante + aménagement du gîte (neuf : 570 k€-1,24 M€ [A4 §13.2])
A13: Répartition travaux : année d'acquisition | B13: 0.6 | C13: % | D13: EST
A14: Répartition travaux : année +1 | B14: 0.3 | C14: % | D14: EST
A15: Répartition travaux : année +2 | B15: 0.1 | C15: % | D15: EST
A16: Gros entretien patrimonial annuel (% prix+travaux) | B16: 0.018 | C16: % | D16: ≈ 41 k€/an sur (bâti + travaux) : Demeure Historique ≥ 40 k€/an hors restauration (PL [A8]) ; Barnes 20-80 k€/an [A4 §11] ; démarre en année d'acquisition + 3
... A20: Loyer de la partie privée payé par le fondateur (hors CA d'exploitation) | B20: 0 | C20: € | D20: Correction audit M1 : aucun loyer privé compté — le logis doit être détenu à part (SCI à l'IR, hors taxe 235 ter C [A6]) et payé par le fondateur personnellement
A22: 2. Financement
A23: Apport du fondateur (année 1) | B23: 250000 | C23: € | D23: S2 (les prêts d'honneur sont comptés en dette — correction audit)
A24: Fonds propres apportés à l'acquisition (investisseurs ou holding) | B24: 0 | C24: € | D24: Aucun investisseur
A25: Ces fonds propres viennent-ils de la holding du fondateur ? (1/0) | B25: 0
A26: Subventions (non acquises : 0 par défaut) | B26: 0 | C26: € | D26: Aucune subvention considérée comme acquise
A27: Dette bancaire (année d'acquisition) | B27: 1680000 | C27: € | D27: NON ACQUIS — banque 15 ans + prêt OpCo garanti + prêts d'honneur 80 k€ regroupés [A2]
A28: Taux de la dette bancaire | B28: 0.04 | C28: % | D28: PL : nouveaux crédits PME 3,64 % (FBF, 06/2026) ; EX : 3,66 % (BdF, 08/2026) ; retenu 4,0 % [A2]
A29: Durée dette bancaire | B29: 15 | C29: ans | D29: A2
A30: Différé d'amortissement (dans la durée) | B30: 1 | C30: ans | D30: EST
A31: Crédit-vendeur | B31: 1000000 | C31: € | D31: NON ACQUIS — 40 % du prix : usage 30-50 %, 1-5 ans, taux ≥ banque (PL [A8]) ; clause résolutoire
A32: Taux crédit-vendeur | B32: 0.045 | C32: % | D32: PL [A8] : taux ≥ banque
A33: Durée crédit-vendeur (amortissable) | B33: 5 | C33: ans | D33: PL [A8]
A34: Obligations / quasi-fonds propres (in fine) | B34: 500000 | C34: € | D34: NON ACQUIS — obligations PSFP in fine 5 ans [A2]
A35: Coupon annuel des obligations | B35: 0.08 | C35: % | D35: A2 : 7-9 %
A36: Année de remboursement des obligations | B36: 6 | C36: année | D36: Remboursement in fine en année 6
A37: Part de capital supplémentaire accordée au fondateur pour son travail (sweat equity) | B37: 0 | C37: % | D37: Fondateur seul
A38: Droits de vote du fondateur | B38: 1 | C38: %
A39: Réserve de liquidité cible | B39: 150000 | C39: € | D39: EST
A40: TRI minimal exigé par des investisseurs extérieurs | B40: 0.06 | C40: % | D40: EST : rendement minimal d'un investisseur en fonds propres illiquide (Anaxago affiche 8,7 % net, PL [A2])
A41: Le dirigeant est-il rémunéré par le domaine ? (1/0) | B41: 1 | D41: Rémunération du dirigeant incluse
A42: Part du capital du fondateur (calculée : apports au prorata + prime d'industrie, plafonnée à 100 %) | B42: =MIN(1,($B$23+$B$24*$B$25)/MAX(1,$B$23+$B$24)+$B$37)
A44: 3. Paramètres de stress (neutres = 100 % / 0)
A45: Multiplicateur de chiffre d'affaires | B45: 1 | C45: % | D45: neutre
A46: Multiplicateur du budget travaux | B46: 1 | C46: % | D46: neutre
A47: Retard d'ouverture | B47: 0 | C47: ans | D47: neutre
A48: Hausse du taux bancaire (points) | B48: 0 | C48: % | D48: neutre
A49: Part des fonds investisseurs non versée | B49: 0 | C49: % | D49: neutre
A50: Part des événements annulés | B50: 0 | C50: % | D50: neutre
A52: 4. Exploitation — hypothèses générales
A53: Montée en charge : 1re année d'exploitation | B53: 0.5 | C53: % | D53: A4 : mariages 40/70/100 % ; gîte 50/80/100 %
A54: Montée en charge : 2e année | B54: 0.8 | C54: % | D54: EST
A55: Montée en charge : 3e année | B55: 1 | C55: % | D55: EST
A56: Indexation annuelle des prix | B56: 0.02 | C56: % | D56: EST
A57: Inflation annuelle des charges | B57: 0.02 | C57: % | D57: EST : indexation identique aux prix (correction audit, biais pessimiste retiré)
A58: BFR en % du CA (négatif = acomptes clients) | B58: -0.03 | C58: % | D58: Acomptes (mariages, pensions payées d'avance) — EST
A59: Taux normal d'IS | B59: 0.25 | C59: % | D59: PL : IS 25 % au-delà de 42 500 € [A6]
A60: Taux réduit d'IS (PME, jusqu'au seuil) | B60: 0.15 | C60: % | D60: PL : 15 % jusqu'à 42 500 € (PME) [A6]
A61: Seuil du taux réduit d'IS | B61: 42500 | C61: € | D61: PL [A6]
A63: 5. Lignes de revenus (à maturité, euros de l'année d'ouverture)
A64: Libellé | B64: Volume | C64: Prix unitaire | D64: Coût var. % | E64: Événement ? | F64: Équestre ? | G64: Unité / source
A65: Pension box premium (places occupées) | B65: 22 | C65: 5118 | D65: 0.23 | E65: 0 | F65: 1 | G65: PL : 450 € TTC/mois = 3e quartile hors IdF (médiane 375 €, 10 % des offres ≥ 520 €) [A3, recalcul A8] → 426,5 € HT à TVA 5,5 % ; 24 box × 92 % ; coûts directs 1 200 €/an EST
A66: Pension au pré (places occupées) | B66: 23 | C66: 2502 | D66: 0.245 | E66: 0 | F66: 1 | G66: PL : 220 € TTC/mois (médianes 200-240 €) → 208,5 € HT [A3 H3] ; 25 places × 92 % ; coûts 613 €/an [A3 §4]
A67: Pension retraite / convalescence (places occupées) | B67: 9 | C67: 2100 | D67: 0.24 | E67: 0 | F67: 1 | G67: PL : 210 € TTC/mois, TVA 20 % → 175 € HT [A3 H4] ; 10 places × 90 %
A68: Mariages (location du lieu + hébergement 15 couchages) | B68: 12 | C68: 4197 | D68: 0.43 | E68: 1 | F68: 0 | G68: PL : médiane 3 400 € TTC location (17 châteaux) + 1 500 € TTC hébergement → 4 197 € HT [A4 §13.1] ; 12/an EST ; coût variable 1 450 € + 8 %
A69: Gîte 15 couchages hors mariages (nuits) | B69: 92 | C69: 450 | D69: 0.45 | E69: 0 | F69: 0 | G69: PL : fourchettes de prix [A4 §4.2] ; 92 nuits EST (occupation annuelle ≈ 33 % observée en Normandie hors saison) [A4 §4.3]
A70: Séminaires à la journée (jours) | B70: 12 | C70: 800 | D70: 0.19 | E70: 1 | F70: 0 | G70: PL : salle 1 000 €/jour (Feugerets) ; 800 € HT retenu [A4 §3]
A71: Tournages / shootings (jours) | B71: 3 | C71: 2000 | D71: 0.15 | E71: 1 | F71: 0 | G71: PL : 1 500-4 000 €/jour [A4 §5] ; fréquence EST
A72: Fermage / vente d'herbe (ha) | B72: 10 | C72: 150 | D72: 0 | E72: 0 | F72: 0 | G72: PL : arrêtés Orne/Calvados 2026-27 : 50-268 €/ha [A4 §8.2]
A74: 6. Charges fixes annuelles (euros de l'année d'ouverture)
A75: Libellé | B75: Montant/an | C75: Dès l'acq. (1) / dès l'ouverture (0) | G75: Source / statut
A76: Taxe foncière | B76: 6000 | C76: 1 | G76: EX : 2,6-4,0 k€ sur 3 annonces ; EST 4-8 k€ [A4 §11]
A77: Assurance multirisque château | B77: 12000 | C77: 1 | G77: Correction audit : courtier spécialisé 15-30 k€ (fiabilité moyenne), annonces ≥ 2,5 k€ [A4 §11, A8] ; EST 12 k€
A78: Énergie (chauffage partiel, électricité, eau) | B78: 20000 | C78: 1 | G78: PL : Meung, Louvignies ; EX annonce Montluçon 18-25 k€ [A1, A4 §11] ; EST
A79: Jardinier / agent d'entretien (1 ETP au Smic chargé) | B79: 27000 | C79: 1 | G79: PL : Smic 2026 22 404 € brut/an [A4 §11] ; EST charges
A80: Divers (abonnements, petit matériel, véhicule, honoraires) | B80: 8000 | C80: 1 | G80: EST
A81: Soigneurs (3 ETP au Smic chargés) | B81: 90000 | C81: 0 | G81: PL : Smic 1 867 €/mois, grille IDCC 7026 inférieure ; 1 ETP / 17-20 équidés [A3 H13-H14] ; ~54 équidés → 3 ETP (correction audit M5)
A82: Autres charges de structure équestres (entretien installations, matériel, assurance RC, énergie écuries) | B82: 30000 | C82: 0 | G82: Calibré pour un EBE équestre ≈ 37 % (réf. pension hébergement 36-38 %, PL [A3 H10])
A83: Coûts fixes mariages (coordination, nettoyage, publicité) | B83: 11000 | C83: 0 | G83: EST [A4 §13.1]
A84: Coûts fixes du gîte | B84: 4400 | C84: 0 | G84: EST [A4 §13.1]
A85: Commercial, site, salons | B85: 12000 | C85: 0 | G85: EST
A86: Comptabilité, juridique, banque, logiciels | B86: 12000 | C86: 0 | G86: EST
A87: Rémunération du dirigeant (chargée) | B87: 35000 | C87: 0 | G87: EST : minimum ; le dirigeant paie en plus 18 k€ de loyer privé
A89: 7. Calcul sur 10 ans
A90: Année | B90: Total / réf. | C90: 1 | D90: 2 | E90: 3 | F90: 4 | G90: 5 | H90: 6 | I90: 7 | J90: 8 | K90: 9 | L90: 10
A91: Année d'ouverture effective | C91: =$B$6+$B$47 | D91: =$B$6+$B$47 | E91: =$B$6+$B$47 | F91: =$B$6+$B$47 | G91: =$B$6+$B$47 | H91: =$B$6+$B$47 | I91: =$B$6+$B$47 | J91: =$B$6+$B$47 | ... L91: =$B$6+$B$47
A92: Rang de l'année d'exploitation | C92: =MAX(0,C$90-C91+1) | D92: =MAX(0,D$90-D91+1) | E92: =MAX(0,E$90-E91+1) | F92: =MAX(0,F$90-F91+1) | G92: =MAX(0,G$90-G91+1) | H92: =MAX(0,H$90-H91+1) | I92: =MAX(0,I$90-I91+1) | J92: =MAX(0,J$90-J91+1) | ... L92: =MAX(0,L$90-L91+1)
A93: Coefficient de montée en charge | C93: =IF(C92=0,0,IF(C92=1,$B$53,IF(C92=2,$B$54,IF(C92=3,$B$55,1)))) | D93: =IF(D92=0,0,IF(D92=1,$B$53,IF(D92=2,$B$54,IF(D92=3,$B$55,1)))) | E93: =IF(E92=0,0,IF(E92=1,$B$53,IF(E92=2,$B$54,IF(E92=3,$B$55,1)))) | F93: =IF(F92=0,0,IF(F92=1,$B$53,IF(F92=2,$B$54,IF(F92=3,$B$55,1)))) | G93: =IF(G92=0,0,IF(G92=1,$B$53,IF(G92=2,$B$54,IF(G92=3,$B$55,1)))) | H93: =IF(H92=0,0,IF(H92=1,$B$53,IF(H92=2,$B$54,IF(H92=3,$B$55,1)))) | I93: =IF(I92=0,0,IF(I92=1,$B$53,IF(I92=2,$B$54,IF(I92=3,$B$55,1)))) | J93: =IF(J92=0,0,IF(J92=1,$B$53,IF(J92=2,$B$54,IF(J92=3,$B$55,1)))) | ... L93: =IF(L92=0,0,IF(L92=1,$B$53,IF(L92=2,$B$54,IF(L92=3,$B$55,1))))
A94: Indice prix | C94: =(1+$B$56)^(C$90-1) | D94: =(1+$B$56)^(D$90-1) | E94: =(1+$B$56)^(E$90-1) | F94: =(1+$B$56)^(F$90-1) | G94: =(1+$B$56)^(G$90-1) | H94: =(1+$B$56)^(H$90-1) | I94: =(1+$B$56)^(I$90-1) | J94: =(1+$B$56)^(J$90-1) | ... L94: =(1+$B$56)^(L$90-1)
A95: Indice charges | C95: =(1+$B$57)^(C$90-1) | D95: =(1+$B$57)^(D$90-1) | E95: =(1+$B$57)^(E$90-1) | F95: =(1+$B$57)^(F$90-1) | G95: =(1+$B$57)^(G$90-1) | H95: =(1+$B$57)^(H$90-1) | I95: =(1+$B$57)^(I$90-1) | J95: =(1+$B$57)^(J$90-1) | ... L95: =(1+$B$57)^(L$90-1)
A96: Murs détenus (1/0) | C96: =IF(C$90>=$B$5,1,0) | D96: =IF(D$90>=$B$5,1,0) | E96: =IF(E$90>=$B$5,1,0) | F96: =IF(F$90>=$B$5,1,0) | G96: =IF(G$90>=$B$5,1,0) | H96: =IF(H$90>=$B$5,1,0) | I96: =IF(I$90>=$B$5,1,0) | J96: =IF(J$90>=$B$5,1,0) | ... L96: =IF(L$90>=$B$5,1,0)
A98: Compte de résultat
A99: Pension box premium (places occupées) | B99: =SUM(C99:L99) | C99: =$B$65*$C$65*C93*C94*$B$45*(1-$E$65*$B$50) | D99: =$B$65*$C$65*D93*D94*$B$45*(1-$E$65*$B$50) | E99: =$B$65*$C$65*E93*E94*$B$45*(1-$E$65*$B$50) | F99: =$B$65*$C$65*F93*F94*$B$45*(1-$E$65*$B$50) | G99: =$B$65*$C$65*G93*G94*$B$45*(1-$E$65*$B$50) | H99: =$B$65*$C$65*H93*H94*$B$45*(1-$E$65*$B$50) | I99: =$B$65*$C$65*I93*I94*$B$45*(1-$E$65*$B$50) | J99: =$B$65*$C$65*J93*J94*$B$45*(1-$E$65*$B$50) | ... L99: =$B$65*$C$65*L93*L94*$B$45*(1-$E$65*$B$50)
A100: Pension au pré (places occupées) | B100: =SUM(C100:L100) | C100: =$B$66*$C$66*C93*C94*$B$45*(1-$E$66*$B$50) | D100: =$B$66*$C$66*D93*D94*$B$45*(1-$E$66*$B$50) | E100: =$B$66*$C$66*E93*E94*$B$45*(1-$E$66*$B$50) | F100: =$B$66*$C$66*F93*F94*$B$45*(1-$E$66*$B$50) | G100: =$B$66*$C$66*G93*G94*$B$45*(1-$E$66*$B$50) | H100: =$B$66*$C$66*H93*H94*$B$45*(1-$E$66*$B$50) | I100: =$B$66*$C$66*I93*I94*$B$45*(1-$E$66*$B$50) | J100: =$B$66*$C$66*J93*J94*$B$45*(1-$E$66*$B$50) | ... L100: =$B$66*$C$66*L93*L94*$B$45*(1-$E$66*$B$50)
A101: Pension retraite / convalescence (places occupées) | B101: =SUM(C101:L101) | C101: =$B$67*$C$67*C93*C94*$B$45*(1-$E$67*$B$50) | D101: =$B$67*$C$67*D93*D94*$B$45*(1-$E$67*$B$50) | E101: =$B$67*$C$67*E93*E94*$B$45*(1-$E$67*$B$50) | F101: =$B$67*$C$67*F93*F94*$B$45*(1-$E$67*$B$50) | G101: =$B$67*$C$67*G93*G94*$B$45*(1-$E$67*$B$50) | H101: =$B$67*$C$67*H93*H94*$B$45*(1-$E$67*$B$50) | I101: =$B$67*$C$67*I93*I94*$B$45*(1-$E$67*$B$50) | J101: =$B$67*$C$67*J93*J94*$B$45*(1-$E$67*$B$50) | ... L101: =$B$67*$C$67*L93*L94*$B$45*(1-$E$67*$B$50)
A102: Mariages (location du lieu + hébergement 15 couchages) | B102: =SUM(C102:L102) | C102: =$B$68*$C$68*C93*C94*$B$45*(1-$E$68*$B$50) | D102: =$B$68*$C$68*D93*D94*$B$45*(1-$E$68*$B$50) | E102: =$B$68*$C$68*E93*E94*$B$45*(1-$E$68*$B$50) | F102: =$B$68*$C$68*F93*F94*$B$45*(1-$E$68*$B$50) | G102: =$B$68*$C$68*G93*G94*$B$45*(1-$E$68*$B$50) | H102: =$B$68*$C$68*H93*H94*$B$45*(1-$E$68*$B$50) | I102: =$B$68*$C$68*I93*I94*$B$45*(1-$E$68*$B$50) | J102: =$B$68*$C$68*J93*J94*$B$45*(1-$E$68*$B$50) | ... L102: =$B$68*$C$68*L93*L94*$B$45*(1-$E$68*$B$50)
A103: Gîte 15 couchages hors mariages (nuits) | B103: =SUM(C103:L103) | C103: =$B$69*$C$69*C93*C94*$B$45*(1-$E$69*$B$50) | D103: =$B$69*$C$69*D93*D94*$B$45*(1-$E$69*$B$50) | E103: =$B$69*$C$69*E93*E94*$B$45*(1-$E$69*$B$50) | F103: =$B$69*$C$69*F93*F94*$B$45*(1-$E$69*$B$50) | G103: =$B$69*$C$69*G93*G94*$B$45*(1-$E$69*$B$50) | H103: =$B$69*$C$69*H93*H94*$B$45*(1-$E$69*$B$50) | I103: =$B$69*$C$69*I93*I94*$B$45*(1-$E$69*$B$50) | J103: =$B$69*$C$69*J93*J94*$B$45*(1-$E$69*$B$50) | ... L103: =$B$69*$C$69*L93*L94*$B$45*(1-$E$69*$B$50)
A104: Séminaires à la journée (jours) | B104: =SUM(C104:L104) | C104: =$B$70*$C$70*C93*C94*$B$45*(1-$E$70*$B$50) | D104: =$B$70*$C$70*D93*D94*$B$45*(1-$E$70*$B$50) | E104: =$B$70*$C$70*E93*E94*$B$45*(1-$E$70*$B$50) | F104: =$B$70*$C$70*F93*F94*$B$45*(1-$E$70*$B$50) | G104: =$B$70*$C$70*G93*G94*$B$45*(1-$E$70*$B$50) | H104: =$B$70*$C$70*H93*H94*$B$45*(1-$E$70*$B$50) | I104: =$B$70*$C$70*I93*I94*$B$45*(1-$E$70*$B$50) | J104: =$B$70*$C$70*J93*J94*$B$45*(1-$E$70*$B$50) | ... L104: =$B$70*$C$70*L93*L94*$B$45*(1-$E$70*$B$50)
A105: Tournages / shootings (jours) | B105: =SUM(C105:L105) | C105: =$B$71*$C$71*C93*C94*$B$45*(1-$E$71*$B$50) | D105: =$B$71*$C$71*D93*D94*$B$45*(1-$E$71*$B$50) | E105: =$B$71*$C$71*E93*E94*$B$45*(1-$E$71*$B$50) | F105: =$B$71*$C$71*F93*F94*$B$45*(1-$E$71*$B$50) | G105: =$B$71*$C$71*G93*G94*$B$45*(1-$E$71*$B$50) | H105: =$B$71*$C$71*H93*H94*$B$45*(1-$E$71*$B$50) | I105: =$B$71*$C$71*I93*I94*$B$45*(1-$E$71*$B$50) | J105: =$B$71*$C$71*J93*J94*$B$45*(1-$E$71*$B$50) | ... L105: =$B$71*$C$71*L93*L94*$B$45*(1-$E$71*$B$50)
A106: Fermage / vente d'herbe (ha) | B106: =SUM(C106:L106) | C106: =$B$72*$C$72*C93*C94*$B$45*(1-$E$72*$B$50) | D106: =$B$72*$C$72*D93*D94*$B$45*(1-$E$72*$B$50) | E106: =$B$72*$C$72*E93*E94*$B$45*(1-$E$72*$B$50) | F106: =$B$72*$C$72*F93*F94*$B$45*(1-$E$72*$B$50) | G106: =$B$72*$C$72*G93*G94*$B$45*(1-$E$72*$B$50) | H106: =$B$72*$C$72*H93*H94*$B$45*(1-$E$72*$B$50) | I106: =$B$72*$C$72*I93*I94*$B$45*(1-$E$72*$B$50) | J106: =$B$72*$C$72*J93*J94*$B$45*(1-$E$72*$B$50) | ... L106: =$B$72*$C$72*L93*L94*$B$45*(1-$E$72*$B$50)
A107: Chiffre d'affaires total | B107: =SUM(C107:L107) | C107: =C99+C100+C101+C102+C103+C104+C105+C106 | D107: =D99+D100+D101+D102+D103+D104+D105+D106 | E107: =E99+E100+E101+E102+E103+E104+E105+E106 | F107: =F99+F100+F101+F102+F103+F104+F105+F106 | G107: =G99+G100+G101+G102+G103+G104+G105+G106 | H107: =H99+H100+H101+H102+H103+H104+H105+H106 | I107: =I99+I100+I101+I102+I103+I104+I105+I106 | J107: =J99+J100+J101+J102+J103+J104+J105+J106 | ... L107: =L99+L100+L101+L102+L103+L104+L105+L106
A108: dont équestre | B108: =SUM(C108:L108) | C108: =C99*$F$65+C100*$F$66+C101*$F$67+C102*$F$68+C103*$F$69+C104*$F$70+C105*$F$71+C106*$F$72 | D108: =D99*$F$65+D100*$F$66+D101*$F$67+D102*$F$68+D103*$F$69+D104*$F$70+D105*$F$71+D106*$F$72 | E108: =E99*$F$65+E100*$F$66+E101*$F$67+E102*$F$68+E103*$F$69+E104*$F$70+E105*$F$71+E106*$F$72 | F108: =F99*$F$65+F100*$F$66+F101*$F$67+F102*$F$68+F103*$F$69+F104*$F$70+F105*$F$71+F106*$F$72 | G108: =G99*$F$65+G100*$F$66+G101*$F$67+G102*$F$68+G103*$F$69+G104*$F$70+G105*$F$71+G106*$F$72 | H108: =H99*$F$65+H100*$F$66+H101*$F$67+H102*$F$68+H103*$F$69+H104*$F$70+H105*$F$71+H106*$F$72 | I108: =I99*$F$65+I100*$F$66+I101*$F$67+I102*$F$68+I103*$F$69+I104*$F$70+I105*$F$71+I106*$F$72 | J108: =J99*$F$65+J100*$F$66+J101*$F$67+J102*$F$68+J103*$F$69+J104*$F$70+J105*$F$71+J106*$F$72 | ... L108: =L99*$F$65+L100*$F$66+L101*$F$67+L102*$F$68+L103*$F$69+L104*$F$70+L105*$F$71+L106*$F$72
A109: Part équestre du CA | C109: =IF(C107=0,0,C108/C107) | D109: =IF(D107=0,0,D108/D107) | E109: =IF(E107=0,0,E108/E107) | F109: =IF(F107=0,0,F108/F107) | G109: =IF(G107=0,0,G108/G107) | H109: =IF(H107=0,0,H108/H107) | I109: =IF(I107=0,0,I108/I107) | J109: =IF(J107=0,0,J108/J107) | ... L109: =IF(L107=0,0,L108/L107)
A110: Coûts variables | B110: =SUM(C110:L110) | C110: =-(C99*$D$65+C100*$D$66+C101*$D$67+C102*$D$68+C103*$D$69+C104*$D$70+C105*$D$71+C106*$D$72) | D110: =-(D99*$D$65+D100*$D$66+D101*$D$67+D102*$D$68+D103*$D$69+D104*$D$70+D105*$D$71+D106*$D$72) | E110: =-(E99*$D$65+E100*$D$66+E101*$D$67+E102*$D$68+E103*$D$69+E104*$D$70+E105*$D$71+E106*$D$72) | F110: =-(F99*$D$65+F100*$D$66+F101*$D$67+F102*$D$68+F103*$D$69+F104*$D$70+F105*$D$71+F106*$D$72) | G110: =-(G99*$D$65+G100*$D$66+G101*$D$67+G102*$D$68+G103*$D$69+G104*$D$70+G105*$D$71+G106*$D$72) | H110: =-(H99*$D$65+H100*$D$66+H101*$D$67+H102*$D$68+H103*$D$69+H104*$D$70+H105*$D$71+H106*$D$72) | I110: =-(I99*$D$65+I100*$D$66+I101*$D$67+I102*$D$68+I103*$D$69+I104*$D$70+I105*$D$71+I106*$D$72) | J110: =-(J99*$D$65+J100*$D$66+J101*$D$67+J102*$D$68+J103*$D$69+J104*$D$70+J105*$D$71+J106*$D$72) | ... L110: =-(L99*$D$65+L100*$D$66+L101*$D$67+L102*$D$68+L103*$D$69+L104*$D$70+L105*$D$71+L106*$D$72)
A111: Marge sur coûts variables | B111: =SUM(C111:L111) | C111: =C107+C110 | D111: =D107+D110 | E111: =E107+E110 | F111: =F107+F110 | G111: =G107+G110 | H111: =H107+H110 | I111: =I107+I110 | J111: =J107+J110 | ... L111: =L107+L110
...

Sheet B_sans_dette
A1: Diagnostic — exploitation B sans aucune dette (tout en fonds propres)
A2: Cellules jaunes/bleues = hypothèses éditables. Tout le reste est calculé. Colonne D (bloc hypothèses) = source ou statut (ESTIMATION = non vérifiée).
A4: 1. Calendrier, acquisition et travaux
A5: Année d'acquisition des murs (1 = immédiate) | B5: 1 | C5: année | D5: Achat immédiat (2027)
A6: Année d'ouverture commerciale (avant stress) | B6: 2 | C6: année | D6: Année 1 = travaux ; EST
A7: Prix d'acquisition | B7: 2500000 | C7: € | D7: PL : médiane de 19 annonces de châteaux ≥ 30 ha (quartiles 1,29-3,07 M€) [A1]
A8: Frais d'acquisition (droits + notaire) | B8: 0.075 | C8: % | D8: EST : DMTO ≈ 5,8-6,3 % + notaire ≈ 1,2 % ; vente SAFER : frais 8,4 % TTC mais exonération de droits possible [A1, PL]
A9: Part du prix affectable au bâti (amortissable) | B9: 0.55 | C9: % | D9: EST
A10: Travaux de restauration / mise aux normes | B10: 500000 | C10: € | D10: EST sans visite : top 5 des biens équipés 0,1-0,7 M€ [A1]
A11: Investissements équestres (boxes, carrière, manège…) | B11: 150000 | C11: € | D11: EST : remise à niveau d'écuries existantes (une écurie neuve de 30 box coûterait 0,78-0,83 M€ HT [A3 H20])
A12: Investissements événementiel / hébergement | B12: 250000 | C12: € | D12: EST : mise aux normes d'une salle existante + aménagement du gîte (neuf : 570 k€-1,24 M€ [A4 §13.2])
A13: Répartition travaux : année d'acquisition | B13: 0.6 | C13: % | D13: EST
A14: Répartition travaux : année +1 | B14: 0.3 | C14: % | D14: EST
A15: Répartition travaux : année +2 | B15: 0.1 | C15: % | D15: EST
A16: Gros entretien patrimonial annuel (% prix+travaux) | B16: 0.018 | C16: % | D16: ≈ 41 k€/an sur (bâti + travaux) : Demeure Historique ≥ 40 k€/an hors restauration (PL [A8]) ; Barnes 20-80 k€/an [A4 §11] ; démarre en année d'acquisition + 3
... A20: Loyer de la partie privée payé par le fondateur (hors CA d'exploitation) | B20: 0 | C20: € | D20: Correction audit M1 : aucun loyer privé compté — le logis doit être détenu à part (SCI à l'IR, hors taxe 235 ter C [A6]) et payé par le fondateur personnellement
A22: 2. Financement
A23: Apport du fondateur (année 1) | B23: 3900000 | C23: € | D23: Test : tout financé en fonds propres (emplois + réserve)
A24: Fonds propres apportés à l'acquisition (investisseurs ou holding) | B24: 0 | C24: € | D24: Aucun investisseur
A25: Ces fonds propres viennent-ils de la holding du fondateur ? (1/0) | B25: 0
A26: Subventions (non acquises : 0 par défaut) | B26: 0 | C26: € | D26: Aucune subvention considérée comme acquise
A27: Dette bancaire (année d'acquisition) | B27: 0 | C27: € | D27: Test
A28: Taux de la dette bancaire | B28: 0.04 | C28: % | D28: PL : nouveaux crédits PME 3,64 % (FBF, 06/2026) ; EX : 3,66 % (BdF, 08/2026) ; retenu 4,0 % [A2]
A29: Durée dette bancaire | B29: 20 | C29: ans | D29: A2 (Bpifrance : 15 ans avec hypothèque, PL)
A30: Différé d'amortissement (dans la durée) | B30: 1 | C30: ans | D30: EST
A31: Crédit-vendeur | B31: 0 | C31: €
A32: Taux crédit-vendeur | B32: 0.03 | C32: % | D32: EST
A33: Durée crédit-vendeur (amortissable) | B33: 12 | C33: ans | D33: EST
A34: Obligations / quasi-fonds propres (in fine) | B34: 0 | C34: €
A35: Coupon annuel des obligations | B35: 0.07 | C35: % | D35: PL : obligations Château Fontenay 7 % [A2]
A36: Année de remboursement des obligations | B36: 6 | C36: année | D36: EST
A37: Part de capital supplémentaire accordée au fondateur pour son travail (sweat equity) | B37: 0 | C37: % | D37: Fondateur seul
A38: Droits de vote du fondateur | B38: 1 | C38: %
A39: Réserve de liquidité cible | B39: 150000 | C39: € | D39: EST
A40: TRI minimal exigé par des investisseurs extérieurs | B40: 0.06 | C40: % | D40: EST : rendement minimal d'un investisseur en fonds propres illiquide (Anaxago affiche 8,7 % net, PL [A2])
A41: Le dirigeant est-il rémunéré par le domaine ? (1/0) | B41: 1 | D41: Rémunération du dirigeant incluse
A42: Part du capital du fondateur (calculée : apports au prorata + prime d'industrie, plafonnée à 100 %) | B42: =MIN(1,($B$23+$B$24*$B$25)/MAX(1,$B$23+$B$24)+$B$37)
A44: 3. Paramètres de stress (neutres = 100 % / 0)
A45: Multiplicateur de chiffre d'affaires | B45: 1 | C45: % | D45: neutre
A46: Multiplicateur du budget travaux | B46: 1 | C46: % | D46: neutre
A47: Retard d'ouverture | B47: 0 | C47: ans | D47: neutre
A48: Hausse du taux bancaire (points) | B48: 0 | C48: % | D48: neutre
A49: Part des fonds investisseurs non versée | B49: 0 | C49: % | D49: neutre
A50: Part des événements annulés | B50: 0 | C50: % | D50: neutre
A52: 4. Exploitation — hypothèses générales
A53: Montée en charge : 1re année d'exploitation | B53: 0.5 | C53: % | D53: A4 : mariages 40/70/100 % ; gîte 50/80/100 %
A54: Montée en charge : 2e année | B54: 0.8 | C54: % | D54: EST
A55: Montée en charge : 3e année | B55: 1 | C55: % | D55: EST
A56: Indexation annuelle des prix | B56: 0.02 | C56: % | D56: EST
A57: Inflation annuelle des charges | B57: 0.02 | C57: % | D57: EST : indexation identique aux prix (correction audit, biais pessimiste retiré)
A58: BFR en % du CA (négatif = acomptes clients) | B58: -0.03 | C58: % | D58: Acomptes (mariages, pensions payées d'avance) — EST
A59: Taux normal d'IS | B59: 0.25 | C59: % | D59: PL : IS 25 % au-delà de 42 500 € [A6]
A60: Taux réduit d'IS (PME, jusqu'au seuil) | B60: 0.15 | C60: % | D60: PL : 15 % jusqu'à 42 500 € (PME) [A6]
A61: Seuil du taux réduit d'IS | B61: 42500 | C61: € | D61: PL [A6]
A63: 5. Lignes de revenus (à maturité, euros de l'année d'ouverture)
A64: Libellé | B64: Volume | C64: Prix unitaire | D64: Coût var. % | E64: Événement ? | F64: Équestre ? | G64: Unité / source
A65: Pension box premium (places occupées) | B65: 22 | C65: 5118 | D65: 0.23 | E65: 0 | F65: 1 | G65: PL : 450 € TTC/mois = 3e quartile hors IdF (médiane 375 €, 10 % des offres ≥ 520 €) [A3, recalcul A8] → 426,5 € HT à TVA 5,5 % ; 24 box × 92 % ; coûts directs 1 200 €/an EST
A66: Pension au pré (places occupées) | B66: 23 | C66: 2502 | D66: 0.245 | E66: 0 | F66: 1 | G66: PL : 220 € TTC/mois (médianes 200-240 €) → 208,5 € HT [A3 H3] ; 25 places × 92 % ; coûts 613 €/an [A3 §4]
A67: Pension retraite / convalescence (places occupées) | B67: 9 | C67: 2100 | D67: 0.24 | E67: 0 | F67: 1 | G67: PL : 210 € TTC/mois, TVA 20 % → 175 € HT [A3 H4] ; 10 places × 90 %
A68: Mariages (location du lieu + hébergement 15 couchages) | B68: 12 | C68: 4197 | D68: 0.43 | E68: 1 | F68: 0 | G68: PL : médiane 3 400 € TTC location (17 châteaux) + 1 500 € TTC hébergement → 4 197 € HT [A4 §13.1] ; 12/an EST ; coût variable 1 450 € + 8 %
A69: Gîte 15 couchages hors mariages (nuits) | B69: 92 | C69: 450 | D69: 0.45 | E69: 0 | F69: 0 | G69: PL : fourchettes de prix [A4 §4.2] ; 92 nuits EST (occupation annuelle ≈ 33 % observée en Normandie hors saison) [A4 §4.3]
A70: Séminaires à la journée (jours) | B70: 12 | C70: 800 | D70: 0.19 | E70: 1 | F70: 0 | G70: PL : salle 1 000 €/jour (Feugerets) ; 800 € HT retenu [A4 §3]
A71: Tournages / shootings (jours) | B71: 3 | C71: 2000 | D71: 0.15 | E71: 1 | F71: 0 | G71: PL : 1 500-4 000 €/jour [A4 §5] ; fréquence EST
A72: Fermage / vente d'herbe (ha) | B72: 10 | C72: 150 | D72: 0 | E72: 0 | F72: 0 | G72: PL : arrêtés Orne/Calvados 2026-27 : 50-268 €/ha [A4 §8.2]
A74: 6. Charges fixes annuelles (euros de l'année d'ouverture)
A75: Libellé | B75: Montant/an | C75: Dès l'acq. (1) / dès l'ouverture (0) | G75: Source / statut
A76: Taxe foncière | B76: 6000 | C76: 1 | G76: EX : 2,6-4,0 k€ sur 3 annonces ; EST 4-8 k€ [A4 §11]
A77: Assurance multirisque château | B77: 12000 | C77: 1 | G77: Correction audit : courtier spécialisé 15-30 k€ (fiabilité moyenne), annonces ≥ 2,5 k€ [A4 §11, A8] ; EST 12 k€
A78: Énergie (chauffage partiel, électricité, eau) | B78: 20000 | C78: 1 | G78: PL : Meung, Louvignies ; EX annonce Montluçon 18-25 k€ [A1, A4 §11] ; EST
A79: Jardinier / agent d'entretien (1 ETP au Smic chargé) | B79: 27000 | C79: 1 | G79: PL : Smic 2026 22 404 € brut/an [A4 §11] ; EST charges
A80: Divers (abonnements, petit matériel, véhicule, honoraires) | B80: 8000 | C80: 1 | G80: EST
A81: Soigneurs (3 ETP au Smic chargés) | B81: 90000 | C81: 0 | G81: PL : Smic 1 867 €/mois, grille IDCC 7026 inférieure ; 1 ETP / 17-20 équidés [A3 H13-H14] ; ~54 équidés → 3 ETP (correction audit M5)
A82: Autres charges de structure équestres (entretien installations, matériel, assurance RC, énergie écuries) | B82: 30000 | C82: 0 | G82: Calibré pour un EBE équestre ≈ 37 % (réf. pension hébergement 36-38 %, PL [A3 H10])
A83: Coûts fixes mariages (coordination, nettoyage, publicité) | B83: 11000 | C83: 0 | G83: EST [A4 §13.1]
A84: Coûts fixes du gîte | B84: 4400 | C84: 0 | G84: EST [A4 §13.1]
A85: Commercial, site, salons | B85: 12000 | C85: 0 | G85: EST
A86: Comptabilité, juridique, banque, logiciels | B86: 12000 | C86: 0 | G86: EST
A87: Rémunération du dirigeant (chargée) | B87: 35000 | C87: 0 | G87: EST : minimum ; le dirigeant paie en plus 18 k€ de loyer privé
A89: 7. Calcul sur 10 ans
A90: Année | B90: Total / réf. | C90: 1 | D90: 2 | E90: 3 | F90: 4 | G90: 5 | H90: 6 | I90: 7 | J90: 8 | K90: 9 | L90: 10
A91: Année d'ouverture effective | C91: =$B$6+$B$47 | D91: =$B$6+$B$47 | E91: =$B$6+$B$47 | F91: =$B$6+$B$47 | G91: =$B$6+$B$47 | H91: =$B$6+$B$47 | I91: =$B$6+$B$47 | J91: =$B$6+$B$47 | ... L91: =$B$6+$B$47
A92: Rang de l'année d'exploitation | C92: =MAX(0,C$90-C91+1) | D92: =MAX(0,D$90-D91+1) | E92: =MAX(0,E$90-E91+1) | F92: =MAX(0,F$90-F91+1) | G92: =MAX(0,G$90-G91+1) | H92: =MAX(0,H$90-H91+1) | I92: =MAX(0,I$90-I91+1) | J92: =MAX(0,J$90-J91+1) | ... L92: =MAX(0,L$90-L91+1)
A93: Coefficient de montée en charge | C93: =IF(C92=0,0,IF(C92=1,$B$53,IF(C92=2,$B$54,IF(C92=3,$B$55,1)))) | D93: =IF(D92=0,0,IF(D92=1,$B$53,IF(D92=2,$B$54,IF(D92=3,$B$55,1)))) | E93: =IF(E92=0,0,IF(E92=1,$B$53,IF(E92=2,$B$54,IF(E92=3,$B$55,1)))) | F93: =IF(F92=0,0,IF(F92=1,$B$53,IF(F92=2,$B$54,IF(F92=3,$B$55,1)))) | G93: =IF(G92=0,0,IF(G92=1,$B$53,IF(G92=2,$B$54,IF(G92=3,$B$55,1)))) | H93: =IF(H92=0,0,IF(H92=1,$B$53,IF(H92=2,$B$54,IF(H92=3,$B$55,1)))) | I93: =IF(I92=0,0,IF(I92=1,$B$53,IF(I92=2,$B$54,IF(I92=3,$B$55,1)))) | J93: =IF(J92=0,0,IF(J92=1,$B$53,IF(J92=2,$B$54,IF(J92=3,$B$55,1)))) | ... L93: =IF(L92=0,0,IF(L92=1,$B$53,IF(L92=2,$B$54,IF(L92=3,$B$55,1))))
A94: Indice prix | C94: =(1+$B$56)^(C$90-1) | D94: =(1+$B$56)^(D$90-1) | E94: =(1+$B$56)^(E$90-1) | F94: =(1+$B$56)^(F$90-1) | G94: =(1+$B$56)^(G$90-1) | H94: =(1+$B$56)^(H$90-1) | I94: =(1+$B$56)^(I$90-1) | J94: =(1+$B$56)^(J$90-1) | ... L94: =(1+$B$56)^(L$90-1)
A95: Indice charges | C95: =(1+$B$57)^(C$90-1) | D95: =(1+$B$57)^(D$90-1) | E95: =(1+$B$57)^(E$90-1) | F95: =(1+$B$57)^(F$90-1) | G95: =(1+$B$57)^(G$90-1) | H95: =(1+$B$57)^(H$90-1) | I95: =(1+$B$57)^(I$90-1) | J95: =(1+$B$57)^(J$90-1) | ... L95: =(1+$B$57)^(L$90-1)
A96: Murs détenus (1/0) | C96: =IF(C$90>=$B$5,1,0) | D96: =IF(D$90>=$B$5,1,0) | E96: =IF(E$90>=$B$5,1,0) | F96: =IF(F$90>=$B$5,1,0) | G96: =IF(G$90>=$B$5,1,0) | H96: =IF(H$90>=$B$5,1,0) | I96: =IF(I$90>=$B$5,1,0) | J96: =IF(J$90>=$B$5,1,0) | ... L96: =IF(L$90>=$B$5,1,0)
A98: Compte de résultat
A99: Pension box premium (places occupées) | B99: =SUM(C99:L99) | C99: =$B$65*$C$65*C93*C94*$B$45*(1-$E$65*$B$50) | D99: =$B$65*$C$65*D93*D94*$B$45*(1-$E$65*$B$50) | E99: =$B$65*$C$65*E93*E94*$B$45*(1-$E$65*$B$50) | F99: =$B$65*$C$65*F93*F94*$B$45*(1-$E$65*$B$50) | G99: =$B$65*$C$65*G93*G94*$B$45*(1-$E$65*$B$50) | H99: =$B$65*$C$65*H93*H94*$B$45*(1-$E$65*$B$50) | I99: =$B$65*$C$65*I93*I94*$B$45*(1-$E$65*$B$50) | J99: =$B$65*$C$65*J93*J94*$B$45*(1-$E$65*$B$50) | ... L99: =$B$65*$C$65*L93*L94*$B$45*(1-$E$65*$B$50)
A100: Pension au pré (places occupées) | B100: =SUM(C100:L100) | C100: =$B$66*$C$66*C93*C94*$B$45*(1-$E$66*$B$50) | D100: =$B$66*$C$66*D93*D94*$B$45*(1-$E$66*$B$50) | E100: =$B$66*$C$66*E93*E94*$B$45*(1-$E$66*$B$50) | F100: =$B$66*$C$66*F93*F94*$B$45*(1-$E$66*$B$50) | G100: =$B$66*$C$66*G93*G94*$B$45*(1-$E$66*$B$50) | H100: =$B$66*$C$66*H93*H94*$B$45*(1-$E$66*$B$50) | I100: =$B$66*$C$66*I93*I94*$B$45*(1-$E$66*$B$50) | J100: =$B$66*$C$66*J93*J94*$B$45*(1-$E$66*$B$50) | ... L100: =$B$66*$C$66*L93*L94*$B$45*(1-$E$66*$B$50)
A101: Pension retraite / convalescence (places occupées) | B101: =SUM(C101:L101) | C101: =$B$67*$C$67*C93*C94*$B$45*(1-$E$67*$B$50) | D101: =$B$67*$C$67*D93*D94*$B$45*(1-$E$67*$B$50) | E101: =$B$67*$C$67*E93*E94*$B$45*(1-$E$67*$B$50) | F101: =$B$67*$C$67*F93*F94*$B$45*(1-$E$67*$B$50) | G101: =$B$67*$C$67*G93*G94*$B$45*(1-$E$67*$B$50) | H101: =$B$67*$C$67*H93*H94*$B$45*(1-$E$67*$B$50) | I101: =$B$67*$C$67*I93*I94*$B$45*(1-$E$67*$B$50) | J101: =$B$67*$C$67*J93*J94*$B$45*(1-$E$67*$B$50) | ... L101: =$B$67*$C$67*L93*L94*$B$45*(1-$E$67*$B$50)
A102: Mariages (location du lieu + hébergement 15 couchages) | B102: =SUM(C102:L102) | C102: =$B$68*$C$68*C93*C94*$B$45*(1-$E$68*$B$50) | D102: =$B$68*$C$68*D93*D94*$B$45*(1-$E$68*$B$50) | E102: =$B$68*$C$68*E93*E94*$B$45*(1-$E$68*$B$50) | F102: =$B$68*$C$68*F93*F94*$B$45*(1-$E$68*$B$50) | G102: =$B$68*$C$68*G93*G94*$B$45*(1-$E$68*$B$50) | H102: =$B$68*$C$68*H93*H94*$B$45*(1-$E$68*$B$50) | I102: =$B$68*$C$68*I93*I94*$B$45*(1-$E$68*$B$50) | J102: =$B$68*$C$68*J93*J94*$B$45*(1-$E$68*$B$50) | ... L102: =$B$68*$C$68*L93*L94*$B$45*(1-$E$68*$B$50)
A103: Gîte 15 couchages hors mariages (nuits) | B103: =SUM(C103:L103) | C103: =$B$69*$C$69*C93*C94*$B$45*(1-$E$69*$B$50) | D103: =$B$69*$C$69*D93*D94*$B$45*(1-$E$69*$B$50) | E103: =$B$69*$C$69*E93*E94*$B$45*(1-$E$69*$B$50) | F103: =$B$69*$C$69*F93*F94*$B$45*(1-$E$69*$B$50) | G103: =$B$69*$C$69*G93*G94*$B$45*(1-$E$69*$B$50) | H103: =$B$69*$C$69*H93*H94*$B$45*(1-$E$69*$B$50) | I103: =$B$69*$C$69*I93*I94*$B$45*(1-$E$69*$B$50) | J103: =$B$69*$C$69*J93*J94*$B$45*(1-$E$69*$B$50) | ... L103: =$B$69*$C$69*L93*L94*$B$45*(1-$E$69*$B$50)
A104: Séminaires à la journée (jours) | B104: =SUM(C104:L104) | C104: =$B$70*$C$70*C93*C94*$B$45*(1-$E$70*$B$50) | D104: =$B$70*$C$70*D93*D94*$B$45*(1-$E$70*$B$50) | E104: =$B$70*$C$70*E93*E94*$B$45*(1-$E$70*$B$50) | F104: =$B$70*$C$70*F93*F94*$B$45*(1-$E$70*$B$50) | G104: =$B$70*$C$70*G93*G94*$B$45*(1-$E$70*$B$50) | H104: =$B$70*$C$70*H93*H94*$B$45*(1-$E$70*$B$50) | I104: =$B$70*$C$70*I93*I94*$B$45*(1-$E$70*$B$50) | J104: =$B$70*$C$70*J93*J94*$B$45*(1-$E$70*$B$50) | ... L104: =$B$70*$C$70*L93*L94*$B$45*(1-$E$70*$B$50)
A105: Tournages / shootings (jours) | B105: =SUM(C105:L105) | C105: =$B$71*$C$71*C93*C94*$B$45*(1-$E$71*$B$50) | D105: =$B$71*$C$71*D93*D94*$B$45*(1-$E$71*$B$50) | E105: =$B$71*$C$71*E93*E94*$B$45*(1-$E$71*$B$50) | F105: =$B$71*$C$71*F93*F94*$B$45*(1-$E$71*$B$50) | G105: =$B$71*$C$71*G93*G94*$B$45*(1-$E$71*$B$50) | H105: =$B$71*$C$71*H93*H94*$B$45*(1-$E$71*$B$50) | I105: =$B$71*$C$71*I93*I94*$B$45*(1-$E$71*$B$50) | J105: =$B$71*$C$71*J93*J94*$B$45*(1-$E$71*$B$50) | ... L105: =$B$71*$C$71*L93*L94*$B$45*(1-$E$71*$B$50)
A106: Fermage / vente d'herbe (ha) | B106: =SUM(C106:L106) | C106: =$B$72*$C$72*C93*C94*$B$45*(1-$E$72*$B$50) | D106: =$B$72*$C$72*D93*D94*$B$45*(1-$E$72*$B$50) | E106: =$B$72*$C$72*E93*E94*$B$45*(1-$E$72*$B$50) | F106: =$B$72*$C$72*F93*F94*$B$45*(1-$E$72*$B$50) | G106: =$B$72*$C$72*G93*G94*$B$45*(1-$E$72*$B$50) | H106: =$B$72*$C$72*H93*H94*$B$45*(1-$E$72*$B$50) | I106: =$B$72*$C$72*I93*I94*$B$45*(1-$E$72*$B$50) | J106: =$B$72*$C$72*J93*J94*$B$45*(1-$E$72*$B$50) | ... L106: =$B$72*$C$72*L93*L94*$B$45*(1-$E$72*$B$50)
A107: Chiffre d'affaires total | B107: =SUM(C107:L107) | C107: =C99+C100+C101+C102+C103+C104+C105+C106 | D107: =D99+D100+D101+D102+D103+D104+D105+D106 | E107: =E99+E100+E101+E102+E103+E104+E105+E106 | F107: =F99+F100+F101+F102+F103+F104+F105+F106 | G107: =G99+G100+G101+G102+G103+G104+G105+G106 | H107: =H99+H100+H101+H102+H103+H104+H105+H106 | I107: =I99+I100+I101+I102+I103+I104+I105+I106 | J107: =J99+J100+J101+J102+J103+J104+J105+J106 | ... L107: =L99+L100+L101+L102+L103+L104+L105+L106
A108: dont équestre | B108: =SUM(C108:L108) | C108: =C99*$F$65+C100*$F$66+C101*$F$67+C102*$F$68+C103*$F$69+C104*$F$70+C105*$F$71+C106*$F$72 | D108: =D99*$F$65+D100*$F$66+D101*$F$67+D102*$F$68+D103*$F$69+D104*$F$70+D105*$F$71+D106*$F$72 | E108: =E99*$F$65+E100*$F$66+E101*$F$67+E102*$F$68+E103*$F$69+E104*$F$70+E105*$F$71+E106*$F$72 | F108: =F99*$F$65+F100*$F$66+F101*$F$67+F102*$F$68+F103*$F$69+F104*$F$70+F105*$F$71+F106*$F$72 | G108: =G99*$F$65+G100*$F$66+G101*$F$67+G102*$F$68+G103*$F$69+G104*$F$70+G105*$F$71+G106*$F$72 | H108: =H99*$F$65+H100*$F$66+H101*$F$67+H102*$F$68+H103*$F$69+H104*$F$70+H105*$F$71+H106*$F$72 | I108: =I99*$F$65+I100*$F$66+I101*$F$67+I102*$F$68+I103*$F$69+I104*$F$70+I105*$F$71+I106*$F$72 | J108: =J99*$F$65+J100*$F$66+J101*$F$67+J102*$F$68+J103*$F$69+J104*$F$70+J105*$F$71+J106*$F$72 | ... L108: =L99*$F$65+L100*$F$66+L101*$F$67+L102*$F$68+L103*$F$69+L104*$F$70+L105*$F$71+L106*$F$72
A109: Part équestre du CA | C109: =IF(C107=0,0,C108/C107) | D109: =IF(D107=0,0,D108/D107) | E109: =IF(E107=0,0,E108/E107) | F109: =IF(F107=0,0,F108/F107) | G109: =IF(G107=0,0,G108/G107) | H109: =IF(H107=0,0,H108/H107) | I109: =IF(I107=0,0,I108/I107) | J109: =IF(J107=0,0,J108/J107) | ... L109: =IF(L107=0,0,L108/L107)
A110: Coûts variables | B110: =SUM(C110:L110) | C110: =-(C99*$D$65+C100*$D$66+C101*$D$67+C102*$D$68+C103*$D$69+C104*$D$70+C105*$D$71+C106*$D$72) | D110: =-(D99*$D$65+D100*$D$66+D101*$D$67+D102*$D$68+D103*$D$69+D104*$D$70+D105*$D$71+D106*$D$72) | E110: =-(E99*$D$65+E100*$D$66+E101*$D$67+E102*$D$68+E103*$D$69+E104*$D$70+E105*$D$71+E106*$D$72) | F110: =-(F99*$D$65+F100*$D$66+F101*$D$67+F102*$D$68+F103*$D$69+F104*$D$70+F105*$D$71+F106*$D$72) | G110: =-(G99*$D$65+G100*$D$66+G101*$D$67+G102*$D$68+G103*$D$69+G104*$D$70+G105*$D$71+G106*$D$72) | H110: =-(H99*$D$65+H100*$D$66+H101*$D$67+H102*$D$68+H103*$D$69+H104*$D$70+H105*$D$71+H106*$D$72) | I110: =-(I99*$D$65+I100*$D$66+I101*$D$67+I102*$D$68+I103*$D$69+I104*$D$70+I105*$D$71+I106*$D$72) | J110: =-(J99*$D$65+J100*$D$66+J101*$D$67+J102*$D$68+J103*$D$69+J104*$D$70+J105*$D$71+J106*$D$72) | ... L110: =-(L99*$D$65+L100*$D$66+L101*$D$67+L102*$D$68+L103*$D$69+L104*$D$70+L105*$D$71+L106*$D$72)
A111: Marge sur coûts variables | B111: =SUM(C111:L111) | C111: =C107+C110 | D111: =D107+D110 | E111: =E107+E110 | F111: =F107+F110 | G111: =G107+G110 | H111: =H107+H110 | I111: =I107+I110 | J111: =J107+J110 | ... L111: =L107+L110
...

Sheet B_frugal
A1: B frugal — fondateur non rémunéré, même financement bancaire que B central
A2: Cellules jaunes/bleues = hypothèses éditables. Tout le reste est calculé. Colonne D (bloc hypothèses) = source ou statut (ESTIMATION = non vérifiée).
A4: 1. Calendrier, acquisition et travaux
A5: Année d'acquisition des murs (1 = immédiate) | B5: 1 | C5: année | D5: Achat immédiat (2027)
A6: Année d'ouverture commerciale (avant stress) | B6: 2 | C6: année | D6: Année 1 = travaux ; EST
A7: Prix d'acquisition | B7: 2500000 | C7: € | D7: PL : médiane de 19 annonces de châteaux ≥ 30 ha (quartiles 1,29-3,07 M€) [A1]
A8: Frais d'acquisition (droits + notaire) | B8: 0.075 | C8: % | D8: EST : DMTO ≈ 5,8-6,3 % + notaire ≈ 1,2 % ; vente SAFER : frais 8,4 % TTC mais exonération de droits possible [A1, PL]
A9: Part du prix affectable au bâti (amortissable) | B9: 0.55 | C9: % | D9: EST
A10: Travaux de restauration / mise aux normes | B10: 500000 | C10: € | D10: EST sans visite : top 5 des biens équipés 0,1-0,7 M€ [A1]
A11: Investissements équestres (boxes, carrière, manège…) | B11: 150000 | C11: € | D11: EST : remise à niveau d'écuries existantes (une écurie neuve de 30 box coûterait 0,78-0,83 M€ HT [A3 H20])
A12: Investissements événementiel / hébergement | B12: 250000 | C12: € | D12: EST : mise aux normes d'une salle existante + aménagement du gîte (neuf : 570 k€-1,24 M€ [A4 §13.2])
A13: Répartition travaux : année d'acquisition | B13: 0.6 | C13: % | D13: EST
A14: Répartition travaux : année +1 | B14: 0.3 | C14: % | D14: EST
A15: Répartition travaux : année +2 | B15: 0.1 | C15: % | D15: EST
A16: Gros entretien patrimonial annuel (% prix+travaux) | B16: 0.018 | C16: % | D16: ≈ 41 k€/an sur (bâti + travaux) : Demeure Historique ≥ 40 k€/an hors restauration (PL [A8]) ; Barnes 20-80 k€/an [A4 §11] ; démarre en année d'acquisition + 3
... A20: Loyer de la partie privée payé par le fondateur (hors CA d'exploitation) | B20: 0 | C20: € | D20: Correction audit M1 : aucun loyer privé compté — le logis doit être détenu à part (SCI à l'IR, hors taxe 235 ter C [A6]) et payé par le fondateur personnellement
A22: 2. Financement
A23: Apport du fondateur (année 1) | B23: 1000000 | C23: € | D23: Scénario d'apport S3 (hypothèse ; apport réel inconnu)
A24: Fonds propres apportés à l'acquisition (investisseurs ou holding) | B24: 0 | C24: € | D24: Aucun investisseur
A25: Ces fonds propres viennent-ils de la holding du fondateur ? (1/0) | B25: 0
A26: Subventions (non acquises : 0 par défaut) | B26: 0 | C26: € | D26: Aucune subvention considérée comme acquise
A27: Dette bancaire (année d'acquisition) | B27: 2400000 | C27: € | D27: NON ACQUIS — montage 1 [A2] : prêt hypothécaire 20 ans ; LTV ≈ 70 %, jugée trop élevée par l'agent 2
A28: Taux de la dette bancaire | B28: 0.04 | C28: % | D28: PL : nouveaux crédits PME 3,64 % (FBF, 06/2026) ; EX : 3,66 % (BdF, 08/2026) ; retenu 4,0 % [A2]
A29: Durée dette bancaire | B29: 20 | C29: ans | D29: A2 (Bpifrance : 15 ans avec hypothèque, PL)
A30: Différé d'amortissement (dans la durée) | B30: 1 | C30: ans | D30: EST
A31: Crédit-vendeur | B31: 0 | C31: €
A32: Taux crédit-vendeur | B32: 0.03 | C32: % | D32: EST
A33: Durée crédit-vendeur (amortissable) | B33: 12 | C33: ans | D33: EST
A34: Obligations / quasi-fonds propres (in fine) | B34: 0 | C34: €
A35: Coupon annuel des obligations | B35: 0.07 | C35: % | D35: PL : obligations Château Fontenay 7 % [A2]
A36: Année de remboursement des obligations | B36: 6 | C36: année | D36: EST
A37: Part de capital supplémentaire accordée au fondateur pour son travail (sweat equity) | B37: 0 | C37: % | D37: Fondateur seul
A38: Droits de vote du fondateur | B38: 1 | C38: %
A39: Réserve de liquidité cible | B39: 150000 | C39: € | D39: EST
A40: TRI minimal exigé par des investisseurs extérieurs | B40: 0.06 | C40: % | D40: EST : rendement minimal d'un investisseur en fonds propres illiquide (Anaxago affiche 8,7 % net, PL [A2])
A41: Le dirigeant est-il rémunéré par le domaine ? (1/0) | B41: 0 | D41: Variante frugale : fondateur non rémunéré par le domaine
A42: Part du capital du fondateur (calculée : apports au prorata + prime d'industrie, plafonnée à 100 %) | B42: =MIN(1,($B$23+$B$24*$B$25)/MAX(1,$B$23+$B$24)+$B$37)
A44: 3. Paramètres de stress (neutres = 100 % / 0)
A45: Multiplicateur de chiffre d'affaires | B45: 1 | C45: % | D45: neutre
A46: Multiplicateur du budget travaux | B46: 1 | C46: % | D46: neutre
A47: Retard d'ouverture | B47: 0 | C47: ans | D47: neutre
A48: Hausse du taux bancaire (points) | B48: 0 | C48: % | D48: neutre
A49: Part des fonds investisseurs non versée | B49: 0 | C49: % | D49: neutre
A50: Part des événements annulés | B50: 0 | C50: % | D50: neutre
A52: 4. Exploitation — hypothèses générales
A53: Montée en charge : 1re année d'exploitation | B53: 0.5 | C53: % | D53: A4 : mariages 40/70/100 % ; gîte 50/80/100 %
A54: Montée en charge : 2e année | B54: 0.8 | C54: % | D54: EST
A55: Montée en charge : 3e année | B55: 1 | C55: % | D55: EST
A56: Indexation annuelle des prix | B56: 0.02 | C56: % | D56: EST
A57: Inflation annuelle des charges | B57: 0.02 | C57: % | D57: EST : indexation identique aux prix (correction audit, biais pessimiste retiré)
A58: BFR en % du CA (négatif = acomptes clients) | B58: -0.03 | C58: % | D58: Acomptes (mariages, pensions payées d'avance) — EST
A59: Taux normal d'IS | B59: 0.25 | C59: % | D59: PL : IS 25 % au-delà de 42 500 € [A6]
A60: Taux réduit d'IS (PME, jusqu'au seuil) | B60: 0.15 | C60: % | D60: PL : 15 % jusqu'à 42 500 € (PME) [A6]
A61: Seuil du taux réduit d'IS | B61: 42500 | C61: € | D61: PL [A6]
A63: 5. Lignes de revenus (à maturité, euros de l'année d'ouverture)
A64: Libellé | B64: Volume | C64: Prix unitaire | D64: Coût var. % | E64: Événement ? | F64: Équestre ? | G64: Unité / source
A65: Pension box premium (places occupées) | B65: 22 | C65: 5118 | D65: 0.23 | E65: 0 | F65: 1 | G65: PL : 450 € TTC/mois = 3e quartile hors IdF (médiane 375 €, 10 % des offres ≥ 520 €) [A3, recalcul A8] → 426,5 € HT à TVA 5,5 % ; 24 box × 92 % ; coûts directs 1 200 €/an EST
A66: Pension au pré (places occupées) | B66: 23 | C66: 2502 | D66: 0.245 | E66: 0 | F66: 1 | G66: PL : 220 € TTC/mois (médianes 200-240 €) → 208,5 € HT [A3 H3] ; 25 places × 92 % ; coûts 613 €/an [A3 §4]
A67: Pension retraite / convalescence (places occupées) | B67: 9 | C67: 2100 | D67: 0.24 | E67: 0 | F67: 1 | G67: PL : 210 € TTC/mois, TVA 20 % → 175 € HT [A3 H4] ; 10 places × 90 %
A68: Mariages (location du lieu + hébergement 15 couchages) | B68: 12 | C68: 4197 | D68: 0.43 | E68: 1 | F68: 0 | G68: PL : médiane 3 400 € TTC location (17 châteaux) + 1 500 € TTC hébergement → 4 197 € HT [A4 §13.1] ; 12/an EST ; coût variable 1 450 € + 8 %
A69: Gîte 15 couchages hors mariages (nuits) | B69: 92 | C69: 450 | D69: 0.45 | E69: 0 | F69: 0 | G69: PL : fourchettes de prix [A4 §4.2] ; 92 nuits EST (occupation annuelle ≈ 33 % observée en Normandie hors saison) [A4 §4.3]
A70: Séminaires à la journée (jours) | B70: 12 | C70: 800 | D70: 0.19 | E70: 1 | F70: 0 | G70: PL : salle 1 000 €/jour (Feugerets) ; 800 € HT retenu [A4 §3]
A71: Tournages / shootings (jours) | B71: 3 | C71: 2000 | D71: 0.15 | E71: 1 | F71: 0 | G71: PL : 1 500-4 000 €/jour [A4 §5] ; fréquence EST
A72: Fermage / vente d'herbe (ha) | B72: 10 | C72: 150 | D72: 0 | E72: 0 | F72: 0 | G72: PL : arrêtés Orne/Calvados 2026-27 : 50-268 €/ha [A4 §8.2]
A74: 6. Charges fixes annuelles (euros de l'année d'ouverture)
A75: Libellé | B75: Montant/an | C75: Dès l'acq. (1) / dès l'ouverture (0) | G75: Source / statut
A76: Taxe foncière | B76: 6000 | C76: 1 | G76: EX : 2,6-4,0 k€ sur 3 annonces ; EST 4-8 k€ [A4 §11]
A77: Assurance multirisque château | B77: 12000 | C77: 1 | G77: Correction audit : courtier spécialisé 15-30 k€ (fiabilité moyenne), annonces ≥ 2,5 k€ [A4 §11, A8] ; EST 12 k€
A78: Énergie (chauffage partiel, électricité, eau) | B78: 20000 | C78: 1 | G78: PL : Meung, Louvignies ; EX annonce Montluçon 18-25 k€ [A1, A4 §11] ; EST
A79: Jardinier à mi-temps / prestataire | B79: 14000 | C79: 1 | G79: Variante frugale — EST
A80: Divers (abonnements, petit matériel, véhicule, honoraires) | B80: 8000 | C80: 1 | G80: EST
A81: Soigneurs (2 ETP chargés) | B81: 60000 | C81: 0 | G81: Variante frugale : le fondateur est le 3e ETP de l'écurie (non payé)
A82: Autres charges de structure équestres (entretien installations, matériel, assurance RC, énergie écuries) | B82: 30000 | C82: 0 | G82: Calibré pour un EBE équestre ≈ 37 % (réf. pension hébergement 36-38 %, PL [A3 H10])
A83: Coûts fixes mariages (coordination, nettoyage, publicité) | B83: 11000 | C83: 0 | G83: EST [A4 §13.1]
A84: Coûts fixes du gîte | B84: 4400 | C84: 0 | G84: EST [A4 §13.1]
A85: Commercial, site, salons | B85: 12000 | C85: 0 | G85: EST
A86: Comptabilité, juridique, banque, logiciels | B86: 12000 | C86: 0 | G86: EST
A88: 7. Calcul sur 10 ans
A89: Année | B89: Total / réf. | C89: 1 | D89: 2 | E89: 3 | F89: 4 | G89: 5 | H89: 6 | I89: 7 | J89: 8 | K89: 9 | L89: 10
A90: Année d'ouverture effective | C90: =$B$6+$B$47 | D90: =$B$6+$B$47 | E90: =$B$6+$B$47 | F90: =$B$6+$B$47 | G90: =$B$6+$B$47 | H90: =$B$6+$B$47 | I90: =$B$6+$B$47 | J90: =$B$6+$B$47 | ... L90: =$B$6+$B$47
A91: Rang de l'année d'exploitation | C91: =MAX(0,C$89-C90+1) | D91: =MAX(0,D$89-D90+1) | E91: =MAX(0,E$89-E90+1) | F91: =MAX(0,F$89-F90+1) | G91: =MAX(0,G$89-G90+1) | H91: =MAX(0,H$89-H90+1) | I91: =MAX(0,I$89-I90+1) | J91: =MAX(0,J$89-J90+1) | ... L91: =MAX(0,L$89-L90+1)
A92: Coefficient de montée en charge | C92: =IF(C91=0,0,IF(C91=1,$B$53,IF(C91=2,$B$54,IF(C91=3,$B$55,1)))) | D92: =IF(D91=0,0,IF(D91=1,$B$53,IF(D91=2,$B$54,IF(D91=3,$B$55,1)))) | E92: =IF(E91=0,0,IF(E91=1,$B$53,IF(E91=2,$B$54,IF(E91=3,$B$55,1)))) | F92: =IF(F91=0,0,IF(F91=1,$B$53,IF(F91=2,$B$54,IF(F91=3,$B$55,1)))) | G92: =IF(G91=0,0,IF(G91=1,$B$53,IF(G91=2,$B$54,IF(G91=3,$B$55,1)))) | H92: =IF(H91=0,0,IF(H91=1,$B$53,IF(H91=2,$B$54,IF(H91=3,$B$55,1)))) | I92: =IF(I91=0,0,IF(I91=1,$B$53,IF(I91=2,$B$54,IF(I91=3,$B$55,1)))) | J92: =IF(J91=0,0,IF(J91=1,$B$53,IF(J91=2,$B$54,IF(J91=3,$B$55,1)))) | ... L92: =IF(L91=0,0,IF(L91=1,$B$53,IF(L91=2,$B$54,IF(L91=3,$B$55,1))))
A93: Indice prix | C93: =(1+$B$56)^(C$89-1) | D93: =(1+$B$56)^(D$89-1) | E93: =(1+$B$56)^(E$89-1) | F93: =(1+$B$56)^(F$89-1) | G93: =(1+$B$56)^(G$89-1) | H93: =(1+$B$56)^(H$89-1) | I93: =(1+$B$56)^(I$89-1) | J93: =(1+$B$56)^(J$89-1) | ... L93: =(1+$B$56)^(L$89-1)
A94: Indice charges | C94: =(1+$B$57)^(C$89-1) | D94: =(1+$B$57)^(D$89-1) | E94: =(1+$B$57)^(E$89-1) | F94: =(1+$B$57)^(F$89-1) | G94: =(1+$B$57)^(G$89-1) | H94: =(1+$B$57)^(H$89-1) | I94: =(1+$B$57)^(I$89-1) | J94: =(1+$B$57)^(J$89-1) | ... L94: =(1+$B$57)^(L$89-1)
A95: Murs détenus (1/0) | C95: =IF(C$89>=$B$5,1,0) | D95: =IF(D$89>=$B$5,1,0) | E95: =IF(E$89>=$B$5,1,0) | F95: =IF(F$89>=$B$5,1,0) | G95: =IF(G$89>=$B$5,1,0) | H95: =IF(H$89>=$B$5,1,0) | I95: =IF(I$89>=$B$5,1,0) | J95: =IF(J$89>=$B$5,1,0) | ... L95: =IF(L$89>=$B$5,1,0)
A97: Compte de résultat
A98: Pension box premium (places occupées) | B98: =SUM(C98:L98) | C98: =$B$65*$C$65*C92*C93*$B$45*(1-$E$65*$B$50) | D98: =$B$65*$C$65*D92*D93*$B$45*(1-$E$65*$B$50) | E98: =$B$65*$C$65*E92*E93*$B$45*(1-$E$65*$B$50) | F98: =$B$65*$C$65*F92*F93*$B$45*(1-$E$65*$B$50) | G98: =$B$65*$C$65*G92*G93*$B$45*(1-$E$65*$B$50) | H98: =$B$65*$C$65*H92*H93*$B$45*(1-$E$65*$B$50) | I98: =$B$65*$C$65*I92*I93*$B$45*(1-$E$65*$B$50) | J98: =$B$65*$C$65*J92*J93*$B$45*(1-$E$65*$B$50) | ... L98: =$B$65*$C$65*L92*L93*$B$45*(1-$E$65*$B$50)
A99: Pension au pré (places occupées) | B99: =SUM(C99:L99) | C99: =$B$66*$C$66*C92*C93*$B$45*(1-$E$66*$B$50) | D99: =$B$66*$C$66*D92*D93*$B$45*(1-$E$66*$B$50) | E99: =$B$66*$C$66*E92*E93*$B$45*(1-$E$66*$B$50) | F99: =$B$66*$C$66*F92*F93*$B$45*(1-$E$66*$B$50) | G99: =$B$66*$C$66*G92*G93*$B$45*(1-$E$66*$B$50) | H99: =$B$66*$C$66*H92*H93*$B$45*(1-$E$66*$B$50) | I99: =$B$66*$C$66*I92*I93*$B$45*(1-$E$66*$B$50) | J99: =$B$66*$C$66*J92*J93*$B$45*(1-$E$66*$B$50) | ... L99: =$B$66*$C$66*L92*L93*$B$45*(1-$E$66*$B$50)
A100: Pension retraite / convalescence (places occupées) | B100: =SUM(C100:L100) | C100: =$B$67*$C$67*C92*C93*$B$45*(1-$E$67*$B$50) | D100: =$B$67*$C$67*D92*D93*$B$45*(1-$E$67*$B$50) | E100: =$B$67*$C$67*E92*E93*$B$45*(1-$E$67*$B$50) | F100: =$B$67*$C$67*F92*F93*$B$45*(1-$E$67*$B$50) | G100: =$B$67*$C$67*G92*G93*$B$45*(1-$E$67*$B$50) | H100: =$B$67*$C$67*H92*H93*$B$45*(1-$E$67*$B$50) | I100: =$B$67*$C$67*I92*I93*$B$45*(1-$E$67*$B$50) | J100: =$B$67*$C$67*J92*J93*$B$45*(1-$E$67*$B$50) | ... L100: =$B$67*$C$67*L92*L93*$B$45*(1-$E$67*$B$50)
